Workbook
Name Annual_Rtns: INDIRECT([1]Analytics!$G$1)
Name Holidays: [2]Holidays!$A$3:$A$2001
Name IQ_CH: 110000
Name IQ_CQ: 5000
Name IQ_CY: 10000
Name IQ_DAILY: 500000
Name IQ_FH: 100000
Name IQ_FQ: 500
Name IQ_FY: 1000
Name IQ_LTM: 2000
Name IQ_MONTH: 15000
Name IQ_NTM: 6000
Name IQ_WEEK: 50000
Name IQ_YTD: 3000
Name max_alloc: [3]Parameters!$O$2
Name MaxLeverage: #REF!
Name OLE_LINK1: 'Daily Returns'!#REF!
Name OLE_LINK1: Dashboard!#REF!
Name OLE_LINK1: 'Index Levels'!#REF!
Name OLE_LINK1: 'Index Levels - Full'!#REF!
Name OLE_LINK2: Dashboard!#REF!
Name OLE_LINK3: Dashboard!#REF!
Name TargetVol: #REF!
Name USAHolidays: [4]Holidays!$A:$A
Name vol_budget: [3]Parameters!$O$3

Sheet __FDSCACHE__
B1: This sheet contains FactSet XML data for use with this workbook's =FDS codes. Modifying the worksheet's contents may damage the workbook's =FDS functionality.

Sheet Dashboard
F2: S&P DJI Multi-Asset Indices
F3: spdji-multiasset@spglobal.com
B4: Dashboard: S&P 500® FC TCA 0.50% Decrement Index (USD) ER
F5: =MAX('Index Levels'!A:A) -> 46234
A8: Performance Summary
C17: Return
A18: Index | C18: 1-Month | D18: QTD | E18: YTD | F18: 12-Month
A19: Index
A20: =Performance!B6 -> S&P 500 FC TCA 0.50% Decrement Index (USD) ER | C20: =Performance!C6 -> -0.018640114 | D20: =Performance!D6 -> -0.018640114 | E20: =Performance!E6 -> 0.0096897624 | F20: =Performance!F6 -> -0.0099443632
A21: =Performance!B7 -> S&P 500 | C21: =Performance!C7 -> -0.0012846572 | D21: =Performance!D7 -> -0.0012846572 | E21: =Performance!E7 -> 0.09410849 | F21: =Performance!F7 -> 0.18145743
A38: Asset Class Exposures
D39: =F5 -> 46234 | F39: (End of Month)
D40: Equities | F40: Total
A41: S&P 500 FC TCA 0.50% Decrement Index (USD) ER | D41: ='Asset Class Exposures'!K19 -> 0.61270038 | F41: =D41 -> 0.61270038
D42: 12-Month Average
D43: Equities | F43: Total
A44: S&P 500 FC TCA 0.50% Decrement Index (USD) ER | D44: ='Asset Class Exposures'!F23 -> 0.9339335 | F44: =D44 -> 0.9339335
A61: The S&P 500 FC TCA Indices are based in part on “Fast Convergence” methodology developed and licensed by Bank of America Corporation and BofA Securities, Inc. (“BofA”). The index was developed in collaboration with BofA
A62: For Institutional Use Only; Not for use with Retail Investors
A63: Source: S&P Dow Jones Indices LLC. Data as of Jul. 31, 2026. Index performance based on returns in USD. Charts and tables are provided for illustrative purposes. Past performance is no guarantee of future results. All data prior to index launch date is back-tested hypothetical data. Chart is provided for illustrative purposes and reflects hypothetical historical performance. Please see the Performance Disclosure for more information regarding the inherent limitations associated with back-tested performance. https://legal.spindices.com/legal/trademarknotices-and-disclaimers/general-disclaimer-and-performance-disclosures

Sheet Disclaimer
A1: Dashboard: S&P 500 FC TCA 0.50% Decrement Index (USD) ER | E1: =Dashboard!F5 -> 46234
A5: GENERAL DISCLAIMER
A47: CONTACT US: | C47: New York | D47: +1.212.438.7354
B48: index_services@spglobal.com | C48: Toronto | D48: +1.212.438.7354
C49: London | D49: +44.20.7176.8888
C50: Tokyo | D50: +813.4550.8564
C51: Beijing | D51: +86.10.6569.2770
C52: Sydney | D52: +61.2.9255.9802
C53: Mumbai | D53: +91.22.272.5312
C54: Dubai | D54: +971.(0)4.371.7131
B56: www.spglobal.com/spdji

Sheet Performance
B2: Start Date | C2: =EOMONTH(C3,-1) -> 46203 | D2: {=_xlfn.IFS(MONTH(D3)=1,EOMONTH(D3,-1),MONTH(D3)=2,EOMONTH(D3,-2),MONTH(D3)=3,EOMONTH(D3,-3),MONTH(D3)=4,EOMONTH(D3,-1),MONTH(D3)=5,EOMONTH(D3,-2),MONTH(D3)=6,EOMONTH(D3,-3),MONTH(D3)=7,EOMONTH(D3,-1),MONTH(D3)=8,EOMONTH(D3,-2),MONTH(D3)=9,EOMONTH(D3,-3),MONTH(D3)=10,EOMONTH(D3,-1),MONTH(D3)=11,EOMONTH(D3,-2),MONTH(D3)=12,EOMONTH(D3,-3))} -> 46203 | E2: =DATE(YEAR(E3)-1,12,31) -> 46022 | F2: =EOMONTH(F3,-12) -> 45869
B3: End Date | C3: {=INDEX('Index Levels'!A3:A1048576,COUNT('Index Levels'!A3:A1048576),0)} -> 46234 | D3: =$C$3 -> 46234 | E3: =$C$3 -> 46234 | F3: =$C$3 -> 46234
C5: 1 Month | D5: QTD | E5: YTD | F5: 12 Month
B6: ='Index Levels - Full'!B1 -> S&P 500 FC TCA 0.50% Decrement Index (USD) ER | C6: =INDEX('Index Levels - Full'!$B:$B,MATCH(Performance!C$3,'Index Levels - Full'!$A:$A,0))/INDEX('Index Levels - Full'!$B:$B,MATCH(Performance!C$2,'Index Levels - Full'!$A:$A,0))-1 -> -0.018640114 | D6: =INDEX('Index Levels - Full'!$B:$B,MATCH(Performance!D$3,'Index Levels - Full'!$A:$A,0))/INDEX('Index Levels - Full'!$B:$B,MATCH(Performance!D$2,'Index Levels - Full'!$A:$A,0))-1 -> -0.018640114 | E6: =INDEX('Index Levels - Full'!$B:$B,MATCH(Performance!E$3,'Index Levels - Full'!$A:$A,0))/INDEX('Index Levels - Full'!$B:$B,MATCH(Performance!E$2,'Index Levels - Full'!$A:$A,0))-1 -> 0.0096897624 | F6: =INDEX('Index Levels - Full'!$B:$B,MATCH(Performance!F$3,'Index Levels - Full'!$A:$A,0))/INDEX('Index Levels - Full'!$B:$B,MATCH(Performance!F$2,'Index Levels - Full'!$A:$A,0))-1 -> -0.0099443632
B7: ='Index Levels - Full'!C1 -> S&P 500 | C7: =INDEX('Index Levels - Full'!$C:$C,MATCH(Performance!C$3,'Index Levels - Full'!$A:$A,0))/INDEX('Index Levels - Full'!$C:$C,MATCH(Performance!C$2,'Index Levels - Full'!$A:$A,0))-1 -> -0.0012846572 | D7: =INDEX('Index Levels - Full'!$C:$C,MATCH(Performance!D$3,'Index Levels - Full'!$A:$A,0))/INDEX('Index Levels - Full'!$C:$C,MATCH(Performance!D$2,'Index Levels - Full'!$A:$A,0))-1 -> -0.0012846572 | E7: =INDEX('Index Levels - Full'!$C:$C,MATCH(Performance!E$3,'Index Levels - Full'!$A:$A,0))/INDEX('Index Levels - Full'!$C:$C,MATCH(Performance!E$2,'Index Levels - Full'!$A:$A,0))-1 -> 0.09410849 | F7: =INDEX('Index Levels - Full'!$C:$C,MATCH(Performance!F$3,'Index Levels - Full'!$A:$A,0))/INDEX('Index Levels - Full'!$C:$C,MATCH(Performance!F$2,'Index Levels - Full'!$A:$A,0))-1 -> 0.18145743

Sheet 12 Month Rolling Return
B2: Start Date | C2: =EOMONTH(C3,-12) -> 45535 | D2: =EOMONTH(D3,-12) -> 45565 | E2: =EOMONTH(E3,-12) -> 45596 | F2: =EOMONTH(F3,-12) -> 45626 | G2: =EOMONTH(G3,-12) -> 45657 | H2: =EOMONTH(H3,-12) -> 45688 | I2: =EOMONTH(I3,-12) -> 45716 | J2: =EOMONTH(J3,-12) -> 45747 | ... N2: =EOMONTH(N3,-12) -> 45869
B3: End Date | C3: =EOMONTH(D3,-1) -> 45900 | D3: =EOMONTH(E3,-1) -> 45930 | E3: =EOMONTH(F3,-1) -> 45961 | F3: =EOMONTH(G3,-1) -> 45991 | G3: =EOMONTH(H3,-1) -> 46022 | H3: =EOMONTH(I3,-1) -> 46053 | I3: =EOMONTH(J3,-1) -> 46081 | J3: =EOMONTH(K3,-1) -> 46112 | ... M3: =EOMONTH(N3,-1) -> 46203 | N3: {=INDEX('Index Levels'!A3:A1048576,COUNT('Index Levels'!A3:A1048576),0)} -> 46234
C5: =TEXT(C3,"mmm")&". "&TEXT(C3,"yyyy") -> Aug. 2025 | D5: =TEXT(D3,"mmm")&". "&TEXT(D3,"yyyy") -> Sep. 2025 | E5: =TEXT(E3,"mmm")&". "&TEXT(E3,"yyyy") -> Oct. 2025 | F5: =TEXT(F3,"mmm")&". "&TEXT(F3,"yyyy") -> Nov. 2025 | G5: =TEXT(G3,"mmm")&". "&TEXT(G3,"yyyy") -> Dec. 2025 | H5: =TEXT(H3,"mmm")&". "&TEXT(H3,"yyyy") -> Jan. 2026 | I5: =TEXT(I3,"mmm")&". "&TEXT(I3,"yyyy") -> Feb. 2026 | J5: =TEXT(J3,"mmm")&". "&TEXT(J3,"yyyy") -> Mar. 2026 | ... N5: =TEXT(N3,"mmm")&". "&TEXT(N3,"yyyy") -> Jul. 2026
B6: S&P 500 FC TCA 0.50% Decrement Index ER | C6: =INDEX('Index Levels - Full'!$B:$B,MATCH('12 Month Rolling Return'!C$3,'Index Levels - Full'!$A:$A,0))/INDEX('Index Levels - Full'!$B:$B,MATCH('12 Month Rolling Return'!C$2,'Index Levels - Full'!$A:$A,0))-1 -> 0.0077591245 | D6: =INDEX('Index Levels - Full'!$B:$B,MATCH('12 Month Rolling Return'!D$3,'Index Levels - Full'!$A:$A,0))/INDEX('Index Levels - Full'!$B:$B,MATCH('12 Month Rolling Return'!D$2,'Index Levels - Full'!$A:$A,0))-1 -> 0.032831679 | E6: =INDEX('Index Levels - Full'!$B:$B,MATCH('12 Month Rolling Return'!E$3,'Index Levels - Full'!$A:$A,0))/INDEX('Index Levels - Full'!$B:$B,MATCH('12 Month Rolling Return'!E$2,'Index Levels - Full'!$A:$A,0))-1 -> 0.051304028 | F6: =INDEX('Index Levels - Full'!$B:$B,MATCH('12 Month Rolling Return'!F$3,'Index Levels - Full'!$A:$A,0))/INDEX('Index Levels - Full'!$B:$B,MATCH('12 Month Rolling Return'!F$2,'Index Levels - Full'!$A:$A,0))-1 -> -0.02144005 | G6: =INDEX('Index Levels - Full'!$B:$B,MATCH('12 Month Rolling Return'!G$3,'Index Levels - Full'!$A:$A,0))/INDEX('Index Levels - Full'!$B:$B,MATCH('12 Month Rolling Return'!G$2,'Index Levels - Full'!$A:$A,0))-1 -> 0.0159889 | H6: =INDEX('Index Levels - Full'!$B:$B,MATCH('12 Month Rolling Return'!H$3,'Index Levels - Full'!$A:$A,0))/INDEX('Index Levels - Full'!$B:$B,MATCH('12 Month Rolling Return'!H$2,'Index Levels - Full'!$A:$A,0))-1 -> 0.0097088733 | I6: =INDEX('Index Levels - Full'!$B:$B,MATCH('12 Month Rolling Return'!I$3,'Index Levels - Full'!$A:$A,0))/INDEX('Index Levels - Full'!$B:$B,MATCH('12 Month Rolling Return'!I$2,'Index Levels - Full'!$A:$A,0))-1 -> 0.021996138 | J6: =INDEX('Index Levels - Full'!$B:$B,MATCH('12 Month Rolling Return'!J$3,'Index Levels - Full'!$A:$A,0))/INDEX('Index Levels - Full'!$B:$B,MATCH('12 Month Rolling Return'!J$2,'Index Levels - Full'!$A:$A,0))-1 -> 0.0081577105 | ... N6: =INDEX('Index Levels - Full'!$B:$B,MATCH('12 Month Rolling Return'!N$3,'Index Levels - Full'!$A:$A,0))/INDEX('Index Levels - Full'!$B:$B,MATCH('12 Month Rolling Return'!N$2,'Index Levels - Full'!$A:$A,0))-1 -> -0.0099443632
B7: S&P 500 | C7: =INDEX('Index Levels - Full'!$C:$C,MATCH('12 Month Rolling Return'!C$3,'Index Levels - Full'!$A:$A,0))/INDEX('Index Levels - Full'!$C:$C,MATCH('12 Month Rolling Return'!C$2,'Index Levels - Full'!$A:$A,0))-1 -> 0.14373377 | D7: =INDEX('Index Levels - Full'!$C:$C,MATCH('12 Month Rolling Return'!D$3,'Index Levels - Full'!$A:$A,0))/INDEX('Index Levels - Full'!$C:$C,MATCH('12 Month Rolling Return'!D$2,'Index Levels - Full'!$A:$A,0))-1 -> 0.16069008 | E7: =INDEX('Index Levels - Full'!$C:$C,MATCH('12 Month Rolling Return'!E$3,'Index Levels - Full'!$A:$A,0))/INDEX('Index Levels - Full'!$C:$C,MATCH('12 Month Rolling Return'!E$2,'Index Levels - Full'!$A:$A,0))-1 -> 0.198889 | F7: =INDEX('Index Levels - Full'!$C:$C,MATCH('12 Month Rolling Return'!F$3,'Index Levels - Full'!$A:$A,0))/INDEX('Index Levels - Full'!$C:$C,MATCH('12 Month Rolling Return'!F$2,'Index Levels - Full'!$A:$A,0))-1 -> 0.13538643 | G7: =INDEX('Index Levels - Full'!$C:$C,MATCH('12 Month Rolling Return'!G$3,'Index Levels - Full'!$A:$A,0))/INDEX('Index Levels - Full'!$C:$C,MATCH('12 Month Rolling Return'!G$2,'Index Levels - Full'!$A:$A,0))-1 -> 0.16387931 | H7: =INDEX('Index Levels - Full'!$C:$C,MATCH('12 Month Rolling Return'!H$3,'Index Levels - Full'!$A:$A,0))/INDEX('Index Levels - Full'!$C:$C,MATCH('12 Month Rolling Return'!H$2,'Index Levels - Full'!$A:$A,0))-1 -> 0.14874592 | I7: =INDEX('Index Levels - Full'!$C:$C,MATCH('12 Month Rolling Return'!I$3,'Index Levels - Full'!$A:$A,0))/INDEX('Index Levels - Full'!$C:$C,MATCH('12 Month Rolling Return'!I$2,'Index Levels - Full'!$A:$A,0))-1 -> 0.15523939 | J7: =INDEX('Index Levels - Full'!$C:$C,MATCH('12 Month Rolling Return'!J$3,'Index Levels - Full'!$A:$A,0))/INDEX('Index Levels - Full'!$C:$C,MATCH('12 Month Rolling Return'!J$2,'Index Levels - Full'!$A:$A,0))-1 -> 0.16334441 | ... N7: =INDEX('Index Levels - Full'!$C:$C,MATCH('12 Month Rolling Return'!N$3,'Index Levels - Full'!$A:$A,0))/INDEX('Index Levels - Full'!$C:$C,MATCH('12 Month Rolling Return'!N$2,'Index Levels - Full'!$A:$A,0))-1 -> 0.18145743

Sheet Asset Class Exposures
A1: File Location | B1: S:\IndexReports\Standard\Options\500 FC TCA Index
F2: Monthly Average | J2: End of Month
A3: Date | B3: Month | C3: Equity | D3: Cash | G3: Equities | H3: Cash | L3: Equities | M3: Cash
A4: ='Index Levels'!A1092 -> 45870 | B4: =TEXT(MONTH(A4)*29,"mmmm") -> August | C4: 0.24362167 | D4: =IF(C4>1,0,1-C4) -> 0.75637833 | F4: {=_xlfn.IFS(F5="August","July",F5="July","June",F5="June","May",F5="May","April",F5="April","March",F5="March","February",F5="February","January",F5="January","December",F5="December","November",F5="November","October",F5="October","September",F5="September","August")} -> August | G4: =AVERAGEIF($B:$B,"*"&$F4&"*",$C:$C) -> 0.99814855 | H4: =AVERAGEIF($B:$B,"*"&$F4&"*",D:D) -> 0.10578172 | I4: =RANK(G4,$G$4:$G$15,0) -> 5 | J4: {=MAX(IF(B:B=F4,A:A))} -> 45898 | K4: =TEXT(J4,"mmm")&". "&YEAR(J4) -> Aug. 2025 | L4: =INDEX(C:C,MATCH($J4,$A:$A,0)) -> 1.3152958 | M4: =INDEX(D:D,MATCH($J4,$A:$A,0)) -> 0
A5: ='Index Levels'!A1093 -> 45873 | B5: =TEXT(MONTH(A5)*29,"mmmm") -> August | C5: 0.6104369 | D5: =IF(C5>1,0,1-C5) -> 0.3895631 | F5: {=_xlfn.IFS(F6="August","July",F6="July","June",F6="June","May",F6="May","April",F6="April","March",F6="March","February",F6="February","January",F6="January","December",F6="December","November",F6="November","October",F6="October","September",F6="September","August")} -> September | G5: =AVERAGEIF($B:$B,"*"&$F5&"*",$C:$C) -> 1.2666352 | H5: =AVERAGEIF($B:$B,"*"&$F5&"*",D:D) -> 0.0071530144 | I5: =RANK(G5,$G$4:$G$15,0) -> 1 | J5: {=MAX(IF(B:B=F5,A:A))} -> 45930 | K5: =TEXT(J5,"mmm")&". "&YEAR(J5) -> Sep. 2025 | L5: =INDEX(C:C,MATCH($J5,$A:$A,0)) -> 1.2323654 | M5: =INDEX(D:D,MATCH($J5,$A:$A,0)) -> 0
A6: ='Index Levels'!A1094 -> 45874 | B6: =TEXT(MONTH(A6)*29,"mmmm") -> August | C6: 0.63740794 | D6: =IF(C6>1,0,1-C6) -> 0.36259206 | F6: {=_xlfn.IFS(F7="August","July",F7="July","June",F7="June","May",F7="May","April",F7="April","March",F7="March","February",F7="February","January",F7="January","December",F7="December","November",F7="November","October",F7="October","September",F7="September","August")} -> October | G6: =AVERAGEIF($B:$B,"*"&$F6&"*",$C:$C) -> 0.95211856 | H6: =AVERAGEIF($B:$B,"*"&$F6&"*",D:D) -> 0.19884201 | I6: =RANK(G6,$G$4:$G$15,0) -> 7 | J6: {=MAX(IF(B:B=F6,A:A))} -> 45961 | K6: =TEXT(J6,"mmm")&". "&YEAR(J6) -> Oct. 2025 | L6: =INDEX(C:C,MATCH($J6,$A:$A,0)) -> 0.96994943 | M6: =INDEX(D:D,MATCH($J6,$A:$A,0)) -> 0.030050571
A7: ='Index Levels'!A1095 -> 45875 | B7: =TEXT(MONTH(A7)*29,"mmmm") -> August | C7: 0.75477355 | D7: =IF(C7>1,0,1-C7) -> 0.24522645 | F7: {=_xlfn.IFS(F8="August","July",F8="July","June",F8="June","May",F8="May","April",F8="April","March",F8="March","February",F8="February","January",F8="January","December",F8="December","November",F8="November","October",F8="October","September",F8="September","August")} -> November | G7: =AVERAGEIF($B:$B,"*"&$F7&"*",$C:$C) -> 0.73762359 | H7: =AVERAGEIF($B:$B,"*"&$F7&"*",D:D) -> 0.26961676 | I7: =RANK(G7,$G$4:$G$15,0) -> 11 | J7: {=MAX(IF(B:B=F7,A:A))} -> 45989 | K7: =TEXT(J7,"mmm")&". "&YEAR(J7) -> Nov. 2025 | L7: =INDEX(C:C,MATCH($J7,$A:$A,0)) -> 0.6083575 | M7: =INDEX(D:D,MATCH($J7,$A:$A,0)) -> 0.3916425
A8: ='Index Levels'!A1096 -> 45876 | B8: =TEXT(MONTH(A8)*29,"mmmm") -> August | C8: 0.83435202 | D8: =IF(C8>1,0,1-C8) -> 0.16564798 | F8: {=_xlfn.IFS(F9="August","July",F9="July","June",F9="June","May",F9="May","April",F9="April","March",F9="March","February",F9="February","January",F9="January","December",F9="December","November",F9="November","October",F9="October","September",F9="September","August")} -> December | G8: =AVERAGEIF($B:$B,"*"&$F8&"*",$C:$C) -> 1.1437936 | H8: =AVERAGEIF($B:$B,"*"&$F8&"*",D:D) -> 0.047761848 | I8: =RANK(G8,$G$4:$G$15,0) -> 2 | J8: {=MAX(IF(B:B=F8,A:A))} -> 46022 | K8: =TEXT(J8,"mmm")&". "&YEAR(J8) -> Dec. 2025 | L8: =INDEX(C:C,MATCH($J8,$A:$A,0)) -> 1.6929365 | M8: =INDEX(D:D,MATCH($J8,$A:$A,0)) -> 0
A9: ='Index Levels'!A1097 -> 45877 | B9: =TEXT(MONTH(A9)*29,"mmmm") -> August | C9: 0.84458892 | D9: =IF(C9>1,0,1-C9) -> 0.15541108 | F9: {=_xlfn.IFS(F10="August","July",F10="July","June",F10="June","May",F10="May","April",F10="April","March",F10="March","February",F10="February","January",F10="January","December",F10="December","November",F10="November","October",F10="October","September",F10="September","August")} -> January | G9: =AVERAGEIF($B:$B,"*"&$F9&"*",$C:$C) -> 1.1061201 | H9: =AVERAGEIF($B:$B,"*"&$F9&"*",D:D) -> 0.12020686 | I9: =RANK(G9,$G$4:$G$15,0) -> 3 | J9: {=MAX(IF(B:B=F9,A:A))} -> 46052 | K9: =TEXT(J9,"mmm")&". "&YEAR(J9) -> Jan. 2026 | L9: =INDEX(C:C,MATCH($J9,$A:$A,0)) -> 0.84336196 | M9: =INDEX(D:D,MATCH($J9,$A:$A,0)) -> 0.15663804
A10: ='Index Levels'!A1098 -> 45880 | B10: =TEXT(MONTH(A10)*29,"mmmm") -> August | C10: 0.96316342 | D10: =IF(C10>1,0,1-C10) -> 0.036836578 | F10: {=_xlfn.IFS(F11="August","July",F11="July","June",F11="June","May",F11="May","April",F11="April","March",F11="March","February",F11="February","January",F11="January","December",F11="December","November",F11="November","October",F11="October","September",F11="September","August")} -> February | G10: =AVERAGEIF($B:$B,"*"&$F10&"*",$C:$C) -> 0.82410586 | H10: =AVERAGEIF($B:$B,"*"&$F10&"*",D:D) -> 0.17589414 | I10: =RANK(G10,$G$4:$G$15,0) -> 8 | J10: {=MAX(IF(B:B=F10,A:A))} -> 46080 | K10: =TEXT(J10,"mmm")&". "&YEAR(J10) -> Feb. 2026 | L10: =INDEX(C:C,MATCH($J10,$A:$A,0)) -> 0.92257802 | M10: =INDEX(D:D,MATCH($J10,$A:$A,0)) -> 0.077421979
A11: ='Index Levels'!A1099 -> 45881 | B11: =TEXT(MONTH(A11)*29,"mmmm") -> August | C11: 0.98772617 | D11: =IF(C11>1,0,1-C11) -> 0.012273828 | F11: {=_xlfn.IFS(F12="August","July",F12="July","June",F12="June","May",F12="May","April",F12="April","March",F12="March","February",F12="February","January",F12="January","December",F12="December","November",F12="November","October",F12="October","September",F12="September","August")} -> March | G11: =AVERAGEIF($B:$B,"*"&$F11&"*",$C:$C) -> 0.59937049 | H11: =AVERAGEIF($B:$B,"*"&$F11&"*",D:D) -> 0.40062951 | I11: =RANK(G11,$G$4:$G$15,0) -> 12 | J11: {=MAX(IF(B:B=F11,A:A))} -> 46112 | K11: =TEXT(J11,"mmm")&". "&YEAR(J11) -> Mar. 2026 | L11: =INDEX(C:C,MATCH($J11,$A:$A,0)) -> 0.76354447 | M11: =INDEX(D:D,MATCH($J11,$A:$A,0)) -> 0.23645553
A12: ='Index Levels'!A1100 -> 45882 | B12: =TEXT(MONTH(A12)*29,"mmmm") -> August | C12: 1.0005434 | D12: =IF(C12>1,0,1-C12) -> 0 | F12: {=_xlfn.IFS(F13="August","July",F13="July","June",F13="June","May",F13="May","April",F13="April","March",F13="March","February",F13="February","January",F13="January","December",F13="December","November",F13="November","October",F13="October","September",F13="September","August")} -> April | G12: =AVERAGEIF($B:$B,"*"&$F12&"*",$C:$C) -> 0.77753211 | H12: =AVERAGEIF($B:$B,"*"&$F12&"*",D:D) -> 0.23772129 | I12: =RANK(G12,$G$4:$G$15,0) -> 9 | J12: {=MAX(IF(B:B=F12,A:A))} -> 46142 | K12: =TEXT(J12,"mmm")&". "&YEAR(J12) -> Apr. 2026 | L12: =INDEX(C:C,MATCH($J12,$A:$A,0)) -> 1.1692219 | M12: =INDEX(D:D,MATCH($J12,$A:$A,0)) -> 0
A13: ='Index Levels'!A1101 -> 45883 | B13: =TEXT(MONTH(A13)*29,"mmmm") -> August | C13: 1.0970355 | D13: =IF(C13>1,0,1-C13) -> 0 | F13: {=_xlfn.IFS(F14="August","July",F14="July","June",F14="June","May",F14="May","April",F14="April","March",F14="March","February",F14="February","January",F14="January","December",F14="December","November",F14="November","October",F14="October","September",F14="September","August")} -> May | G13: =AVERAGEIF($B:$B,"*"&$F13&"*",$C:$C) -> 1.0482862 | H13: =AVERAGEIF($B:$B,"*"&$F13&"*",D:D) -> 0.035560257 | I13: =RANK(G13,$G$4:$G$15,0) -> 4 | J13: {=MAX(IF(B:B=F13,A:A))} -> 46171 | K13: =TEXT(J13,"mmm")&". "&YEAR(J13) -> May. 2026 | L13: =INDEX(C:C,MATCH($J13,$A:$A,0)) -> 1.1055989 | M13: =INDEX(D:D,MATCH($J13,$A:$A,0)) -> 0
A14: ='Index Levels'!A1102 -> 45884 | B14: =TEXT(MONTH(A14)*29,"mmmm") -> August | C14: 1.2102612 | D14: =IF(C14>1,0,1-C14) -> 0 | F14: {=_xlfn.IFS(F15="August","July",F15="July","June",F15="June","May",F15="May","April",F15="April","March",F15="March","February",F15="February","January",F15="January","December",F15="December","November",F15="November","October",F15="October","September",F15="September","August")} -> June | G14: =AVERAGEIF($B:$B,"*"&$F14&"*",$C:$C) -> 0.76795396 | H14: =AVERAGEIF($B:$B,"*"&$F14&"*",D:D) -> 0.28484901 | I14: =RANK(G14,$G$4:$G$15,0) -> 10 | J14: {=MAX(IF(B:B=F14,A:A))} -> 46203 | K14: =TEXT(J14,"mmm")&". "&YEAR(J14) -> Jun. 2026 | L14: =INDEX(C:C,MATCH($J14,$A:$A,0)) -> 0.81344901 | M14: =INDEX(D:D,MATCH($J14,$A:$A,0)) -> 0.18655099
A15: ='Index Levels'!A1103 -> 45887 | B15: =TEXT(MONTH(A15)*29,"mmmm") -> August | C15: 1.3436339 | D15: =IF(C15>1,0,1-C15) -> 0 | F15: {=TEXT(INDEX(A4:A290,COUNTA(A4:A290)),"mmmm")} -> July | G15: =AVERAGEIF($B:$B,"*"&$F15&"*",$C:$C) -> 0.97237815 | H15: =AVERAGEIF($B:$B,"*"&$F15&"*",D:D) -> 0.095170869 | I15: =RANK(G15,$G$4:$G$15,0) -> 6 | J15: {=MAX(IF(B:B=F15,A:A))} -> 46234 | K15: =TEXT(J15,"mmm")&". "&YEAR(J15) -> Jul. 2026 | L15: =INDEX(C:C,MATCH($J15,$A:$A,0)) -> 0.61270038 | M15: =INDEX(D:D,MATCH($J15,$A:$A,0)) -> 0.38729962
A16: ='Index Levels'!A1104 -> 45888 | B16: =TEXT(MONTH(A16)*29,"mmmm") -> August | C16: 1.4398855 | D16: =IF(C16>1,0,1-C16) -> 0
A17: ='Index Levels'!A1105 -> 45889 | B17: =TEXT(MONTH(A17)*29,"mmmm") -> August | C17: 1.2026383 | D17: =IF(C17>1,0,1-C17) -> 0 | F17: {=TEXT((INDEX(A4:A99291,COUNT(A4:A99291),0)),"mmmm")&" "&YEAR(INDEX(A4:A99291,COUNT(A4:A99291),0))&" Average"} -> July 2026 Average | J17: {=TEXT((INDEX(A4:A99291,COUNT(A4:A99291),0)),"mmmm")&" "&YEAR(INDEX(A4:A99291,COUNT(A4:A99291),0))&" End of Month"} -> July 2026 End of Month
A18: ='Index Levels'!A1106 -> 45890 | B18: =TEXT(MONTH(A18)*29,"mmmm") -> August | C18: 1.2007173 | D18: =IF(C18>1,0,1-C18) -> 0 | F18: Equities | G18: Cash | H18: Total | K18: Equities | L18: Cash | M18: Total
A19: ='Index Levels'!A1107 -> 45891 | B19: =TEXT(MONTH(A19)*29,"mmmm") -> August | C19: 0.97478729 | D19: =IF(C19>1,0,1-C19) -> 0.025212709 | F19: =G15 -> 0.97237815 | G19: =H15 -> 0.095170869 | H19: =SUM(F19:G19) -> 1.067549 | K19: {=INDEX(C4:C9479,COUNT(C4:C99479),0)} -> 0.61270038 | L19: {=INDEX(D4:D9291,COUNT(D4:D99291),0)} -> 0.38729962 | M19: =SUM(K19:L19) -> 1
A20: ='Index Levels'!A1108 -> 45894 | B20: =TEXT(MONTH(A20)*29,"mmmm") -> August | C20: 0.92772591 | D20: =IF(C20>1,0,1-C20) -> 0.072274095
A21: ='Index Levels'!A1109 -> 45895 | B21: =TEXT(MONTH(A21)*29,"mmmm") -> August | C21: 1.0227554 | D21: =IF(C21>1,0,1-C21) -> 0 | F21: 12 Month Average
A22: ='Index Levels'!A1110 -> 45896 | B22: =TEXT(MONTH(A22)*29,"mmmm") -> August | C22: 1.1214596 | D22: =IF(C22>1,0,1-C22) -> 0 | F22: Equities | G22: Cash | H22: Total
A23: ='Index Levels'!A1111 -> 45897 | B23: =TEXT(MONTH(A23)*29,"mmmm") -> August | C23: 1.2283097 | D23: =IF(C23>1,0,1-C23) -> 0 | F23: =AVERAGE(C:C) -> 0.9339335 | G23: =AVERAGE(D:D) -> 0.16516889 | H23: =SUM(F23:G23) -> 1.0991024
A24: ='Index Levels'!A1112 -> 45898 | B24: =TEXT(MONTH(A24)*29,"mmmm") -> August | C24: 1.3152958 | D24: =IF(C24>1,0,1-C24) -> 0
A25: ='Index Levels'!A1113 -> 45902 | B25: =TEXT(MONTH(A25)*29,"mmmm") -> September | C25: 0.99164558 | D25: =IF(C25>1,0,1-C25) -> 0.0083544167
A26: ='Index Levels'!A1114 -> 45903 | B26: =TEXT(MONTH(A26)*29,"mmmm") -> September | C26: 1.0759459 | D26: =IF(C26>1,0,1-C26) -> 0
A27: ='Index Levels'!A1115 -> 45904 | B27: =TEXT(MONTH(A27)*29,"mmmm") -> September | C27: 1.192364 | D27: =IF(C27>1,0,1-C27) -> 0
A28: ='Index Levels'!A1116 -> 45905 | B28: =TEXT(MONTH(A28)*29,"mmmm") -> September | C28: 0.86822376 | D28: =IF(C28>1,0,1-C28) -> 0.13177624
A29: ='Index Levels'!A1117 -> 45908 | B29: =TEXT(MONTH(A29)*29,"mmmm") -> September | C29: 1.0394381 | D29: =IF(C29>1,0,1-C29) -> 0
A30: ='Index Levels'!A1118 -> 45909 | B30: =TEXT(MONTH(A30)*29,"mmmm") -> September | C30: 1.1551657 | D30: =IF(C30>1,0,1-C30) -> 0
A31: ='Index Levels'!A1119 -> 45910 | B31: =TEXT(MONTH(A31)*29,"mmmm") -> September | C31: 1.1871527 | D31: =IF(C31>1,0,1-C31) -> 0
A32: ='Index Levels'!A1120 -> 45911 | B32: =TEXT(MONTH(A32)*29,"mmmm") -> September | C32: 1.237496 | D32: =IF(C32>1,0,1-C32) -> 0
A33: ='Index Levels'!A1121 -> 45912 | B33: =TEXT(MONTH(A33)*29,"mmmm") -> September | C33: 1.3763869 | D33: =IF(C33>1,0,1-C33) -> 0
A34: ='Index Levels'!A1122 -> 45915 | B34: =TEXT(MONTH(A34)*29,"mmmm") -> September | C34: 1.4569549 | D34: =IF(C34>1,0,1-C34) -> 0
A35: ='Index Levels'!A1123 -> 45916 | B35: =TEXT(MONTH(A35)*29,"mmmm") -> September | C35: 1.6065856 | D35: =IF(C35>1,0,1-C35) -> 0
... A148: ='Index Levels'!A1236 -> 46080 | B148: =TEXT(MONTH(A148)*29,"mmmm") -> February | C148: 0.92257802 | D148: =IF(C148>1,0,1-C148) -> 0.077421979
A149: ='Index Levels'!A1237 -> 46083 | B149: =TEXT(MONTH(A149)*29,"mmmm") -> March | C149: 0.91765681 | D149: =IF(C149>1,0,1-C149) -> 0.082343189 | E149: X
A150: ='Index Levels'!A1238 -> 46084 | B150: =TEXT(MONTH(A150)*29,"mmmm") -> March | C150: 0.44346359 | D150: =IF(C150>1,0,1-C150) -> 0.55653641
A151: ='Index Levels'!A1239 -> 46085 | B151: =TEXT(MONTH(A151)*29,"mmmm") -> March | C151: 0.52390754 | D151: =IF(C151>1,0,1-C151) -> 0.47609246
A152: ='Index Levels'!A1240 -> 46086 | B152: =TEXT(MONTH(A152)*29,"mmmm") -> March | C152: 0.58838243 | D152: =IF(C152>1,0,1-C152) -> 0.41161757
A153: ='Index Levels'!A1241 -> 46087 | B153: =TEXT(MONTH(A153)*29,"mmmm") -> March | C153: 0.4981286 | D153: =IF(C153>1,0,1-C153) -> 0.5018714
A154: ='Index Levels'!A1242 -> 46090 | B154: =TEXT(MONTH(A154)*29,"mmmm") -> March | C154: 0.46500735 | D154: =IF(C154>1,0,1-C154) -> 0.53499265
A155: ='Index Levels'!A1243 -> 46091 | B155: =TEXT(MONTH(A155)*29,"mmmm") -> March | C155: 0.50909884 | D155: =IF(C155>1,0,1-C155) -> 0.49090116
A156: ='Index Levels'!A1244 -> 46092 | B156: =TEXT(MONTH(A156)*29,"mmmm") -> March | C156: 0.57672335 | D156: =IF(C156>1,0,1-C156) -> 0.42327665
A157: ='Index Levels'!A1245 -> 46093 | B157: =TEXT(MONTH(A157)*29,"mmmm") -> March | C157: 0.58805927 | D157: =IF(C157>1,0,1-C157) -> 0.41194073
A158: ='Index Levels'!A1246 -> 46094 | B158: =TEXT(MONTH(A158)*29,"mmmm") -> March | C158: 0.58613247 | D158: =IF(C158>1,0,1-C158) -> 0.41386753
A159: ='Index Levels'!A1247 -> 46097 | B159: =TEXT(MONTH(A159)*29,"mmmm") -> March | C159: 0.57590358 | D159: =IF(C159>1,0,1-C159) -> 0.42409642
A160: ='Index Levels'!A1248 -> 46098 | B160: =TEXT(MONTH(A160)*29,"mmmm") -> March | C160: 0.60816731 | D160: =IF(C160>1,0,1-C160) -> 0.39183269
A161: ='Index Levels'!A1249 -> 46099 | B161: =TEXT(MONTH(A161)*29,"mmmm") -> March | C161: 0.6736688 | D161: =IF(C161>1,0,1-C161) -> 0.3263312
... A254: ='Index Levels'!A1342 -> 46234 | B254: =TEXT(MONTH(A254)*29,"mmmm") -> July | C254: 0.61270038 | D254: =IF(C254>1,0,1-C254) -> 0.38729962

Sheet Calc 
A1: DATE | B1: ISROLLDATE | C1: IS_PARTIAL | D1: RIC | E1: CYCLE | F1: FutTWAP | G1: ROLL_IN | H1: ROLL_IN_TWAP | I1: SPXFP | J1: FFR | K1: 500TR | L1: SPTWAP | M1: EQ_intraday | N1: ROLL_FUT_IDX_LAST | O1: VIX_LAG | P1: SPTR_TWAP | Q1: ES_TWAP_RATIO | R1: ROLL_FUT_IDX | S1: FINAN_FEE | T1: FINAN_FEE_FOR_CALC | U1: EQ_VOL_ST | V1: EQ_VOL_LT | W1: EQ_VOL | X1: Delta | Y1: DAILY_120D_VOL | Z1: DAILY_120D_VOL_FOR_VAF | AA1: INTRADAY_21D_VOL | AB1: PARTICIPATION | AC1: FCVHL_RET | AD1: FCVHL_1 | AE1: FCVHL | AF1: INDEX_LEVEL | AG1: INDEX_LEVEL_1 | AH1: DATE_FOR_FT | AI1: EQ_LOGRET | AJ1: EQ_LAST_LVL | AK1: EQ_LVL_FOR_STRIKE | AL1: Call_strike | AM1: Put_strike | AN1: ITTE | AO1: ITTE_DELTA | AP1: VOL_FOR_DELTA | AQ1: Delta_Call | AR1: Delta_Put | AS1: DAILY_120D_VAF | AT1: INTRADAY_21D_VAF | AU1: VAF | AV1: TARGET_PARTICIPATION
A2: 45566 | B2: FALSE | C2: FALSE | D2: 2024ESZ | E2: C1 | F2: 5765.175 | H2: 0 | I2: 488.06552 | J2: 0.0483 | K2: 12490.872 | L2: 12501.521 | M2: 461.24197 | O2: 16.73 | P2: 12501.521 | Q2: 0.99171944 | T2: 0.057439256 | U2: 0.11296447 | V2: 0.10977371 | W2: 0.11296447 | X2: -0.069264198 | Z2: 0.10749124 | AA2: 0.11725005 | AB2: 1.2353789 | AC2: -0.010589899 | AD2: 491.5148 | AE2: 486.30971 | AG2: 491.5148 | AI2: 6.3056296e-05 | AK2: 464.91918 | AL2: 471.89297 | AM2: 457.94539 | AN2: 0.0010058422 | AO2: 0.00084049824 | AP2: 0.1673 | AQ2: 1.2729114e-06 | AR2: -0.069265471 | AS2: 1.0612841 | AT2: 1.0181423 | AU2: 1.0181423 | AV2: 1.2353789
A3: 45566 | B3: FALSE | C3: FALSE | D3: 2024ESZ | E3: C2 | F3: 5752.7875 | H3: 0 | I3: 488.06552 | J3: 0.0483 | K3: 12490.872 | L3: 12474.495 | M3: 460.24485 | O3: 16.73 | P3: 12474.495 | Q3: 0.99785132 | T3: 0.057439256 | U3: 0.11176324 | V3: 0.10925481 | W3: 0.11176324 | X3: -0.12417458 | Z3: 0.10749124 | AA3: 0.11760953 | AB3: 0.98537893 | AC3: -0.0026956631 | AD3: 491.5148 | AE3: 484.99878 | AG3: 491.5148 | AI3: 4.6835757e-06 | AK3: 464.91918 | AL3: 471.89297 | AM3: 457.94539 | AN3: 0.00084049824 | AO3: 0.00067515432 | AP3: 0.1673 | AQ3: 4.533019e-09 | AR3: -0.12417458 | AS3: 1.0612841 | AT3: 0.98004385 | AU3: 0.98004385 | AV3: 0.92786425
A4: 45566 | B4: FALSE | C4: FALSE | D4: 2024ESZ | E4: C3 | F4: 5761.05 | H4: 0 | I4: 488.06552 | J4: 0.0483 | K4: 12490.872 | L4: 12491.565 | M4: 460.87464 | O4: 16.73 | P4: 12491.565 | Q4: 1.0014363 | T4: 0.057439256 | U4: 0.1092679 | V4: 0.10806235 | W4: 0.1092679 | X4: -0.04553021 | Z4: 0.10749124 | AA4: 0.11690751 | AB4: 0.88446146 | AC4: 0.001338293 | AD4: 491.5148 | AE4: 485.64785 | AG4: 491.5148 | AI4: 1.8699377e-06 | AK4: 464.91918 | AL4: 471.89297 | AM4: 457.94539 | AN4: 0.00067515432 | AO4: 0.00050981041 | AP4: 0.1673 | AQ4: 2.0183454e-10 | AR4: -0.04553021 | AS4: 1.0612841 | AT4: 0.97678142 | AU4: 0.97678142 | AV4: 0.88446146
A5: 45566 | B5: FALSE | C5: FALSE | D5: 2024ESZ | E5: C4 | F5: 5748.3 | H5: 0 | I5: 488.06552 | J5: 0.0483 | K5: 12490.872 | L5: 12464.412 | M5: 459.87284 | O5: 16.73 | P5: 12464.412 | Q5: 0.99778686 | T5: 0.057439256 | U5: 0.10827876 | V5: 0.1075999 | W5: 0.10827876 | X5: -0.087835308 | Z5: 0.10749124 | AA5: 0.1170209 | AB5: 0.98297203 | AC5: -0.001932411 | AD5: 491.5148 | AE5: 484.70938 | AG5: 491.5148 | AI5: 4.7352926e-06 | AK5: 464.91918 | AL5: 471.89297 | AM5: 457.94539 | AN5: 0.00050981041 | AO5: 0.00034446649 | AP5: 0.1673 | AQ5: 4.8590437e-17 | AR5: -0.087835308 | AS5: 1.0612841 | AT5: 0.98313313 | AU5: 0.98313313 | AV5: 0.98297203
A6: 45566 | B6: FALSE | C6: FALSE | D6: 2024ESZ | E6: C5 | F6: 5754.775 | H6: 0 | I6: 488.06552 | J6: 0.0483 | K6: 12490.872 | L6: 12475.933 | M6: 460.2979 | O6: 16.73 | P6: 12475.933 | Q6: 1.0011264 | T6: 0.057439256 | U6: 0.10540955 | V6: 0.10618652 | W6: 0.10618652 | X6: -0.011024312 | Z6: 0.10749124 | AA6: 0.11697493 | AB6: 0.94919887 | AC6: 0.00090519509 | AD6: 491.5148 | AE6: 485.14814 | AG6: 491.5148 | AI6: 8.5356283e-07 | AK6: 464.91918 | AL6: 471.89297 | AM6: 457.94539 | AN6: 0.00034446649 | AO6: 0.00017912257 | AP6: 0.1673 | AQ6: 5.6211893e-29 | AR6: -0.011024312 | AS6: 1.0612841 | AT6: 0.98211254 | AU6: 0.98211254 | AV6: 0.94919887
A7: 45566 | B7: FALSE | C7: FALSE | D7: 2024ESZ | E7: C6 | F7: 5777.175 | H7: 0 | I7: 488.06552 | J7: 0.0483 | K7: 12490.872 | L7: 12524.803 | M7: 462.10096 | O7: 16.73 | P7: 12524.803 | Q7: 1.0038924 | T7: 0.057439256 | U7: 0.10982793 | V7: 0.10837964 | W7: 0.10982793 | X7: 0 | Z7: 0.10749124 | AA7: 0.11737608 | AB7: 1.0534355 | AC7: 0.003707723 | AD7: 491.5148 | AE7: 486.94693 | AG7: 491.5148 | AI7: 1.5284111e-05 | AK7: 464.91918 | AL7: 471.89297 | AM7: 457.94539 | AN7: 0.00017912257 | AO7: 0 | AP7: 0.1673 | AQ7: 0 | AR7: 0 | AS7: 1.0612841 | AT7: 0.9825266 | AU7: 0.9825266 | AV7: 1.0534355
A8: 45566 | B8: FALSE | C8: FALSE | D8: 2024ESZ | E8: C7 | F8: 5762.15 | G8: usual | H8: 0 | I8: 488.06552 | J8: 0.0483 | K8: 12490.872 | L8: 12493.091 | M8: 460.93095 | N8: 465.13237 | O8: 16.73 | P8: 12493.091 | Q8: 0.99739925 | R8: 465.13237 | S8: 0.067556415 | T8: 0.057439256 | U8: 0.10962971 | V8: 0.10832302 | W8: 0.10962971 | X8: 0 | Y8: 0.108659 | Z8: 0.10749124 | AA8: 0.11634042 | AB8: 1.0250014 | AC8: -0.0026700747 | AD8: 491.5148 | AE8: 485.64675 | AF8: 485.64675 | AG8: 491.5148 | AH8: 45566 | AI8: 6.4269693e-06 | AJ8: 460.93095 | AK8: 464.91918 | AL8: 471.89297 | AM8: 457.94539 | AN8: 0 | AO8: 0.0010058422 | AP8: 0.1673 | AQ8: 0 | AR8: 0 | AS8: 1.0612841 | AT8: 0.97890241 | AU8: 0.97890241 | AV8: 1.0250014
A9: 45567 | B9: FALSE | C9: FALSE | D9: 2024ESZ | E9: C1 | F9: 5741.45 | H9: 0 | I9: 488.10789 | J9: 0.0483 | K9: 12493.354 | L9: 12451.121 | M9: 459.29597 | O9: 19.26 | P9: 12451.121 | Q9: 0.99640759 | T9: 0.067556415 | U9: 0.11240095 | V9: 0.10977281 | W9: 0.11240095 | X9: -0.01859669 | Z9: 0.108659 | AA9: 0.113252 | AB9: 1.0366147 | AC9: -0.0036508465 | AD9: 485.64675 | AE9: 483.87372 | AG9: 485.64675 | AI9: 1.262679e-05 | AK9: 460.93095 | AL9: 467.84491 | AM9: 454.01698 | AN9: 0.0010058422 | AO9: 0.00084049824 | AP9: 0.1926 | AQ9: 0.00048338644 | AR9: -0.019080076 | AS9: 1.0522537 | AT9: 0.98820672 | AU9: 0.98820672 | AV9: 1.0366147
A10: 45567 | B10: FALSE | C10: FALSE | D10: 2024ESZ | E10: C2 | F10: 5761.25 | H10: 0 | I10: 488.10789 | J10: 0.0483 | K10: 12493.354 | L10: 12493.64 | M10: 460.86441 | O10: 19.26 | P10: 12493.64 | Q10: 1.0034486 | T10: 0.067556415 | U10: 0.11448131 | V10: 0.11092153 | W10: 0.11448131 | X10: -3.4487518e-05 | Z10: 0.108659 | AA10: 0.1121222 | AB10: 1.0176728 | AC10: 0.0035380137 | AD10: 485.64675 | AE10: 485.58568 | AG10: 485.64675 | AI10: 1.1621661e-05 | AK10: 460.93095 | AL10: 467.84491 | AM10: 454.01698 | AN10: 0.00084049824 | AO10: 0.00067515432 | AP10: 0.1926 | AQ10: 0.0013436647 | AR10: -0.0013781523 | AS10: 1.0522537 | AT10: 1.0149724 | AU10: 1.0149724 | AV10: 1.0176728
A11: 45567 | B11: FALSE | C11: FALSE | D11: 2024ESZ | E11: C3 | F11: 5769.5 | H11: 0 | I11: 488.10789 | J11: 0.0483 | K11: 12493.354 | L11: 12510.938 | M11: 461.5025 | O11: 19.26 | P11: 12510.938 | Q11: 1.001432 | T11: 0.067556415 | U11: 0.11190274 | V11: 0.10970772 | W11: 0.11190274 | X11: 0.00077066445 | Z11: 0.108659 | AA11: 0.11220792 | AB11: 1.0290546 | AC11: 0.0014078751 | AD11: 485.64675 | AE11: 486.26932 | AG11: 485.64675 | AI11: 1.9143126e-06 | AK11: 460.93095 | AL11: 467.84491 | AM11: 454.01698 | AN11: 0.00067515432 | AO11: 0.00050981041 | AP11: 0.1926 | AQ11: 0.0008547538 | AR11: -8.4089349e-05 | AS11: 1.0522537 | AT11: 1.0244132 | AU11: 1.0244132 | AV11: 1.0290546
A12: 45567 | B12: FALSE | C12: FALSE | D12: 2024ESZ | E12: C4 | F12: 5759.3375 | H12: 0 | I12: 488.10789 | J12: 0.0483 | K12: 12493.354 | L12: 12489.661 | M12: 460.71763 | O12: 19.26 | P12: 12489.661 | Q12: 0.99823858 | T12: 0.067556415 | U12: 0.10989782 | V12: 0.10875675 | W12: 0.10989782 | X12: -1.1806012e-05 | Z12: 0.108659 | AA12: 0.11234531 | AB12: 1.0520375 | AC12: -0.0017523825 | AD12: 485.64675 | AE12: 485.41719 | AG12: 485.64675 | AI12: 2.8972112e-06 | AK12: 460.93095 | AL12: 467.84491 | AM12: 454.01698 | AN12: 0.00050981041 | AO12: 0.00034446649 | AP12: 0.1926 | AQ12: 8.821751e-06 | AR12: -2.0627763e-05 | AS12: 1.0522537 | AT12: 1.0237033 | AU12: 1.0237033 | AV12: 1.0520375
A13: 45567 | B13: FALSE | C13: FALSE | D13: 2024ESZ | E13: C5 | F13: 5759.7 | H13: 0 | I13: 488.10789 | J13: 0.0483 | K13: 12493.354 | L13: 12490.353 | M13: 460.74316 | O13: 19.26 | P13: 12490.353 | Q13: 1.0000629 | T13: 0.067556415 | U13: 0.10655141 | V13: 0.10711374 | W13: 0.10711374 | X13: -4.2784266e-09 | Z13: 0.108659 | AA13: 0.11234128 | AB13: 1.0700374 | AC13: 5.6489016e-05 | AD13: 485.64675 | AE13: 485.44461 | AG13: 485.64675 | AI13: 3.0696356e-09 | AK13: 460.93095 | AL13: 467.84491 | AM13: 454.01698 | AN13: 0.00034446649 | AO13: 0.00017912257 | AP13: 0.1926 | AQ13: 1.4896334e-09 | AR13: -5.76806e-09 | AS13: 1.0522537 | AT13: 1.0225633 | AU13: 1.0225633 | AV13: 1.0700374
A14: 45567 | B14: FALSE | C14: FALSE | D14: 2024ESZ | E14: C6 | F14: 5761.15 | H14: 0 | I14: 488.10789 | J14: 0.0483 | K14: 12493.354 | L14: 12493.73 | M14: 460.86773 | O14: 19.26 | P14: 12493.73 | Q14: 1.0002517 | T14: 0.067556415 | U14: 0.10334286 | V14: 0.10551312 | W14: 0.10551312 | X14: 0 | Z14: 0.108659 | AA14: 0.11229281 | AB14: 1.0978856 | AC14: 0.00028651976 | AD14: 485.64675 | AE14: 485.5837 | AG14: 485.64675 | AI14: 7.3079453e-08 | AK14: 460.93095 | AL14: 467.84491 | AM14: 454.01698 | AN14: 0.00017912257 | AO14: 0 | AP14: 0.1926 | AQ14: 0 | AR14: 0 | AS14: 1.0522537 | AT14: 1.0225968 | AU14: 1.0225968 | AV14: 1.0978856
A15: 45567 | B15: FALSE | C15: FALSE | D15: 2024ESZ | E15: C7 | F15: 5763.025 | G15: usual | H15: 0 | I15: 488.10789 | J15: 0.0483 | K15: 12493.354 | L15: 12498.193 | M15: 461.03236 | N15: 465.203 | O15: 19.26 | P15: 12498.193 | Q15: 1.0003255 | R15: 465.203 | S15: 0.065708187 | T15: 0.067556415 | U15: 0.10026197 | V15: 0.10395085 | W15: 0.10395085 | X15: 0 | Y15: 0.10835016 | Z15: 0.108659 | AA15: 0.11227536 | AB15: 1.1149789 | AC15: 0.00039047647 | AD15: 485.64675 | AE15: 485.77331 | AF15: 485.77331 | AG15: 485.64675 | AH15: 45567 | AI15: 1.2755998e-07 | AJ15: 461.03236 | AK15: 460.93095 | AL15: 467.84491 | AM15: 454.01698 | AN15: 0 | AO15: 0.0010058422 | AP15: 0.1926 | AQ15: 0 | AR15: 0 | AS15: 1.0522537 | AT15: 1.0229992 | AU15: 1.0229992 | AV15: 1.1149789
A16: 45568 | B16: FALSE | C16: FALSE | D16: 2024ESZ | E16: C1 | F16: 5742.8625 | H16: 0 | I16: 487.19697 | J16: 0.0483 | K16: 12472.387 | L16: 12456.027 | M16: 459.39279 | O16: 18.9 | P16: 12456.027 | Q16: 0.9965014 | T16: 0.065708187 | U16: 0.10388778 | V16: 0.10560911 | W16: 0.10560911 | X16: -0.017010178 | Z16: 0.10835016 | AA16: 0.11313166 | AB16: 1.1318961 | AC16: -0.0039807695 | AD16: 485.77331 | AE16: 483.83956 | AG16: 485.77331 | AI16: 1.2692326e-05 | AK16: 461.03236 | AL16: 467.94784 | AM16: 454.11687 | AN16: 0.0010058422 | AO16: 0.00084049824 | AP16: 0.189 | AQ16: 0.00038318241 | AR16: -0.017393361 | AS16: 1.0546591 | AT16: 1.023144 | AU16: 1.023144 | AV16: 1.1318961
A17: 45568 | B17: FALSE | C17: FALSE | D17: 2024ESZ | E17: C2 | F17: 5749.775 | H17: 0 | I17: 487.19697 | J17: 0.0483 | K17: 12472.387 | L17: 12471.329 | M17: 459.95715 | O17: 18.9 | P17: 12471.329 | Q17: 1.0012037 | T17: 0.065708187 | U17: 0.1015118 | V17: 0.10439565 | W17: 0.10439565 | X17: -0.0043710911 | Z17: 0.10835016 | AA17: 0.11316736 | AB17: 1.0842028 | AC17: 0.0013857443 | AD17: 485.77331 | AE17: 484.51004 | AG17: 485.77331 | AI17: 1.5073151e-06 | AK17: 461.03236 | AL17: 467.94784 | AM17: 454.11687 | AN17: 0.00084049824 | AO17: 0.00067515432 | AP17: 0.189 | AQ17: 0.00022853737 | AR17: -0.0045996285 | AS17: 1.0546591 | AT17: 1.0159866 | AU17: 1.0159866 | AV17: 1.0842028
A18: 45568 | B18: FALSE | C18: FALSE | D18: 2024ESZ | E18: C3 | F18: 5758.3375 | H18: 0 | I18: 487.19697 | J18: 0.0483 | K18: 12472.387 | L18: 12488.991 | M18: 460.60855 | O18: 18.9 | P18: 12488.991 | Q18: 1.0014892 | T18: 0.065708187 | U18: 0.099490418 | V18: 0.10333193 | W18: 0.10333193 | X18: -0.00033013713 | Z18: 0.10835016 | AA18: 0.11318775 | AB18: 1.1188578 | AC18: 0.0015319916 | AD18: 485.77331 | AE18: 485.2523 | AG18: 485.77331 | AI18: 2.0028093e-06 | AK18: 461.03236 | AL18: 467.94784 | AM18: 454.11687 | AN18: 0.00067515432 | AO18: 0.00050981041 | AP18: 0.189 | AQ18: 0.00010683624 | AR18: -0.00043697338 | AS18: 1.0546591 | AT18: 1.015686 | AU18: 1.015686 | AV18: 1.1188578
A19: 45568 | B19: FALSE | C19: FALSE | D19: 2024ESZ | E19: C4 | F19: 5736.9 | H19: 0 | I19: 487.19697 | J19: 0.0483 | K19: 12472.387 | L19: 12443.923 | M19: 458.94638 | O19: 18.9 | P19: 12443.923 | Q19: 0.99627714 | T19: 0.065708187 | U19: 0.10338131 | V19: 0.10511322 | W19: 0.10511322 | X19: -0.0012741472 | Z19: 0.10835016 | AA19: 0.11406448 | AB19: 1.1301844 | AC19: -0.0040386633 | AD19: 485.77331 | AE19: 483.29253 | AG19: 485.77331 | AI19: 1.3069273e-05 | AK19: 461.03236 | AL19: 467.94784 | AM19: 454.11687 | AN19: 0.00050981041 | AO19: 0.00034446649 | AP19: 0.189 | AQ19: 1.5520819e-08 | AR19: -0.0012741627 | AS19: 1.0546591 | AT19: 1.0155142 | AU19: 1.0155142 | AV19: 1.1301844
A20: 45568 | B20: FALSE | C20: FALSE | D20: 2024ESZ | E20: C5 | F20: 5739.625 | H20: 0 | I20: 487.19697 | J20: 0.0483 | K20: 12472.387 | L20: 12449.692 | M20: 459.15915 | O20: 18.9 | P20: 12449.692 | Q20: 1.000475 | T20: 0.065708187 | U20: 0.10034525 | V20: 0.10357941 | W20: 0.10357941 | X20: -6.3084444e-06 | Z20: 0.10835016 | AA20: 0.11395635 | AB20: 1.1028867 | AC20: 0.00052122346 | AD20: 485.77331 | AE20: 483.54443 | AG20: 485.77331 | AI20: 2.1482516e-07 | AK20: 461.03236 | AL20: 467.94784 | AM20: 454.11687 | AN20: 0.00034446649 | AO20: 0.00017912257 | AP20: 0.189 | AQ20: 3.3343697e-14 | AR20: -6.3084444e-06 | AS20: 1.0546591 | AT20: 1.0080693 | AU20: 1.0080693 | AV20: 1.1028867
A21: 45568 | B21: FALSE | C21: FALSE | D21: 2024ESZ | E21: C6 | F21: 5741.9875 | H21: 0 | I21: 487.19697 | J21: 0.0483 | K21: 12472.387 | L21: 12454.396 | M21: 459.33264 | O21: 18.9 | P21: 12454.396 | Q21: 1.0004116 | T21: 0.065708187 | U21: 0.097365929 | V21: 0.10205089 | W21: 0.10205089 | X21: 0 | Z21: 0.10835016 | AA21: 0.1138963 | AB21: 1.1202445 | AC21: 0.00041497969 | AD21: 485.77331 | AE21: 483.7451 | AG21: 485.77331 | AI21: 1.4270965e-07 | AK21: 461.03236 | AL21: 467.94784 | AM21: 454.11687 | AN21: 0.00017912257 | AO21: 0 | AP21: 0.189 | AQ21: 0 | AR21: 0 | AS21: 1.0546591 | AT21: 1.0089936 | AU21: 1.0089936 | AV21: 1.1202445
A22: 45568 | B22: FALSE | C22: FALSE | D22: 2024ESZ | E22: C7 | F22: 5745.2 | G22: usual | H22: 0 | I22: 487.19697 | J22: 0.0483 | K22: 12472.387 | L22: 12462.073 | M22: 459.61578 | N22: 463.76413 | O22: 18.9 | P22: 12462.073 | Q22: 1.0005595 | R22: 463.76413 | S22: 0.067394869 | T22: 0.065708187 | U22: 0.094612403 | V22: 0.10060839 | W22: 0.10060839 | X22: 0 | Y22: 0.10698836 | Z22: 0.10835016 | AA22: 0.11379682 | AB22: 1.1376011 | AC22: 0.00068879297 | AD22: 485.77331 | AE22: 484.0783 | AF22: 484.0783 | AG22: 485.77331 | AH22: 45568 | AI22: 3.797258e-07 | AJ22: 459.61578 | AK22: 461.03236 | AL22: 467.94784 | AM22: 454.11687 | AN22: 0 | AO22: 0.0010058422 | AP22: 0.189 | AQ22: 0 | AR22: 0 | AS22: 1.0546591 | AT22: 1.0095062 | AU22: 1.0095062 | AV22: 1.1376011
A23: 45569 | B23: FALSE | C23: FALSE | D23: 2024ESZ | E23: C1 | F23: 5788.8 | H23: 0 | I23: 491.4762 | J23: 0.0483 | K23: 12586.911 | L23: 12559.735 | M23: 463.13162 | O23: 20.49 | P23: 12559.735 | Q23: 1.0075889 | T23: 0.067394869 | U23: 0.12066744 | V23: 0.11354072 | W23: 0.12066744 | X23: 0.11106155 | Z23: 0.10698836 | AA23: 0.1176846 | AB23: 1.154881 | AC23: 0.0086864968 | AD23: 484.0783 | AE23: 488.28324 | AG23: 484.0783 | AI23: 5.8070811e-05 | AK23: 459.61578 | AL23: 466.51001 | AM23: 452.72154 | AN23: 0.0010058422 | AO23: 0.00084049824 | AP23: 0.2049 | AQ23: 0.11112561 | AR23: -6.4060703e-05 | AS23: 1.0651195 | AT23: 1.0103541 | AU23: 1.0103541 | AV23: 1.154881
A24: 45569 | B24: FALSE | C24: FALSE | D24: 2024ESZ | E24: C2 | F24: 5762.9 | H24: 0 | I24: 491.4762 | J24: 0.0483 | K24: 12586.911 | L24: 12506.146 | M24: 461.15556 | O24: 20.49 | P24: 12506.146 | Q24: 0.99552584 | T24: 0.067394869 | U24: 0.12498825 | V24: 0.11607017 | W24: 0.12498825 | X24: 0.014909698 | Z24: 0.10698836 | AA24: 0.1189202 | AB24: 1.0325805 | AC24: -0.0049397955 | AD24: 484.0783 | AE24: 485.87122 | AG24: 484.0783 | AI24: 1.8282967e-05 | AK24: 459.61578 | AL24: 466.51001 | AM24: 452.72154 | AN24: 0.00084049824 | AO24: 0.00067515432 | AP24: 0.2049 | AQ24: 0.015170317 | AR24: -0.00026061863 | AS24: 1.0651195 | AT24: 0.97609749 | AU24: 0.97609749 | AV24: 1.0325805
A25: 45569 | B25: FALSE | C25: FALSE | D25: 2024ESZ | E25: C3 | F25: 5763.475 | H25: 0 | I25: 491.4762 | J25: 0.0483 | K25: 12586.911 | L25: 12506.025 | M25: 461.1511 | O25: 20.49 | P25: 12506.025 | Q25: 1.0000998 | T25: 0.067394869 | U25: 0.12118064 | V25: 0.11431588 | W25: 0.12118064 | X25: 0.0062645337 | Z25: 0.10698836 | AA25: 0.11758696 | AB25: 0.89649052 | AC25: -2.3599464e-05 | AD25: 484.0783 | AE25: 485.85975 | AG25: 484.0783 | AI25: 9.361123e-11 | AK25: 459.61578 | AL25: 466.51001 | AM25: 452.72154 | AN25: 0.00067515432 | AO25: 0.00050981041 | AP25: 0.2049 | AQ25: 0.0062975776 | AR25: -3.3043947e-05 | AS25: 1.0651195 | AT25: 0.96470754 | AU25: 0.96470754 | AV25: 0.89649052
A26: 45569 | B26: FALSE | C26: FALSE | D26: 2024ESZ | E26: C4 | F26: 5781.8125 | H26: 0 | I26: 491.4762 | J26: 0.0483 | K26: 12586.911 | L26: 12545.061 | M26: 462.59053 | O26: 20.49 | P26: 12545.061 | Q26: 1.0031817 | T26: 0.067394869 | U26: 0.12178527 | V26: 0.11484803 | W26: 0.12178527 | X26: 0.013321059 | Z26: 0.10698836 | AA26: 0.11792685 | AB26: 0.9364286 | AC26: 0.0027942897 | AD26: 484.0783 | AE26: 487.21739 | AG26: 484.0783 | AI26: 9.7126602e-06 | AK26: 459.61578 | AL26: 466.51001 | AM26: 452.72154 | AN26: 0.00050981041 | AO26: 0.00034446649 | AP26: 0.2049 | AQ26: 0.013321066 | AR26: -7.0332666e-09 | AS26: 1.0651195 | AT26: 0.97698683 | AU26: 0.97698683 | AV26: 0.9364286
A27: 45569 | B27: FALSE | C27: FALSE | D27: 2024ESZ | E27: C5 | F27: 5780.025 | H27: 0 | I27: 491.4762 | J27: 0.0483 | K27: 12586.911 | L27: 12540.774 | M27: 462.43245 | O27: 20.49 | P27: 12540.774 | Q27: 0.99969084 | T27: 0.067394869 | U27: 0.11812754 | V27: 0.11313952 | W27: 0.11812754 | X27: 0.00068728189 | Z27: 0.10698836 | AA27: 0.11758394 | AB27: 0.92882048 | AC27: -0.00032076479 | AD27: 484.0783 | AE27: 487.06111 | AG27: 484.0783 | AI27: 1.1681802e-07 | AK27: 459.61578 | AL27: 466.51001 | AM27: 452.72154 | AN27: 0.00034446649 | AO27: 0.00017912257 | AP27: 0.2049 | AQ27: 0.00068728189 | AR27: -4.9960036e-15 | AS27: 1.0651195 | AT27: 0.97388422 | AU27: 0.97388422 | AV27: 0.92882048
A28: 45569 | B28: FALSE | C28: FALSE | D28: 2024ESZ | E28: C6 | F28: 5781.25 | H28: 0 | I28: 491.4762 | J28: 0.0483 | K28: 12586.911 | L28: 12542.392 | M28: 462.49211 | O28: 20.49 | P28: 12542.392 | Q28: 1.0002119 | T28: 0.067394869 | U28: 0.11453659 | V28: 0.11143346 | W28: 0.11453659 | X28: 0 | Z28: 0.10698836 | AA28: 0.11755628 | AB28: 0.95114693 | AC28: 0.00011760298 | AD28: 484.0783 | AE28: 487.11839 | AG28: 484.0783 | AI28: 1.6643794e-08 | AK28: 459.61578 | AL28: 466.51001 | AM28: 452.72154 | AN28: 0.00017912257 | AO28: 0 | AP28: 0.2049 | AQ28: 0 | AR28: 0 | AS28: 1.0651195 | AT28: 0.97701436 | AU28: 0.97701436 | AV28: 0.95114693
A29: 45569 | B29: FALSE | C29: FALSE | D29: 2024ESZ | E29: C7 | F29: 5798.675 | G29: usual | H29: 0 | I29: 491.4762 | J29: 0.0483 | K29: 12586.911 | L29: 12580.145 | M29: 463.88423 | N29: 468.08074 | O29: 20.49 | P29: 12580.145 | Q29: 1.0030141 | R29: 468.08074 | S29: 0.064529511 | T29: 0.067394869 | U29: 0.11527175 | V29: 0.11190587 | W29: 0.11527175 | X29: 0 | Y29: 0.10683632 | Z29: 0.10698836 | AA29: 0.11736584 | AB29: 0.98121999 | AC29: 0.0028599753 | AD29: 484.0783 | AE29: 488.51153 | AF29: 488.51153 | AG29: 484.0783 | AH29: 45569 | AI29: 9.0330953e-06 | AJ29: 463.88423 | AK29: 459.61578 | AL29: 466.51001 | AM29: 452.72154 | AN29: 0 | AO29: 0.0010058422 | AP29: 0.2049 | AQ29: 0 | AR29: 0 | AS29: 1.0651195 | AT29: 0.97726604 | AU29: 0.97726604 | AV29: 0.98121999
A30: 45572 | B30: FALSE | C30: FALSE | D30: 2024ESZ | E30: C1 | F30: 5778.125 | H30: 0 | I30: 486.79446 | J30: 0.0483 | K30: 12466.41 | L30: 12540.122 | M30: 462.15895 | O30: 19.21 | P30: 12540.122 | Q30: 0.99645609 | T30: 0.064529511 | U30: 0.11815161 | V30: 0.11349879 | W30: 0.11815161 | X30: -0.019884976 | Z30: 0.10683632 | AA30: 0.11804141 | AB30: 0.97668728 | AC30: -0.0036914613 | AD30: 488.51153 | AE30: 486.70821 | AG30: 488.51153 | AI30: 1.3883979e-05 | AK30: 463.88423 | AL30: 470.84249 | AM30: 456.92596 | AN30: 0.0010058422 | AO30: 0.00084049824 | AP30: 0.1921 | AQ30: 0.00041944182 | AR30: -0.020304418 | AS30: 1.0662728 | AT30: 0.97899522 | AU30: 0.97899522 | AV30: 0.97668728
A31: 45572 | B31: FALSE | C31: FALSE | D31: 2024ESZ | E31: C2 | F31: 5781.35 | H31: 0 | I31: 486.79446 | J31: 0.0483 | K31: 12466.41 | L31: 12546.493 | M31: 462.39375 | O31: 19.21 | P31: 12546.493 | Q31: 1.0005581 | T31: 0.064529511 | U31: 0.11467135 | V31: 0.1118444 | W31: 0.11467135 | X31: -0.0083801148 | Z31: 0.10683632 | AA31: 0.11041427 | AB31: 0.9279469 | AC31: 0.00049133124 | AD31: 488.51153 | AE31: 486.94735 | AG31: 488.51153 | AI31: 2.57983e-07 | AK31: 463.88423 | AL31: 470.84249 | AM31: 456.92596 | AN31: 0.00084049824 | AO31: 0.00067515432 | AP31: 0.1921 | AQ31: 0.00014445166 | AR31: -0.0085245664 | AS31: 1.0662728 | AT31: 0.97283422 | AU31: 0.97283422 | AV31: 0.9279469
A32: 45572 | B32: FALSE | C32: FALSE | D32: 2024ESZ | E32: C3 | F32: 5782.05 | H32: 0 | I32: 486.79446 | J32: 0.0483 | K32: 12466.41 | L32: 12548.843 | M32: 462.48036 | O32: 19.21 | P32: 12548.843 | Q32: 1.0001211 | T32: 0.064529511 | U32: 0.11119469 | V32: 0.11016238 | W32: 0.11119469 | X32: -0.0026346669 | Z32: 0.10683632 | AA32: 0.10969848 | AB32: 1.0309084 | AC32: 0.00016351141 | AD32: 488.51153 | AE32: 487.02697 | AG32: 488.51153 | AI32: 3.507597e-08 | AK32: 463.88423 | AL32: 470.84249 | AM32: 456.92596 | AN32: 0.00067515432 | AO32: 0.00050981041 | AP32: 0.1921 | AQ32: 1.8200714e-05 | AR32: -0.0026528676 | AS32: 1.0662728 | AT32: 1.0383457 | AU32: 1.0383457 | AV32: 1.0309084
A33: 45572 | B33: FALSE | C33: FALSE | D33: 2024ESZ | E33: C4 | F33: 5773.975 | H33: 0 | I33: 486.79446 | J33: 0.0483 | K33: 12466.41 | L33: 12530.608 | M33: 461.80832 | O33: 19.21 | P33: 12530.608 | Q33: 0.99860344 | T33: 0.064529511 | U33: 0.10884033 | V33: 0.10901186 | W33: 0.10901186 | X33: -0.0014278256 | Z33: 0.10683632 | AA33: 0.1098021 | AB33: 1.0797967 | AC33: -0.0015029245 | AD33: 488.51153 | AE33: 486.295 | AG33: 488.51153 | AI33: 2.114636e-06 | AK33: 463.88423 | AL33: 470.84249 | AM33: 456.92596 | AN33: 0.00050981041 | AO33: 0.00034446649 | AP33: 0.1921 | AQ33: 2.7844218e-08 | AR33: -0.0014278534 | AS33: 1.0662728 | AT33: 1.0440666 | AU33: 1.0440666 | AV33: 1.0797967
A34: 45572 | B34: FALSE | C34: FALSE | D34: 2024ESZ | E34: C5 | F34: 5770.025 | H34: 0 | I34: 486.79446 | J34: 0.0483 | K34: 12466.41 | L34: 12522.933 | M34: 461.52546 | O34: 19.21 | P34: 12522.933 | Q34: 0.9993159 | T34: 0.064529511 | U34: 0.1057127 | V34: 0.1074567 | W34: 0.1074567 | X34: -4.869865e-05 | Z34: 0.10683632 | AA34: 0.10984171 | AB34: 1.1005492 | AC34: -0.00066345095 | AD34: 488.51153 | AE34: 485.97237 | AG34: 488.51153 | AI34: 3.7538642e-07 | AK34: 463.88423 | AL34: 470.84249 | AM34: 456.92596 | AN34: 0.00034446649 | AO34: 0.00017912257 | AP34: 0.1921 | AQ34: 3.8479426e-15 | AR34: -4.869865e-05 | AS34: 1.0662728 | AT34: 1.0432427 | AU34: 1.0432427 | AV34: 1.1005492
A35: 45572 | B35: FALSE | C35: FALSE | D35: 2024ESZ | E35: C6 | F35: 5741.225 | H35: 0 | I35: 486.79446 | J35: 0.0483 | K35: 12466.41 | L35: 12460.454 | M35: 459.22284 | O35: 19.21 | P35: 12460.454 | Q35: 0.99500869 | T35: 0.064529511 | U35: 0.11468398 | V35: 0.11191251 | W35: 0.11468398 | X35: 0 | Z35: 0.10683632 | AA35: 0.11158622 | AB35: 1.1161392 | AC35: -0.0054923824 | AD35: 488.51153 | AE35: 483.30322 | AG35: 488.51153 | AI35: 2.5016544e-05 | AK35: 463.88423 | AL35: 470.84249 | AM35: 456.92596 | AN35: 0.00017912257 | AO35: 0 | AP35: 0.1921 | AQ35: 0 | AR35: 0 | AS35: 1.0662728 | AT35: 1.0429273 | AU35: 1.0429273 | AV35: 1.1161392
A36: 45572 | B36: FALSE | C36: FALSE | D36: 2024ESZ | E36: C7 | F36: 5747.5 | G36: usual | H36: 0 | I36: 486.79446 | J36: 0.0483 | K36: 12466.41 | L36: 12470.818 | M36: 459.6048 | N36: 463.94979 | O36: 19.21 | P36: 12470.818 | Q36: 1.001093 | R36: 463.94979 | S36: 0.063450703 | T36: 0.064529511 | U36: 0.11151875 | V36: 0.11038686 | W36: 0.11151875 | X36: 0 | Y36: 0.10789492 | Z36: 0.10683632 | AA36: 0.11161775 | AB36: 1.0316639 | AC36: 0.00091990284 | AD36: 488.51153 | AE36: 483.74782 | AF36: 483.74782 | AG36: 488.51153 | AH36: 45572 | AI36: 6.9123541e-07 | AJ36: 459.6048 | AK36: 463.88423 | AL36: 470.84249 | AM36: 456.92596 | AN36: 0 | AO36: 0.0010058422 | AP36: 0.1921 | AQ36: 0 | AR36: 0 | AS36: 1.0662728 | AT36: 1.0288289 | AU36: 1.0288289 | AV36: 1.0316639
A37: 45573 | B37: FALSE | C37: FALSE | D37: 2024ESZ | E37: C1 | F37: 5768.15 | H37: 0 | I37: 491.51857 | J37: 0.0483 | K37: 12587.255 | L37: 12516.921 | M37: 461.22289 | O37: 22.64 | P37: 12516.921 | Q37: 1.0035929 | T37: 0.063450703 | U37: 0.11400659 | V37: 0.11168406 | W37: 0.11400659 | X37: 0.039602536 | Z37: 0.10789492 | AA37: 0.11170415 | AB37: 1.0606788 | AC37: 0.0036153046 | AD37: 483.74782 | AE37: 485.49671 | AG37: 483.74782 | AI37: 1.2351259e-05 | AK37: 459.6048 | AL37: 466.49887 | AM37: 452.71072 | AN37: 0.0010058422 | AO37: 0.00084049824 | AP37: 0.2264 | AQ37: 0.041848671 | AR37: -0.0022461354 | AS37: 1.0581821 | AT37: 1.0285702 | AU37: 1.0285702 | AV37: 1.0606788
A38: 45573 | B38: FALSE | C38: FALSE | D38: 2024ESZ | E38: C2 | F38: 5789.7 | H38: 0 | I38: 491.51857 | J38: 0.0483 | K38: 12587.255 | L38: 12564.755 | M38: 462.98547 | O38: 22.64 | P38: 12564.755 | Q38: 1.003736 | T38: 0.063450703 | U38: 0.11729227 | V38: 0.1134418 | W38: 0.11729227 | X38: 0.099825192 | Z38: 0.10789492 | AA38: 0.11245238 | AB38: 1.0782899 | AC38: 0.0040516727 | AD38: 483.74782 | AE38: 487.46378 | AG38: 483.74782 | AI38: 1.4548604e-05 | AK38: 459.6048 | AL38: 466.49887 | AM38: 452.71072 | AN38: 0.00084049824 | AO38: 0.00067515432 | AP38: 0.2264 | AQ38: 0.099892488 | AR38: -6.7295524e-05 | AS38: 1.0581821 | AT38: 1.0278608 | AU38: 1.0278608 | AV38: 1.0782899
A39: 45573 | B39: FALSE | C39: FALSE | D39: 2024ESZ | E39: C3 | F39: 5790.225 | H39: 0 | I39: 491.51857 | J39: 0.0483 | K39: 12587.255 | L39: 12565.009 | M39: 462.99483 | O39: 22.64 | P39: 12565.009 | Q39: 1.0000907 | T39: 0.063450703 | U39: 0.11371927 | V39: 0.11172731 | W39: 0.11371927 | X39: 0.070453631 | Z39: 0.10789492 | AA39: 0.11222277 | AB39: 1.1018768 | AC39: 1.9439234e-05 | AD39: 483.74782 | AE39: 487.47326 | AG39: 483.74782 | AI39: 4.0864915e-10 | AK39: 459.6048 | AL39: 466.49887 | AM39: 452.71072 | AN39: 0.00067515432 | AO39: 0.00050981041 | AP39: 0.2264 | AQ39: 0.070459125 | AR39: -5.4944219e-06 | AS39: 1.0581821 | AT39: 1.021673 | AU39: 1.021673 | AV39: 1.1018768
A40: 45573 | B40: FALSE | C40: FALSE | D40: 2024ESZ | E40: C4 | F40: 5788.25 | H40: 0 | I40: 491.51857 | J40: 0.0483 | K40: 12587.255 | L40: 12560.795 | M40: 462.83956 | O40: 22.64 | P40: 12560.795 | Q40: 0.99965891 | T40: 0.063450703 | U40: 0.11030891 | V40: 0.11006569 | W40: 0.11030891 | X40: 0.030598798 | Z40: 0.10789492 | AA40: 0.11192658 | AB40: 1.1075656 | AC40: -0.0003701117 | AD40: 483.74782 | AE40: 487.29284 | AG40: 483.74782 | AI40: 1.1251466e-07 | AK40: 459.6048 | AL40: 466.49887 | AM40: 452.71072 | AN40: 0.00050981041 | AO40: 0.00034446649 | AP40: 0.2264 | AQ40: 0.030598867 | AR40: -6.8947906e-08 | AS40: 1.0581821 | AT40: 1.0235802 | AU40: 1.0235802 | AV40: 1.1075656
A41: 45573 | B41: FALSE | C41: FALSE | D41: 2024ESZ | E41: C5 | F41: 5782.85 | H41: 0 | I41: 491.51857 | J41: 0.0483 | K41: 12587.255 | L41: 12550.094 | M41: 462.44525 | O41: 22.64 | P41: 12550.094 | Q41: 0.99906708 | T41: 0.063450703 | U41: 0.1073073 | V41: 0.1085793 | W41: 0.1085793 | X41: 0.0019961752 | Z41: 0.10789492 | AA41: 0.11184283 | AB41: 1.1017532 | AC41: -0.00094415682 | AD41: 483.74782 | AE41: 486.83276 | AG41: 483.74782 | AI41: 7.2641465e-07 | AK41: 459.6048 | AL41: 466.49887 | AM41: 452.71072 | AN41: 0.00034446649 | AO41: 0.00017912257 | AP41: 0.2264 | AQ41: 0.0019961752 | AR41: -1.0875745e-12 | AS41: 1.0581821 | AT41: 1.0260295 | AU41: 1.0260295 | AV41: 1.1017532
A42: 45573 | B42: FALSE | C42: FALSE | D42: 2024ESZ | E42: C6 | F42: 5794.6 | H42: 0 | I42: 491.51857 | J42: 0.0483 | K42: 12587.255 | L42: 12574.181 | M42: 463.3328 | O42: 22.64 | P42: 12574.181 | Q42: 1.0020319 | T42: 0.063450703 | U42: 0.10589187 | V42: 0.10784406 | W42: 0.10784406 | X42: 0 | Z42: 0.10789492 | AA42: 0.11177073 | AB42: 1.0874336 | AC42: 0.0021131282 | AD42: 483.74782 | AE42: 487.8615 | AG42: 483.74782 | AI42: 3.6765342e-06 | AK42: 459.6048 | AL42: 466.49887 | AM42: 452.71072 | AN42: 0.00017912257 | AO42: 0 | AP42: 0.2264 | AQ42: 0 | AR42: 0 | AS42: 1.0581821 | AT42: 1.0267198 | AU42: 1.0267198 | AV42: 1.0874336
A43: 45573 | B43: FALSE | C43: FALSE | D43: 2024ESZ | E43: C7 | F43: 5803.625 | G43: usual | H43: 0 | I43: 491.51857 | J43: 0.0483 | K43: 12587.255 | L43: 12594.072 | M43: 464.06575 | N43: 468.48032 | O43: 22.64 | P43: 12594.072 | Q43: 1.0015575 | R43: 468.48032 | S43: 0.061763112 | T43: 0.063450703 | U43: 0.10394584 | V43: 0.10683468 | W43: 0.10683468 | X43: 0 | Y43: 0.10844815 | Z43: 0.10789492 | AA43: 0.11188225 | AB43: 1.0954802 | AC43: 0.0017193982 | AD43: 483.74782 | AE43: 488.70033 | AF43: 488.70033 | AG43: 483.74782 | AH43: 45573 | AI43: 2.4984305e-06 | AJ43: 464.06575 | AK43: 459.6048 | AL43: 466.49887 | AM43: 452.71072 | AN43: 0 | AO43: 0.0010058422 | AP43: 0.2264 | AQ43: 0 | AR43: 0 | AS43: 1.0581821 | AT43: 1.0273134 | AU43: 1.0273134 | AV43: 1.0954802
A44: 45574 | B44: FALSE | C44: FALSE | D44: 2024ESZ | E44: C1 | F44: 5803.025 | H44: 0 | I44: 494.97161 | J44: 0.0483 | K44: 12677.158 | L44: 12593.367 | M44: 463.96015 | O44: 21.42 | P44: 12593.367 | Q44: 0.99989662 | T44: 0.061763112 | U44: 0.10080642 | V44: 0.10523298 | W44: 0.10523298 | X44: -0.00066533479 | Z44: 0.10844815 | AA44: 0.11140158 | AB44: 1.1048418 | AC44: -0.00026409381 | AD44: 488.70033 | AE44: 488.57127 | AG44: 488.70033 | AI44: 5.1787564e-08 | AK44: 464.06575 | AL44: 471.02673 | AM44: 457.10476 | AN44: 0.0010058422 | AO44: 0.00084049824 | AP44: 0.2142 | AQ44: 0.00752687 | AR44: -0.0081922048 | AS44: 1.0538972 | AT44: 1.026395 | AU44: 1.026395 | AV44: 1.1048418
A45: 45574 | B45: FALSE | C45: FALSE | D45: 2024ESZ | E45: C2 | F45: 5812.7 | H45: 0 | I45: 494.97161 | J45: 0.0483 | K45: 12677.158 | L45: 12614.761 | M45: 464.74834 | O45: 21.42 | P45: 12614.761 | Q45: 1.0016672 | T45: 0.061763112 | U45: 0.099283218 | V45: 0.10437543 | W45: 0.10437543 | X45: 0.0065857111 | Z45: 0.10844815 | AA45: 0.11113246 | AB45: 1.1259701 | AC45: 0.0018748265 | AD45: 488.70033 | AE45: 489.48725 | AG45: 488.70033 | AI45: 2.8811309e-06 | AK45: 464.06575 | AL45: 471.02673 | AM45: 457.10476 | AN45: 0.00084049824 | AO45: 0.00067515432 | AP45: 0.2142 | AQ45: 0.008015905 | AR45: -0.0014301938 | AS45: 1.0538972 | AT45: 1.0303408 | AU45: 1.0303408 | AV45: 1.1259701
A46: 45574 | B46: FALSE | C46: FALSE | D46: 2024ESZ | E46: C3 | F46: 5837.1 | H46: 0 | I46: 494.97161 | J46: 0.0483 | K46: 12677.158 | L46: 12667.132 | M46: 466.67777 | O46: 21.42 | P46: 12667.132 | Q46: 1.0041977 | T46: 0.061763112 | U46: 0.10527292 | V46: 0.10712485 | W46: 0.10712485 | X46: 0.027705801 | Z46: 0.10844815 | AA46: 0.11212514 | AB46: 1.1490161 | AC46: 0.0046722333 | AD46: 488.70033 | AE46: 491.77425 | AG46: 488.70033 | AI46: 1.7164209e-05 | AK46: 464.06575 | AL46: 471.02673 | AM46: 457.10476 | AN46: 0.00067515432 | AO46: 0.00050981041 | AP46: 0.2142 | AQ46: 0.027714819 | AR46: -9.0181027e-06 | AS46: 1.0538972 | AT46: 1.0325359 | AU46: 1.0325359 | AV46: 1.1490161
A47: 45574 | B47: FALSE | C47: FALSE | D47: 2024ESZ | E47: C4 | F47: 5830.725 | H47: 0 | I47: 494.97161 | J47: 0.0483 | K47: 12677.158 | L47: 12653.987 | M47: 466.19349 | O47: 21.42 | P47: 12653.987 | Q47: 0.99890785 | T47: 0.061763112 | U47: 0.10262329 | V47: 0.10577575 | W47: 0.10577575 | X47: 0.0047648455 | Z47: 0.10844815 | AA47: 0.11217525 | AB47: 1.1326864 | AC47: -0.0011939957 | AD47: 488.70033 | AE47: 491.18707 | AG47: 488.70033 | AI47: 1.0779918e-06 | AK47: 464.06575 | AL47: 471.02673 | AM47: 457.10476 | AN47: 0.00050981041 | AO47: 0.00034446649 | AP47: 0.2142 | AQ47: 0.0047652083 | AR47: -3.6286465e-07 | AS47: 1.0538972 | AT47: 1.0243889 | AU47: 1.0243889 | AV47: 1.1326864
A48: 45574 | B48: FALSE | C48: FALSE | D48: 2024ESZ | E48: C5 | F48: 5830.05 | H48: 0 | I48: 494.97161 | J48: 0.0483 | K48: 12677.158 | L48: 12652.949 | M48: 466.15525 | O48: 21.42 | P48: 12652.949 | Q48: 0.99988423 | T48: 0.061763112 | U48: 0.099500548 | V48: 0.10417874 | W48: 0.10417874 | X48: 0.00014449544 | Z48: 0.10844815 | AA48: 0.11184507 | AB48: 1.1132704 | AC48: -9.4855283e-05 | AD48: 488.70033 | AE48: 491.14048 | AG48: 488.70033 | AI48: 6.7293879e-09 | AK48: 464.06575 | AL48: 471.02673 | AM48: 457.10476 | AN48: 0.00034446649 | AO48: 0.00017912257 | AP48: 0.2142 | AQ48: 0.00014449544 | AR48: -3.9456216e-12 | AS48: 1.0538972 | AT48: 1.023974 | AU48: 1.023974 | AV48: 1.1132704
A49: 45574 | B49: FALSE | C49: FALSE | D49: 2024ESZ | E49: C6 | F49: 5832.45 | H49: 0 | I49: 494.97161 | J49: 0.0483 | K49: 12677.158 | L49: 12658.197 | M49: 466.34859 | O49: 21.42 | P49: 12658.197 | Q49: 1.0004117 | T49: 0.061763112 | U49: 0.096563645 | V49: 0.10264849 | W49: 0.10264849 | X49: 0 | Z49: 0.10844815 | AA49: 0.11170075 | AB49: 1.1333469 | AC49: 0.00045973791 | AD49: 488.70033 | AE49: 491.36628 | AG49: 488.70033 | AI49: 1.7195865e-07 | AK49: 464.06575 | AL49: 471.02673 | AM49: 457.10476 | AN49: 0.00017912257 | AO49: 0 | AP49: 0.2142 | AQ49: 0 | AR49: 0 | AS49: 1.0538972 | AT49: 1.0267013 | AU49: 1.0267013 | AV49: 1.1333469
A50: 45574 | B50: FALSE | C50: FALSE | D50: 2024ESZ | E50: C7 | F50: 5843.7 | G50: usual | H50: 0 | I50: 494.97161 | J50: 0.0483 | K50: 12677.158 | L50: 12682.355 | M50: 467.23861 | N50: 471.71525 | O50: 21.42 | P50: 12682.355 | Q50: 1.0019289 | R50: 471.71525 | S50: 0.058480741 | T50: 0.061763112 | U50: 0.095654766 | V50: 0.10204409 | W50: 0.10204409 | X50: 0 | Y50: 0.1087891 | Z50: 0.10844815 | AA50: 0.11188869 | AB50: 1.1515727 | AC50: 0.0021611549 | AD50: 488.70033 | AE50: 492.4282 | AF50: 492.4282 | AG50: 488.70033 | AH50: 45574 | AI50: 3.6353821e-06 | AJ50: 467.23861 | AK50: 464.06575 | AL50: 471.02673 | AM50: 457.10476 | AN50: 0 | AO50: 0.0010058422 | AP50: 0.2142 | AQ50: 0 | AR50: 0 | AS50: 1.0538972 | AT50: 1.0278887 | AU50: 1.0278887 | AV50: 1.1515727
A51: 45575 | B51: FALSE | C51: FALSE | D51: 2024ESZ | E51: C1 | F51: 5818.45 | H51: 0 | I51: 493.93358 | J51: 0.0483 | K51: 12652.837 | L51: 12633.826 | M51: 465.37482 | O51: 20.86 | P51: 12633.826 | Q51: 0.99567911 | T51: 0.058480741 | U51: 0.10144791 | V51: 0.10462324 | W51: 0.10462324 | X51: -0.031889163 | Z51: 0.1087891 | AA51: 0.11164015 | AB51: 1.1566502 | AC51: -0.0046079557 | AD51: 492.4282 | AE51: 490.15911 | AG51: 492.4282 | AI51: 1.5975378e-05 | AK51: 467.23861 | AL51: 474.24719 | AM51: 460.23003 | AN51: 0.0010058422 | AO51: 0.00084049824 | AP51: 0.2086 | AQ51: 0.00090488985 | AR51: -0.032794053 | AS51: 1.0512368 | AT51: 1.0263419 | AU51: 1.0263419 | AV51: 1.1566502
A52: 45575 | B52: FALSE | C52: FALSE | D52: 2024ESZ | E52: C2 | F52: 5824.65 | H52: 0 | I52: 493.93358 | J52: 0.0483 | K52: 12652.837 | L52: 12646.432 | M52: 465.83917 | O52: 20.86 | P52: 12646.432 | Q52: 1.0010656 | T52: 0.058480741 | U52: 0.098891085 | V52: 0.10329703 | W52: 0.10329703 | X52: -0.012133238 | Z52: 0.1087891 | AA52: 0.10779225 | AB52: 1.0964724 | AC52: 0.0011480849 | AD52: 492.4282 | AE52: 490.72185 | AG52: 492.4282 | AI52: 9.9460735e-07 | AK52: 467.23861 | AL52: 474.24719 | AM52: 460.23003 | AN52: 0.00084049824 | AO52: 0.00067515432 | AP52: 0.2086 | AQ52: 0.00048761592 | AR52: -0.012620854 | AS52: 1.0512368 | AT52: 1.0283864 | AU52: 1.0283864 | AV52: 1.0964724
A53: 45575 | B53: FALSE | C53: FALSE | D53: 2024ESZ | E53: C3 | F53: 5831.8 | H53: 0 | I53: 493.93358 | J53: 0.0483 | K53: 12652.837 | L53: 12661.342 | M53: 466.38839 | O53: 20.86 | P53: 12661.342 | Q53: 1.0012275 | T53: 0.058480741 | U53: 0.096641739 | V53: 0.10209624 | W53: 0.10209624 | X53: -0.0021716086 | Z53: 0.1087891 | AA53: 0.10567735 | AB53: 1.1586326 | AC53: 0.0012865125 | AD53: 492.4282 | AE53: 491.35317 | AG53: 492.4282 | AI53: 1.3883772e-06 | AK53: 467.23861 | AL53: 474.24719 | AM53: 460.23003 | AN53: 0.00067515432 | AO53: 0.00050981041 | AP53: 0.2086 | AQ53: 0.00019599304 | AR53: -0.0023676017 | AS53: 1.0512368 | AT53: 1.058973 | AU53: 1.0512368 | AV53: 1.1586326
A54: 45575 | B54: FALSE | C54: FALSE | D54: 2024ESZ | E54: C4 | F54: 5829.05 | H54: 0 | I54: 493.93358 | J54: 0.0483 | K54: 12652.837 | L54: 12655.229 | M54: 466.16322 | O54: 20.86 | P54: 12655.229 | Q54: 0.99952845 | T54: 0.058480741 | U54: 0.09382927 | V54: 0.10061448 | W54: 0.10061448 | X54: -0.00046111323 | Z54: 0.1087891 | AA54: 0.10550264 | AB54: 1.1841007 | AC54: -0.00056194414 | AD54: 492.4282 | AE54: 491.07706 | AG54: 492.4282 | AI54: 2.3321637e-07 | AK54: 467.23861 | AL54: 474.24719 | AM54: 460.23003 | AN54: 0.00050981041 | AO54: 0.00034446649 | AP54: 0.2086 | AQ54: 4.5219092e-06 | AR54: -0.00046563514 | AS54: 1.0512368 | AT54: 1.0749703 | AU54: 1.0512368 | AV54: 1.1841007
A55: 45575 | B55: FALSE | C55: FALSE | D55: 2024ESZ | E55: C5 | F55: 5824.875 | H55: 0 | I55: 493.93358 | J55: 0.0483 | K55: 12652.837 | L55: 12645.236 | M55: 465.79512 | O55: 20.86 | P55: 12645.236 | Q55: 0.99928376 | T55: 0.058480741 | U55: 0.091333135 | V55: 0.099260259 | W55: 0.099260259 | X55: -8.2887078e-06 | Z55: 0.1087891 | AA55: 0.10493552 | AB55: 1.201539 | AC55: -0.00093675011 | AD55: 492.4282 | AE55: 490.61704 | AG55: 492.4282 | AI55: 6.2401468e-07 | AK55: 467.23861 | AL55: 474.24719 | AM55: 460.23003 | AN55: 0.00034446649 | AO55: 0.00017912257 | AP55: 0.2086 | AQ55: 5.9806258e-11 | AR55: -8.2887676e-06 | AS55: 1.0512368 | AT55: 1.0762672 | AU55: 1.0512368 | AV55: 1.201539
A56: 45575 | B56: FALSE | C56: FALSE | D56: 2024ESZ | E56: C6 | F56: 5818.475 | H56: 0 | I56: 493.93358 | J56: 0.0483 | K56: 12652.837 | L56: 12632.175 | M56: 465.31401 | O56: 20.86 | P56: 12632.175 | Q56: 0.99890126 | T56: 0.058480741 | U56: 0.089186704 | V56: 0.098048644 | W56: 0.098048644 | X56: 0 | Z56: 0.1087891 | AA56: 0.10493126 | AB56: 1.2179318 | AC56: -0.0012426838 | AD56: 492.4282 | AE56: 490.00736 | AG56: 492.4282 | AI56: 1.0679422e-06 | AK56: 467.23861 | AL56: 474.24719 | AM56: 460.23003 | AN56: 0.00017912257 | AO56: 0 | AP56: 0.2086 | AQ56: 0 | AR56: 0 | AS56: 1.0512368 | AT56: 1.0804514 | AU56: 1.0512368 | AV56: 1.2179318
A57: 45575 | B57: FALSE | C57: FALSE | D57: 2024ESZ | E57: C7 | F57: 5829.9 | G57: usual | H57: 0 | I57: 493.93358 | J57: 0.0483 | K57: 12652.837 | L57: 12655.07 | M57: 466.15736 | N57: 470.60129 | O57: 20.86 | P57: 12655.07 | Q57: 1.0019636 | R57: 470.60129 | S57: 0.062962308 | T57: 0.058480741 | U57: 0.088453711 | V57: 0.097461038 | W57: 0.097461038 | X57: 0 | Y57: 0.1081399 | Z57: 0.1087891 | AA57: 0.10486748 | AB57: 1.2329822 | AC57: 0.0022059176 | AD57: 492.4282 | AE57: 491.08828 | AF57: 491.08828 | AG57: 492.4282 | AH57: 45575 | AI57: 3.2789779e-06 | AJ57: 466.15736 | AK57: 467.23861 | AL57: 474.24719 | AM57: 460.23003 | AN57: 0 | AO57: 0.0010058422 | AP57: 0.2086 | AQ57: 0 | AR57: 0 | AS57: 1.0512368 | AT57: 1.0804827 | AU57: 1.0512368 | AV57: 1.2329822
A58: 45576 | B58: FALSE | C58: FALSE | D58: 2024ESZ | E58: C1 | F58: 5835.05 | H58: 0 | I58: 496.53925 | J58: 0.0483 | K58: 12729.523 | L58: 12675.741 | M58: 466.83726 | O58: 20.93 | P58: 12675.741 | Q58: 1.0008834 | T58: 0.062962308 | U58: 0.087059975 | V58: 0.096571767 | W58: 0.096571767 | X58: 0.010408431 | Z58: 0.1081399 | AA58: 0.10498444 | AB58: 1.246378 | AC58: 0.0017831021 | AD58: 491.08828 | AE58: 491.96394 | AG58: 491.08828 | AI58: 2.1241855e-06 | AK58: 466.15736 | AL58: 473.14972 | AM58: 459.165 | AN58: 0.0010058422 | AO58: 0.00084049824 | AP58: 0.2093 | AQ58: 0.013537094 | AR58: -0.003128663 | AS58: 1.0562895 | AT58: 1.0809508 | AU58: 1.0562895 | AV58: 1.246378
A59: 45576 | B59: FALSE | C59: FALSE | D59: 2024ESZ | E59: C2 | F59: 5856 | H59: 0 | I59: 496.53925 | J59: 0.0483 | K59: 12729.523 | L59: 12718.019 | M59: 468.39433 | O59: 20.93 | P59: 12718.019 | Q59: 1.0035904 | T59: 0.062962308 | U59: 0.091094343 | V59: 0.098148236 | W59: 0.098148236 | X59: 0.031694739 | Z59: 0.1081399 | AA59: 0.10569611 | AB59: 1.2704337 | AC59: 0.0041546981 | AD59: 491.08828 | AE59: 494.0079 | AG59: 491.08828 | AI59: 1.1087551e-05 | AK59: 466.15736 | AL59: 473.14972 | AM59: 459.165 | AN59: 0.00084049824 | AO59: 0.00067515432 | AP59: 0.2093 | AQ59: 0.031819841 | AR59: -0.00012510185 | AS59: 1.0562895 | AT59: 1.080092 | AU59: 1.0562895 | AV59: 1.2704337
A60: 45576 | B60: FALSE | C60: FALSE | D60: 2024ESZ | E60: C3 | F60: 5858.7875 | H60: 0 | I60: 496.53925 | J60: 0.0483 | K60: 12729.523 | L60: 12725.616 | M60: 468.67412 | O60: 20.93 | P60: 12725.616 | Q60: 1.000476 | T60: 0.062962308 | U60: 0.088532658 | V60: 0.096762366 | W60: 0.096762366 | X60: 0.022273412 | Z60: 0.1081399 | AA60: 0.10563436 | AB60: 1.2747809 | AC60: 0.000758448 | AD60: 491.08828 | AE60: 494.38258 | AG60: 491.08828 | AI60: 3.5660379e-07 | AK60: 466.15736 | AL60: 473.14972 | AM60: 459.165 | AN60: 0.00067515432 | AO60: 0.00050981041 | AP60: 0.2093 | AQ60: 0.02228054 | AR60: -7.1287013e-06 | AS60: 1.0562895 | AT60: 1.0748309 | AU60: 1.0562895 | AV60: 1.2747809
A61: 45576 | B61: FALSE | C61: FALSE | D61: 2024ESZ | E61: C4 | F61: 5848.65 | H61: 0 | I61: 496.53925 | J61: 0.0483 | K61: 12729.523 | L61: 12704.068 | M61: 467.88052 | O61: 20.93 | P61: 12704.068 | Q61: 0.99826969 | T61: 0.062962308 | U61: 0.087588399 | V61: 0.096093994 | W61: 0.096093994 | X61: 0.0019815649 | Z61: 0.1081399 | AA61: 0.10584862 | AB61: 1.280485 | AC61: -0.0021591282 | AD61: 491.08828 | AE61: 493.31514 | AG61: 491.08828 | AI61: 2.8720514e-06 | AK61: 466.15736 | AL61: 473.14972 | AM61: 459.165 | AN61: 0.00050981041 | AO61: 0.00034446649 | AP61: 0.2093 | AQ61: 0.0019822061 | AR61: -6.4118699e-07 | AS61: 1.0562895 | AT61: 1.0752898 | AU61: 1.0562895 | AV61: 1.280485
A62: 45576 | B62: FALSE | C62: FALSE | D62: 2024ESZ | E62: C5 | F62: 5857.275 | H62: 0 | I62: 496.53925 | J62: 0.0483 | K62: 12729.523 | L62: 12722.384 | M62: 468.55508 | O62: 20.93 | P62: 12722.384 | Q62: 1.0014747 | T62: 0.062962308 | U62: 0.086203878 | V62: 0.095220147 | W62: 0.095220147 | X62: 0.00024867815 | Z62: 0.1081399 | AA62: 0.10543023 | AB62: 1.2641091 | AC62: 0.0018444926 | AD62: 491.08828 | AE62: 494.22506 | AG62: 491.08828 | AI62: 2.0756297e-06 | AK62: 466.15736 | AL62: 473.14972 | AM62: 459.165 | AN62: 0.00034446649 | AO62: 0.00017912257 | AP62: 0.2093 | AQ62: 0.00024867815 | AR62: -2.4447111e-13 | AS62: 1.0562895 | AT62: 1.0736954 | AU62: 1.0562895 | AV62: 1.2641091
A63: 45576 | B63: FALSE | C63: FALSE | D63: 2024ESZ | E63: C6 | F63: 5859.475 | H63: 0 | I63: 496.53925 | J63: 0.0483 | K63: 12729.523 | L63: 12726.859 | M63: 468.7199 | O63: 20.93 | P63: 12726.859 | Q63: 1.0003756 | T63: 0.062962308 | U63: 0.083656035 | V63: 0.093815858 | W63: 0.093815858 | X63: 0 | Z63: 0.1081399 | AA63: 0.10539062 | AB63: 1.27571 | AC63: 0.0004434805 | AD63: 491.08828 | AE63: 494.44424 | AG63: 491.08828 | AI63: 1.2367911e-07 | AK63: 466.15736 | AL63: 473.14972 | AM63: 459.165 | AN63: 0.00017912257 | AO63: 0 | AP63: 0.2093 | AQ63: 0 | AR63: 0 | AS63: 1.0562895 | AT63: 1.0768036 | AU63: 1.0562895 | AV63: 1.27571
A64: 45576 | B64: FALSE | C64: FALSE | D64: 2024ESZ | E64: C7 | F64: 5862.7 | G64: usual | H64: 0 | I64: 496.53925 | J64: 0.0483 | K64: 12729.523 | L64: 12735.164 | M64: 469.02576 | N64: 473.24897 | O64: 20.93 | P64: 12735.164 | Q64: 1.0005504 | R64: 473.24897 | S64: 0.064756061 | T64: 0.062962308 | U64: 0.081384721 | V64: 0.09251969 | W64: 0.09251969 | X64: 0 | Y64: 0.10824575 | Z64: 0.1081399 | AA64: 0.10541358 | AB64: 1.2948056 | AC64: 0.00083056384 | AD64: 491.08828 | AE64: 494.85491 | AF64: 494.85491 | AG64: 491.08828 | AH64: 45576 | AI64: 4.2555283e-07 | AJ64: 469.02576 | AK64: 466.15736 | AL64: 473.14972 | AM64: 459.165 | AN64: 0 | AO64: 0.0010058422 | AP64: 0.2093 | AQ64: 0 | AR64: 0 | AS64: 1.0562895 | AT64: 1.0770967 | AU64: 1.0562895 | AV64: 1.2948056
A65: 45579 | B65: FALSE | C65: FALSE | D65: 2024ESZ | E65: C1 | F65: 5892.25 | H65: 0 | I65: 500.64901 | J65: 0.0483 | K65: 12827.63 | L65: 12798.87 | M65: 471.1189 | O65: 20.46 | P65: 12798.87 | Q65: 1.0050403 | T65: 0.064756061 | U65: 0.091239282 | V65: 0.096707638 | W65: 0.096707638 | X65: 0.039030901 | Z65: 0.10824575 | AA65: 0.10670027 | AB65: 1.3119259 | AC65: 0.0057349966 | AD65: 494.85491 | AE65: 497.6929 | AG65: 494.85491 | AI65: 1.9827495e-05 | AK65: 469.02576 | AL65: 476.06115 | AM65: 461.99038 | AN65: 0.0010058422 | AO65: 0.00084049824 | AP65: 0.2046 | AQ65: 0.039511527 | AR65: -0.00048062656 | AS65: 1.0554694 | AT65: 1.0769268 | AU65: 1.0554694 | AV65: 1.3119259
A66: 45579 | B66: FALSE | C66: FALSE | D66: 2024ESZ | E66: C2 | F66: 5899.15 | H66: 0 | I66: 500.64901 | J66: 0.0483 | K66: 12827.63 | L66: 12812.237 | M66: 471.61093 | O66: 20.46 | P66: 12812.237 | Q66: 1.001171 | T66: 0.064756061 | U66: 0.089109228 | V66: 0.095548199 | W66: 0.095548199 | X66: 0.038814815 | Z66: 0.10824575 | AA66: 0.10671667 | AB66: 1.3053172 | AC66: 0.0013695002 | AD66: 494.85491 | AE66: 498.37449 | AG66: 494.85491 | AI66: 1.0896105e-06 | AK66: 469.02576 | AL66: 476.06115 | AM66: 461.99038 | AN66: 0.00084049824 | AO66: 0.00067515432 | AP66: 0.2046 | AQ66: 0.038867153 | AR66: -5.2337913e-05 | AS66: 1.0554694 | AT66: 1.0673024 | AU66: 1.0554694 | AV66: 1.3053172
A67: 45579 | B67: FALSE | C67: FALSE | D67: 2024ESZ | E67: C3 | F67: 5897.7 | H67: 0 | I67: 500.64901 | J67: 0.0483 | K67: 12827.63 | L67: 12809.027 | M67: 471.49277 | O67: 20.46 | P67: 12809.027 | Q67: 0.9997542 | T67: 0.064756061 | U67: 0.086433053 | V67: 0.094121716 | W67: 0.094121716 | X67: 0.018530716 | Z67: 0.10824575 | AA67: 0.10672246 | AB67: 1.3211567 | AC67: -0.00032862037 | AD67: 494.85491 | AE67: 498.21071 | AG67: 494.85491 | AI67: 6.2786888e-08 | AK67: 469.02576 | AL67: 476.06115 | AM67: 461.99038 | AN67: 0.00067515432 | AO67: 0.00050981041 | AP67: 0.2046 | AQ67: 0.018535897 | AR67: -5.1804892e-06 | AS67: 1.0554694 | AT67: 1.0671784 | AU67: 1.0554694 | AV67: 1.3211567
A68: 45579 | B68: FALSE | C68: FALSE | D68: 2024ESZ | E68: C4 | F68: 5904.475 | H68: 0 | I68: 500.64901 | J68: 0.0483 | K68: 12827.63 | L68: 12823.879 | M68: 472.03947 | O68: 20.46 | P68: 12823.879 | Q68: 1.0011488 | T68: 0.064756061 | U68: 0.084643734 | V68: 0.093081658 | W68: 0.093081658 | X68: 0.01280012 | Z68: 0.10824575 | AA68: 0.10670467 | AB68: 1.3153878 | AC68: 0.0015312974 | AD68: 494.85491 | AE68: 498.97362 | AG68: 494.85491 | AI68: 1.342871e-06 | AK68: 469.02576 | AL68: 476.06115 | AM68: 461.99038 | AN68: 0.00050981041 | AO68: 0.00034446649 | AP68: 0.2046 | AQ68: 0.012800127 | AR68: -7.1966181e-09 | AS68: 1.0554694 | AT68: 1.0671346 | AU68: 1.0554694 | AV68: 1.3153878
A69: 45579 | B69: FALSE | C69: FALSE | D69: 2024ESZ | E69: C5 | F69: 5903.025 | H69: 0 | I69: 500.64901 | J69: 0.0483 | K69: 12827.63 | L69: 12820.926 | M69: 471.93077 | O69: 20.46 | P69: 12820.926 | Q69: 0.99975442 | T69: 0.064756061 | U69: 0.082099339 | V69: 0.091690109 | W69: 0.091690109 | X69: 0.00073408399 | Z69: 0.10824575 | AA69: 0.10660621 | AB69: 1.3170454 | AC69: -0.00030306477 | AD69: 494.85491 | AE69: 498.8224 | AG69: 494.85491 | AI69: 5.3038116e-08 | AK69: 469.02576 | AL69: 476.06115 | AM69: 461.99038 | AN69: 0.00034446649 | AO69: 0.00017912257 | AP69: 0.2046 | AQ69: 0.00073408399 | AR69: -3.7747583e-15 | AS69: 1.0554694 | AT69: 1.0672691 | AU69: 1.0554694 | AV69: 1.3170454
A70: 45579 | B70: FALSE | C70: FALSE | D70: 2024ESZ | E70: C6 | F70: 5909.8 | H70: 0 | I70: 500.64901 | J70: 0.0483 | K70: 12827.63 | L70: 12835.535 | M70: 472.46852 | O70: 20.46 | P70: 12835.535 | Q70: 1.0011477 | T70: 0.064756061 | U70: 0.080455874 | V70: 0.090683493 | W70: 0.090683493 | X70: 0 | Z70: 0.10824575 | AA70: 0.10643156 | AB70: 1.3237958 | AC70: 0.0015000525 | AD70: 494.85491 | AE70: 499.57066 | AG70: 494.85491 | AI70: 1.2969032e-06 | AK70: 469.02576 | AL70: 476.06115 | AM70: 461.99038 | AN70: 0.00017912257 | AO70: 0 | AP70: 0.2046 | AQ70: 0 | AR70: 0 | AS70: 1.0554694 | AT70: 1.0680129 | AU70: 1.0554694 | AV70: 1.3237958
A71: 45579 | B71: FALSE | C71: FALSE | D71: 2024ESZ | E71: C7 | F71: 5910.725 | G71: usual | H71: 0 | I71: 500.64901 | J71: 0.0483 | K71: 12827.63 | L71: 12836.164 | M71: 472.49167 | N71: 477.12564 | O71: 20.46 | P71: 12836.164 | Q71: 1.0001565 | R71: 477.12564 | S71: 0.059114415 | T71: 0.064756061 | U71: 0.078006493 | V71: 0.089313594 | W71: 0.089313594 | X71: 0 | Y71: 0.10823981 | Z71: 0.10824575 | AA71: 0.10641214 | AB71: 1.3384904 | AC71: 6.3402601e-05 | AD71: 494.85491 | AE71: 499.60233 | AF71: 499.60233 | AG71: 494.85491 | AH71: 45579 | AI71: 2.4013312e-09 | AJ71: 472.49167 | AK71: 469.02576 | AL71: 476.06115 | AM71: 461.99038 | AN71: 0 | AO71: 0.0010058422 | AP71: 0.2046 | AQ71: 0 | AR71: 0 | AS71: 1.0554694 | AT71: 1.0693292 | AU71: 1.0554694 | AV71: 1.3384904
A72: 45580 | B72: FALSE | C72: FALSE | D72: 2024ESZ | E72: C1 | F72: 5910.9 | H72: 0 | I72: 496.79346 | J72: 0.0483 | K72: 12731.098 | L72: 12838.113 | M72: 472.48583 | O72: 19.7 | P72: 12838.113 | Q72: 1.0000296 | T72: 0.059114415 | U72: 0.075630208 | V72: 0.087963735 | W72: 0.087963735 | X72: 0.00051696077 | Z72: 0.10823981 | AA72: 0.10634354 | AB72: 1.3590795 | AC72: -3.2505025e-05 | AD72: 499.60233 | AE72: 499.58609 | AG72: 499.60233 | AI72: 1.5302049e-10 | AK72: 472.49167 | AL72: 479.57905 | AM72: 465.4043 | AN72: 0.0010058422 | AO72: 0.00084049824 | AP72: 0.197 | AQ72: 0.0045778952 | AR72: -0.0040609344 | AS72: 1.0555155 | AT72: 1.0694753 | AU72: 1.0555155 | AV72: 1.3590795
A73: 45580 | B73: FALSE | C73: FALSE | D73: 2024ESZ | E73: C2 | F73: 5886.85 | H73: 0 | I73: 496.79346 | J73: 0.0483 | K73: 12731.098 | L73: 12785.81 | M73: 470.5609 | O73: 19.7 | P73: 12785.81 | Q73: 0.99593125 | T73: 0.059114415 | U73: 0.084502241 | V73: 0.091582958 | W73: 0.091582958 | X73: -0.015467976 | Z73: 0.10823981 | AA73: 0.10810543 | AB73: 1.3799355 | AC73: -0.0055390315 | AD73: 499.60233 | AE73: 496.81887 | AG73: 499.60233 | AI73: 1.6665685e-05 | AK73: 472.49167 | AL73: 479.57905 | AM73: 465.4043 | AN73: 0.00084049824 | AO73: 0.00067515432 | AP73: 0.197 | AQ73: 0.00010528002 | AR73: -0.015573256 | AS73: 1.0555155 | AT73: 1.0699911 | AU73: 1.0555155 | AV73: 1.3799355
A74: 45580 | B74: FALSE | C74: FALSE | D74: 2024ESZ | E74: C3 | F74: 5882.575 | H74: 0 | I74: 496.79346 | J74: 0.0483 | K74: 12731.098 | L74: 12776.497 | M74: 470.21815 | O74: 19.7 | P74: 12776.497 | Q74: 0.99927381 | T74: 0.059114415 | U74: 0.082270194 | V74: 0.090354369 | W74: 0.090354369 | X74: -0.01028398 | Z74: 0.10823981 | AA74: 0.10818381 | AB74: 1.2988944 | AC74: -0.0010132293 | AD74: 499.60233 | AE74: 496.31548 | AG74: 499.60233 | AI74: 5.3093229e-07 | AK74: 472.49167 | AL74: 479.57905 | AM74: 465.4043 | AN74: 0.00067515432 | AO74: 0.00050981041 | AP74: 0.197 | AQ74: 4.7254234e-06 | AR74: -0.010288705 | AS74: 1.0555155 | AT74: 1.0565563 | AU74: 1.0555155 | AV74: 1.2988944
A75: 45580 | B75: FALSE | C75: FALSE | D75: 2024ESZ | E75: C4 | F75: 5883.125 | H75: 0 | I75: 496.79346 | J75: 0.0483 | K75: 12731.098 | L75: 12777.684 | M75: 470.26183 | O75: 19.7 | P75: 12777.684 | Q75: 1.0000935 | T75: 0.059114415 | U75: 0.079769639 | V75: 0.088991299 | W75: 0.088991299 | X75: -0.0022440645 | Z75: 0.10823981 | AA75: 0.10817418 | AB75: 1.3299903 | AC75: 0.00011756415 | AD75: 499.60233 | AE75: 496.37383 | AG75: 499.60233 | AI75: 8.6305306e-09 | AK75: 472.49167 | AL75: 479.57905 | AM75: 465.4043 | AN75: 0.00050981041 | AO75: 0.00034446649 | AP75: 0.197 | AQ75: 4.0692464e-08 | AR75: -0.0022441052 | AS75: 1.0555155 | AT75: 1.0559495 | AU75: 1.0555155 | AV75: 1.3299903
A76: 45580 | B76: FALSE | C76: FALSE | D76: 2024ESZ | E76: C5 | F76: 5879.875 | H76: 0 | I76: 496.79346 | J76: 0.0483 | K76: 12731.098 | L76: 12771.004 | M76: 470.01599 | O76: 19.7 | P76: 12771.004 | Q76: 0.99944757 | T76: 0.059114415 | U76: 0.077526417 | V76: 0.087728779 | W76: 0.087728779 | X76: -9.1609956e-05 | Z76: 0.10823981 | AA76: 0.10811555 | AB76: 1.3640017 | AC76: -0.00069870205 | AD76: 499.60233 | AE76: 496.02701 | AG76: 499.60233 | AI76: 2.7344862e-07 | AK76: 472.49167 | AL76: 479.57905 | AM76: 465.4043 | AN76: 0.00034446649 | AO76: 0.00017912257 | AP76: 0.197 | AQ76: 1.1020547e-14 | AR76: -9.1609956e-05 | AS76: 1.0555155 | AT76: 1.0560241 | AU76: 1.0555155 | AV76: 1.3640017
A77: 45580 | B77: FALSE | C77: FALSE | D77: 2024ESZ | E77: C6 | F77: 5868.25 | H77: 0 | I77: 496.79346 | J77: 0.0483 | K77: 12731.098 | L77: 12746.294 | M77: 469.10658 | O77: 19.7 | P77: 12746.294 | Q77: 0.99802292 | T77: 0.059114415 | U77: 0.077760663 | V77: 0.087543969 | W77: 0.087543969 | X77: 0 | Z77: 0.10823981 | AA77: 0.10855726 | AB77: 1.3836312 | AC77: -0.002641104 | AD77: 499.60233 | AE77: 494.71695 | AG77: 499.60233 | AI77: 3.7509077e-06 | AK77: 472.49167 | AL77: 479.57905 | AM77: 465.4043 | AN77: 0.00017912257 | AO77: 0 | AP77: 0.197 | AQ77: 0 | AR77: 0 | AS77: 1.0555155 | AT77: 1.056478 | AU77: 1.0555155 | AV77: 1.3836312
A78: 45580 | B78: FALSE | C78: FALSE | D78: 2024ESZ | E78: C7 | F78: 5860.825 | G78: usual | H78: 0 | I78: 496.79346 | J78: 0.0483 | K78: 12731.098 | L78: 12729.785 | M78: 468.49899 | N78: 473.09762 | O78: 19.7 | P78: 12729.785 | Q78: 0.99873472 | R78: 473.09762 | S78: 0.059267401 | T78: 0.059114415 | U78: 0.076561732 | V78: 0.086734761 | W78: 0.086734761 | X78: 0 | Y78: 0.10974336 | Z78: 0.10823981 | AA78: 0.10875275 | AB78: 1.3833101 | AC78: -0.0017921113 | AD78: 499.60233 | AE78: 493.83037 | AF78: 493.83037 | AG78: 499.60233 | AH78: 45580 | AI78: 1.6797184e-06 | AJ78: 468.49899 | AK78: 472.49167 | AL78: 479.57905 | AM78: 465.4043 | AN78: 0 | AO78: 0.0010058422 | AP78: 0.197 | AQ78: 0 | AR78: 0 | AS78: 1.0555155 | AT78: 1.0530475 | AU78: 1.0530475 | AV78: 1.3833101
A79: 45581 | B79: FALSE | C79: FALSE | D79: 2024ESZ | E79: C1 | F79: 5855.275 | H79: 0 | I79: 498.84834 | J79: 0.0483 | K79: 12790.843 | L79: 12721.72 | M79: 468.12504 | O79: 20.64 | P79: 12721.72 | Q79: 0.99905303 | T79: 0.059267401 | U79: 0.074682537 | V79: 0.085621104 | W79: 0.085621104 | X79: -0.0038887841 | Z79: 0.10974336 | AA79: 0.10843161 | AB79: 1.3838355 | AC79: -0.0011180791 | AD79: 493.83037 | AE79: 493.27822 | AG79: 493.83037 | AI79: 6.3760848e-07 | AK79: 468.49899 | AL79: 475.52647 | AM79: 461.47151 | AN79: 0.0010058422 | AO79: 0.00084049824 | AP79: 0.2064 | AQ79: 0.0044145755 | AR79: -0.0083033596 | AS79: 1.0437099 | AT79: 1.0515212 | AU79: 1.0437099 | AV79: 1.3838355
A80: 45581 | B80: FALSE | C80: FALSE | D80: 2024ESZ | E80: C2 | F80: 5863.775 | H80: 0 | I80: 498.84834 | J80: 0.0483 | K80: 12790.843 | L80: 12738.519 | M80: 468.7432 | O80: 20.64 | P80: 12738.519 | Q80: 1.0014517 | T80: 0.059267401 | U80: 0.073669151 | V80: 0.084871667 | W80: 0.084871667 | X80: 0.0019603523 | Z80: 0.10974336 | AA80: 0.10834042 | AB80: 1.4018348 | AC80: 0.0018255514 | AD80: 493.83037 | AE80: 494.17873 | AG80: 493.83037 | AI80: 1.741414e-06 | AK80: 468.49899 | AL80: 475.52647 | AM80: 461.47151 | AN80: 0.00084049824 | AO80: 0.00067515432 | AP80: 0.2064 | AQ80: 0.0037220014 | AR80: -0.0017616491 | AS80: 1.0437099 | AT80: 1.0540259 | AU80: 1.0437099 | AV80: 1.4018348
A81: 45581 | B81: FALSE | C81: FALSE | D81: 2024ESZ | E81: C3 | F81: 5866.975 | H81: 0 | I81: 498.84834 | J81: 0.0483 | K81: 12790.843 | L81: 12745.375 | M81: 468.99548 | O81: 20.64 | P81: 12745.375 | Q81: 1.0005457 | T81: 0.059267401 | U81: 0.071639077 | V81: 0.083680494 | W81: 0.083680494 | X81: 0.001254946 | Z81: 0.10974336 | AA81: 0.1080896 | AB81: 1.4142133 | AC81: 0.00075324382 | AD81: 493.83037 | AE81: 494.55097 | AG81: 493.83037 | AI81: 2.8951432e-07 | AK81: 468.49899 | AL81: 475.52647 | AM81: 461.47151 | AN81: 0.00067515432 | AO81: 0.00050981041 | AP81: 0.2064 | AQ81: 0.0015126014 | AR81: -0.00025765536 | AS81: 1.0437099 | AT81: 1.0547347 | AU81: 1.0437099 | AV81: 1.4142133
A82: 45581 | B82: FALSE | C82: FALSE | D82: 2024ESZ | E82: C4 | F82: 5873.675 | H82: 0 | I82: 498.84834 | J82: 0.0483 | K82: 12790.843 | L82: 12759.818 | M82: 469.52694 | O82: 20.64 | P82: 12759.818 | Q82: 1.001142 | T82: 0.059267401 | U82: 0.070427172 | V82: 0.082826515 | W82: 0.082826515 | X82: 0.00045914704 | Z82: 0.10974336 | AA82: 0.10679388 | AB82: 1.4343443 | AC82: 0.0016005669 | AD82: 493.83037 | AE82: 495.34253 | AG82: 493.83037 | AI82: 1.2826781e-06 | AK82: 468.49899 | AL82: 475.52647 | AM82: 461.47151 | AN82: 0.00050981041 | AO82: 0.00034446649 | AP82: 0.2064 | AQ82: 0.0004622476 | AR82: -3.1005644e-06 | AS82: 1.0437099 | AT82: 1.0566787 | AU82: 1.0437099 | AV82: 1.4343443
A83: 45581 | B83: FALSE | C83: FALSE | D83: 2024ESZ | E83: C5 | F83: 5878.95 | H83: 0 | I83: 498.84834 | J83: 0.0483 | K83: 12790.843 | L83: 12771.011 | M83: 469.93882 | O83: 20.64 | P83: 12771.011 | Q83: 1.0008981 | T83: 0.059267401 | U83: 0.068874952 | V83: 0.081823655 | W83: 0.081823655 | X83: 9.4484299e-06 | Z83: 0.10974336 | AA83: 0.10685439 | AB83: 1.4491331 | AC83: 0.0012567378 | AD83: 493.83037 | AE83: 495.96504 | AG83: 493.83037 | AI83: 7.6881743e-07 | AK83: 468.49899 | AL83: 475.52647 | AM83: 461.47151 | AN83: 0.00034446649 | AO83: 0.00017912257 | AP83: 0.2064 | AQ83: 9.4484529e-06 | AR83: -2.2984614e-11 | AS83: 1.0437099 | AT83: 1.0665942 | AU83: 1.0437099 | AV83: 1.4491331
A84: 45581 | B84: FALSE | C84: FALSE | D84: 2024ESZ | E84: C6 | F84: 5889.175 | H84: 0 | I84: 498.84834 | J84: 0.0483 | K84: 12790.843 | L84: 12793.009 | M84: 470.74828 | O84: 20.64 | P84: 12793.009 | Q84: 1.0017393 | T84: 0.059267401 | U84: 0.069084148 | V84: 0.081553664 | W84: 0.081553664 | X84: 0 | Z84: 0.10974336 | AA84: 0.10713827 | AB84: 1.4668942 | AC84: 0.002494348 | AD84: 493.83037 | AE84: 497.20215 | AG84: 493.83037 | AI84: 2.9618858e-06 | AK84: 468.49899 | AL84: 475.52647 | AM84: 461.47151 | AN84: 0.00017912257 | AO84: 0 | AP84: 0.2064 | AQ84: 0 | AR84: 0 | AS84: 1.0437099 | AT84: 1.0661359 | AU84: 1.0437099 | AV84: 1.4668942
A85: 45581 | B85: FALSE | C85: FALSE | D85: 2024ESZ | E85: C7 | F85: 5886.425 | G85: usual | H85: 0 | I85: 498.84834 | J85: 0.0483 | K85: 12790.843 | L85: 12789.086 | M85: 470.60393 | N85: 475.1641 | O85: 20.64 | P85: 12789.086 | Q85: 0.99953304 | R85: 475.1641 | S85: 0.055179467 | T85: 0.059267401 | U85: 0.067053844 | V85: 0.080352026 | W85: 0.080352026 | X85: 0 | Y85: 0.10923663 | Z85: 0.10974336 | AA85: 0.10711216 | AB85: 1.4717504 | AC85: -0.00045031145 | AD85: 493.83037 | AE85: 496.97826 | AF85: 496.97826 | AG85: 493.83037 | AH85: 45581 | AI85: 9.4064207e-08 | AJ85: 470.60393 | AK85: 468.49899 | AL85: 475.52647 | AM85: 461.47151 | AN85: 0 | AO85: 0.0010058422 | AP85: 0.2064 | AQ85: 0 | AR85: 0 | AS85: 1.0437099 | AT85: 1.0639794 | AU85: 1.0437099 | AV85: 1.4717504
A86: 45582 | B86: FALSE | C86: FALSE | D86: 2024ESZ | E86: C1 | F86: 5908.1875 | H86: 0 | I86: 498.84834 | J86: 0.0483 | K86: 12788.783 | L86: 12839.3 | M86: 472.37954 | O86: 19.58 | P86: 12839.3 | Q86: 1.0036971 | T86: 0.055179467 | U86: 0.075680249 | V86: 0.083745341 | W86: 0.083745341 | X86: 0.024762017 | Z86: 0.10923663 | AA86: 0.10869738 | AB86: 1.4995017 | AC86: 0.0055363096 | AD86: 496.97826 | AE86: 499.72968 | AG86: 496.97826 | AI86: 1.4182306e-05 | AK86: 470.60393 | AL86: 477.66299 | AM86: 463.54487 | AN86: 0.0010058422 | AO86: 0.00084049824 | AP86: 0.1958 | AQ86: 0.025198195 | AR86: -0.00043617771 | AS86: 1.0477217 | AT86: 1.0641782 | AU86: 1.0477217 | AV86: 1.4995017
A87: 45582 | B87: FALSE | C87: FALSE | D87: 2024ESZ | E87: C2 | F87: 5894.975 | H87: 0 | I87: 498.84834 | J87: 0.0483 | K87: 12788.783 | L87: 12809.179 | M87: 471.27133 | O87: 19.58 | P87: 12809.179 | Q87: 0.9977637 | T87: 0.055179467 | U87: 0.077251104 | V87: 0.084230785 | W87: 0.084230785 | X87: 0.0035069658 | Z87: 0.10923663 | AA87: 0.10947035 | AB87: 1.4675176 | AC87: -0.0035210297 | AD87: 496.97826 | AE87: 497.97012 | AG87: 496.97826 | AI87: 5.5166564e-06 | AK87: 470.60393 | AL87: 477.66299 | AM87: 463.54487 | AN87: 0.00084049824 | AO87: 0.00067515432 | AP87: 0.1958 | AQ87: 0.0040804055 | AR87: -0.00057343969 | AS87: 1.0477217 | AT87: 1.051954 | AU87: 1.0477217 | AV87: 1.4675176
A88: 45582 | B88: FALSE | C88: FALSE | D88: 2024ESZ | E88: C3 | F88: 5904.55 | H88: 0 | I88: 498.84834 | J88: 0.0483 | K88: 12788.783 | L88: 12829.969 | M88: 472.03623 | O88: 19.58 | P88: 12829.969 | Q88: 1.0016243 | T88: 0.055179467 | U88: 0.076733515 | V88: 0.083792374 | W88: 0.083792374 | X88: 0.0036817906 | Z88: 0.10923663 | AA88: 0.1094469 | AB88: 1.4279304 | AC88: 0.0023779028 | AD88: 496.97826 | AE88: 499.15424 | AG88: 496.97826 | AI88: 2.6300377e-06 | AK88: 470.60393 | AL88: 477.66299 | AM88: 463.54487 | AN88: 0.00067515432 | AO88: 0.00050981041 | AP88: 0.1958 | AQ88: 0.0037017259 | AR88: -1.9935266e-05 | AS88: 1.0477217 | AT88: 1.0458756 | AU88: 1.0458756 | AV88: 1.4279304
A89: 45582 | B89: FALSE | C89: FALSE | D89: 2024ESZ | E89: C4 | F89: 5907.625 | H89: 0 | I89: 498.84834 | J89: 0.0483 | K89: 12788.783 | L89: 12836.269 | M89: 472.26802 | O89: 19.58 | P89: 12836.269 | Q89: 1.0005208 | T89: 0.055179467 | U89: 0.074567136 | V89: 0.082603153 | W89: 0.082603153 | X89: 0.00089230919 | Z89: 0.10923663 | AA89: 0.10921498 | AB89: 1.4356561 | AC89: 0.00070039523 | AD89: 496.97826 | AE89: 499.50385 | AG89: 496.97826 | AI89: 2.409998e-07 | AK89: 470.60393 | AL89: 477.66299 | AM89: 463.54487 | AN89: 0.00050981041 | AO89: 0.00034446649 | AP89: 0.1958 | AQ89: 0.00089245246 | AR89: -1.4326866e-07 | AS89: 1.0477217 | AT89: 1.0460612 | AU89: 1.0460612 | AV89: 1.4356561
A90: 45582 | B90: FALSE | C90: FALSE | D90: 2024ESZ | E90: C5 | F90: 5908.75 | H90: 0 | I90: 498.84834 | J90: 0.0483 | K90: 12788.783 | L90: 12839.178 | M90: 472.37505 | O90: 19.58 | P90: 12839.178 | Q90: 1.0001904 | T90: 0.055179467 | U90: 0.072333096 | V90: 0.081371369 | W90: 0.081371369 | X90: 1.0843984e-05 | Z90: 0.10923663 | AA90: 0.10921506 | AB90: 1.4586368 | AC90: 0.00032305531 | AD90: 496.97826 | AE90: 499.66522 | AG90: 496.97826 | AI90: 5.1346567e-08 | AK90: 470.60393 | AL90: 477.66299 | AM90: 463.54487 | AN90: 0.00034446649 | AO90: 0.00017912257 | AP90: 0.1958 | AQ90: 1.0843985e-05 | AR90: -2.962075e-13 | AS90: 1.0477217 | AT90: 1.0478924 | AU90: 1.0477217 | AV90: 1.4586368
A91: 45582 | B91: FALSE | C91: FALSE | D91: 2024ESZ | E91: C6 | F91: 5893.125 | H91: 0 | I91: 498.84834 | J91: 0.0483 | K91: 12788.783 | L91: 12804.956 | M91: 471.11596 | O91: 19.58 | P91: 12804.956 | Q91: 0.99735562 | T91: 0.055179467 | U91: 0.075313389 | V91: 0.082459917 | W91: 0.082459917 | X91: 0 | Z91: 0.10923663 | AA91: 0.10970292 | AB91: 1.4807174 | AC91: -0.0038901103 | AD91: 496.97826 | AE91: 497.72146 | AG91: 496.97826 | AI91: 7.1235291e-06 | AK91: 470.60393 | AL91: 477.66299 | AM91: 463.54487 | AN91: 0.00017912257 | AO91: 0 | AP91: 0.1958 | AQ91: 0 | AR91: 0 | AS91: 1.0477217 | AT91: 1.0478918 | AU91: 1.0477217 | AV91: 1.4807174
A92: 45582 | B92: FALSE | C92: FALSE | D92: 2024ESZ | E92: C7 | F92: 5886.3 | G92: usual | H92: 0 | I92: 498.84834 | J92: 0.0483 | K92: 12788.783 | L92: 12789.306 | M92: 470.54017 | N92: 475.15401 | O92: 19.58 | P92: 12789.306 | Q92: 0.99884187 | R92: 475.15401 | S92: 0.053703051 | T92: 0.055179467 | U92: 0.074095007 | V92: 0.081699411 | W92: 0.081699411 | X92: 0 | Y92: 0.10901123 | Z92: 0.10923663 | AA92: 0.10795777 | AB92: 1.4560238 | AC92: -0.001812177 | AD92: 496.97826 | AE92: 496.8195 | AF92: 496.8195 | AG92: 496.97826 | AH92: 45582 | AI92: 1.495559e-06 | AJ92: 470.54017 | AK92: 470.60393 | AL92: 477.66299 | AM92: 463.54487 | AN92: 0 | AO92: 0.0010058422 | AP92: 0.1958 | AQ92: 0 | AR92: 0 | AS92: 1.0477217 | AT92: 1.0440314 | AU92: 1.0440314 | AV92: 1.4560238
A93: 45583 | B93: FALSE | C93: FALSE | D93: 2024ESZ | E93: C1 | F93: 5894.45 | H93: 0 | I93: 500.45835 | J93: 0.0483 | K93: 12840.3 | L93: 12813.548 | M93: 471.36188 | O93: 19.11 | P93: 12813.548 | Q93: 1.0013846 | T93: 0.053703051 | U93: 0.074046434 | V93: 0.081459525 | W93: 0.081459525 | X93: 0.0077415393 | Z93: 0.10901123 | AA93: 0.10109558 | AB93: 1.4772685 | AC93: 0.0025266625 | AD93: 496.8195 | AE93: 498.0748 | AG93: 496.8195 | AI93: 3.0442981e-06 | AK93: 470.54017 | AL93: 477.59827 | AM93: 463.48207 | AN93: 0.0010058422 | AO93: 0.00084049824 | AP93: 0.1911 | AQ93: 0.008902342 | AR93: -0.0011608027 | AS93: 1.0494954 | AT93: 1.0576973 | AU93: 1.0494954 | AV93: 1.4772685
A94: 45583 | B94: FALSE | C94: FALSE | D94: 2024ESZ | E94: C2 | F94: 5898.025 | H94: 0 | I94: 500.45835 | J94: 0.0483 | K94: 12840.3 | L94: 12821.873 | M94: 471.66813 | O94: 19.11 | P94: 12821.873 | Q94: 1.0006065 | T94: 0.053703051 | U94: 0.072100967 | V94: 0.080367334 | W94: 0.080367334 | X94: 0.0057637247 | Z94: 0.10901123 | AA94: 0.10088828 | AB94: 1.496435 | AC94: 0.00095786907 | AD94: 496.8195 | AE94: 498.55189 | AG94: 496.8195 | AI94: 4.2183984e-07 | AK94: 470.54017 | AL94: 477.59827 | AM94: 463.48207 | AN94: 0.00084049824 | AO94: 0.00067515432 | AP94: 0.1911 | AQ94: 0.005972763 | AR94: -0.00020903826 | AS94: 1.0494954 | AT94: 1.1077893 | AU94: 1.0494954 | AV94: 1.496435
A95: 45583 | B95: FALSE | C95: FALSE | D95: 2024ESZ | E95: C3 | F95: 5901.125 | H95: 0 | I95: 500.45835 | J95: 0.0483 | K95: 12840.3 | L95: 12827.937 | M95: 471.8912 | O95: 19.11 | P95: 12827.937 | Q95: 1.0005256 | T95: 0.053703051 | U95: 0.070073525 | V95: 0.079227346 | W95: 0.079227346 | X95: 0.0026700187 | Z95: 0.10901123 | AA95: 0.10088158 | AB95: 1.5167716 | AC95: 0.00070569306 | AD95: 496.8195 | AE95: 498.90371 | AG95: 496.8195 | AI95: 2.2356823e-07 | AK95: 470.54017 | AL95: 477.59827 | AM95: 463.48207 | AN95: 0.00067515432 | AO95: 0.00050981041 | AP95: 0.1911 | AQ95: 0.0026852926 | AR95: -1.5273972e-05 | AS95: 1.0494954 | AT95: 1.1092174 | AU95: 1.0494954 | AV95: 1.5167716
A96: 45583 | B96: FALSE | C96: FALSE | D96: 2024ESZ | E96: C4 | F96: 5908.8 | H96: 0 | I96: 500.45835 | J96: 0.0483 | K96: 12840.3 | L96: 12843.954 | M96: 472.48041 | O96: 19.11 | P96: 12843.954 | Q96: 1.0013006 | T96: 0.053703051 | U96: 0.069141021 | V96: 0.078556114 | W96: 0.078556114 | X96: 0.0011993822 | Z96: 0.10901123 | AA96: 0.10091125 | AB96: 1.5233625 | AC96: 0.0018931864 | AD96: 496.8195 | AE96: 499.84823 | AG96: 496.8195 | AI96: 1.557065e-06 | AK96: 470.54017 | AL96: 477.59827 | AM96: 463.48207 | AN96: 0.00050981041 | AO96: 0.00034446649 | AP96: 0.1911 | AQ96: 0.0011994115 | AR96: -2.9272035e-08 | AS96: 1.0494954 | AT96: 1.1092635 | AU96: 1.0494954 | AV96: 1.5233625
A97: 45583 | B97: FALSE | C97: FALSE | D97: 2024ESZ | E97: C5 | F97: 5909.225 | H97: 0 | I97: 500.45835 | J97: 0.0483 | K97: 12840.3 | L97: 12844.718 | M97: 472.50851 | O97: 19.11 | P97: 12844.718 | Q97: 1.0000719 | T97: 0.053703051 | U97: 0.0670375 | V97: 0.077370009 | W97: 0.077370009 | X97: 1.408053e-05 | Z97: 0.10901123 | AA97: 0.10080154 | AB97: 1.536379 | AC97: 8.9312882e-05 | AD97: 496.8195 | AE97: 499.89287 | AG97: 496.8195 | AI97: 3.5380454e-09 | AK97: 470.54017 | AL97: 477.59827 | AM97: 463.48207 | AN97: 0.00034446649 | AO97: 0.00017912257 | AP97: 0.1911 | AQ97: 1.408053e-05 | AR97: -2.2981617e-14 | AS97: 1.0494954 | AT97: 1.1090595 | AU97: 1.0494954 | AV97: 1.536379
A98: 45583 | B98: FALSE | C98: FALSE | D98: 2024ESZ | E98: C6 | F98: 5910.425 | H98: 0 | I98: 500.45835 | J98: 0.0483 | K98: 12840.3 | L98: 12847.511 | M98: 472.61125 | O98: 19.11 | P98: 12847.511 | Q98: 1.0002031 | T98: 0.053703051 | U98: 0.065033745 | V98: 0.076217035 | W98: 0.076217035 | X98: 0 | Z98: 0.10901123 | AA98: 0.10051495 | AB98: 1.5599322 | AC98: 0.00033172027 | AD98: 496.8195 | AE98: 500.0587 | AG98: 496.8195 | AI98: 4.7271382e-08 | AK98: 470.54017 | AL98: 477.59827 | AM98: 463.48207 | AN98: 0.00017912257 | AO98: 0 | AP98: 0.1911 | AQ98: 0 | AR98: 0 | AS98: 1.0494954 | AT98: 1.1098136 | AU98: 1.0494954 | AV98: 1.5599322
A99: 45583 | B99: FALSE | C99: FALSE | D99: 2024ESZ | E99: C7 | F99: 5905.3 | G99: usual | H99: 0 | I99: 500.45835 | J99: 0.0483 | K99: 12840.3 | L99: 12836.988 | M99: 472.22415 | N99: 476.68773 | O99: 19.11 | P99: 12836.988 | Q99: 0.99913289 | R99: 476.68773 | S99: 0.052223566 | T99: 0.053703051 | U99: 0.063613586 | V99: 0.075301375 | W99: 0.075301375 | X99: 0 | Y99: 0.10919048 | Z99: 0.10901123 | AA99: 0.10028523 | AB99: 1.5835301 | AC99: -0.0012800521 | AD99: 496.8195 | AE99: 499.4186 | AF99: 499.4186 | AG99: 496.8195 | AH99: 45583 | AI99: 6.7142419e-07 | AJ99: 472.22415 | AK99: 470.54017 | AL99: 477.59827 | AM99: 463.48207 | AN99: 0 | AO99: 0.0010058422 | AP99: 0.1911 | AQ99: 0 | AR99: 0 | AS99: 1.0494954 | AT99: 1.1117773 | AU99: 1.0494954 | AV99: 1.5835301
A100: 45586 | B100: FALSE | C100: FALSE | D100: 2024ESZ | E100: C1 | F100: 5902.825 | H100: 0 | I100: 499.63216 | J100: 0.0483 | K100: 12817.388 | L100: 12834.865 | M100: 471.94054 | O100: 18.03 | P100: 12834.865 | Q100: 0.99958088 | T100: 0.052223566 | U100: 0.061984561 | V100: 0.074291908 | W100: 0.074291908 | X100: -0.0011908395 | Z100: 0.10919048 | AA100: 0.099959539 | AB100: 1.6006325 | AC100: -0.00099441002 | AD100: 499.4186 | AE100: 498.92197 | AG100: 499.4186 | AI100: 3.6091051e-07 | AK100: 472.22415 | AL100: 479.30751 | AM100: 465.14079 | AN100: 0.0010058422 | AO100: 0.00084049824 | AP100: 0.1803 | AQ100: 0.0015349746 | AR100: -0.002725814 | AS100: 1.0480855 | AT100: 1.1133448 | AU100: 1.0480855 | AV100: 1.6006325
...

Sheet Prev Calc
A1: Window | B1: FUTURE TWAP Current | C1: FUTURE TWAP Next | D1: INDEX TWAP | E1: Date | F1: CODE | G1: IS_PARTIAL | H1: IS_ROLL | I1: EXPERY_DAY | J1: 3 DAYS BEFORE EXPERY | K1: IS_EXPIRY | L1: ES1_PAR_C4_FIX | M1: ES_ROLL_FIX | N1: SwitchESData | O1: ES_TWAP | P1: ES_TWAP_RATIO | Q1: ROLL_FUT_IDX | R1: SP_TWAP_PAR_C4_FIX | S1: SP_TWAP_ROLL_FIX | T1: DATE_FOR_FT | U1: SPXT_Last | V1: ROLL_FUT_IDX_Last | W1: FINAN_FEE | X1: FINAN_FEE_FOR_CALC | Y1: SP_TWAP_RATIO | Z1: FINAL_TWAP_RATIO | AA1: EQ_INTRA_LVL | AB1: EQ_LOGRET | AC1: EQ_LOGRETsqrt | AD1: EQVOL_ST | AE1: EQVOL_LT | AF1: EQVOL | AG1: EQ_LAST_LVL | AH1: EQ_LVL_FOR_STRIKE | AI1: VIX_FOR_DELTA | AJ1: CALL_STRIKE | AK1: PUT_STRIKE | AL1: ITTE | AM1: ITTE T+1 AUX | AN1: DELTA_CALL | AP1: DELTA | AQ1: DAILY_120D_VOL | AR1: DAILY_120D_VOL_FOR_VAF | AS1: DAILY_120D_VAF | AT1: INTRADAY_21D_VAF | AU1: TargetPart | AV1: FCVHL | AW1: FCVHL_RETURN | AX1: PARTICIPATION | AY1: INTRADAY_21D_VOL | AZ1: ICL_DATE | BA1: ICL | BB1: OFFICIAL LVL | BC1: ABS DIFF | BD1: DATE
A2: C1 | B2: 4602.675 | C2: 0 | D2: 9844.3 | E2: 45139 | F2: 2023-08-01C1 | G2: FALSE | H2: FALSE | I2: FALSE | J2: FALSE | K2: FALSE | L2: 4602.675 | M2: 4602.675 | N2: FALSE | O2: 4602.675 | P2: 0.99907748 | Q2: 393.6944 | R2: 9844.3 | S2: 9844.3 | X2: 0.0533 | Y2: 0.99916907 | Z2: 0.99916907 | AA2: 390.03774 | AB2: -0.000831274 | AC2: 6.91e-07 | AD2: 0.11062399 | AE2: 0.10778051 | AF2: 0.11062399 | AH2: 390.3621 | AI2: 13.63 | AJ2: 396.21753 | AK2: 384.50667 | AL2: 0.001005842 | AM2: 0.000840498 | AN2: 3.5e-05 | AO2: -0.00014938 | AP2: -0.000114369 | AR2: 0.11926823 | AS2: 0.96145323 | AT2: 0.9757315 | AU2: 0.97194628 | AV2: 425.29817 | AW2: -0.000798742 | AX2: 0.97194628 | AY2: 0.11760163 | BD2: 45139
A3: C2 | B3: 4600.125 | C3: 0 | D3: 9839.071 | E3: 45139 | F3: 2023-08-01C2 | G3: FALSE | H3: FALSE | I3: FALSE | J3: FALSE | K3: FALSE | L3: 4600.125 | M3: 4600.125 | N3: FALSE | O3: 4600.125 | P3: 0.99944597 | Q3: 393.47629 | R3: 9839.071 | S3: 9839.071 | X3: 0.0533 | Y3: 0.99946883 | Z3: 0.99946883 | AA3: 389.83056 | AB3: -0.000531311 | AC3: 2.82e-07 | AD3: 0.10739313 | AE3: 0.10622184 | AF3: 0.10739313 | AH3: 390.3621 | AI3: 13.63 | AJ3: 396.21753 | AK3: 384.50667 | AL3: 0.000840498 | AM3: 0.000675154 | AN3: 2.25e-06 | AO3: -5.13e-05 | AP3: -4.9e-05 | AR3: 0.11926823 | AS3: 0.96145323 | AT3: 0.97685333 | AU3: 0.99948593 | AV3: 425.07743 | AW3: -0.000519023 | AX3: 0.99948593 | AY3: 0.11756638 | BD3: 45139
A4: C3 | B4: 4596.4 | C4: 0 | D4: 9831.735 | E4: 45139 | F4: 2023-08-01C3 | G4: FALSE | H4: FALSE | I4: FALSE | J4: FALSE | K4: FALSE | L4: 4596.4 | M4: 4596.4 | N4: FALSE | O4: 4596.4 | P4: 0.99919024 | Q4: 393.15767 | R4: 9831.735 | S4: 9831.735 | X4: 0.0533 | Y4: 0.9992544 | Z4: 0.9992544 | AA4: 389.5399 | AB4: -0.000745877 | AC4: 5.56e-07 | AD4: 0.10440388 | AE4: 0.10475699 | AF4: 0.10475699 | AH4: 390.3621 | AI4: 13.63 | AJ4: 396.21753 | AK4: 384.50667 | AL4: 0.000675154 | AM4: 0.00050981 | AN4: 1.68e-08 | AO4: -1.18e-05 | AP4: -1.18e-05 | AR4: 0.11926823 | AS4: 0.96145323 | AT4: 0.97717411 | AU4: 1.0295549 | AV4: 424.75938 | AW4: -0.000748222 | AX4: 1.0295549 | AY4: 0.11750051 | BD4: 45139
A5: C4 | B5: 4597.25 | C5: 0 | D5: 9833.261 | E5: 45139 | F5: 2023-08-01C4 | G5: FALSE | H5: FALSE | I5: FALSE | J5: FALSE | K5: FALSE | L5: 4597.25 | M5: 4597.25 | N5: FALSE | O5: 4597.25 | P5: 1.0001849 | Q5: 393.23037 | R5: 9833.261 | S5: 9833.261 | X5: 0.0533 | Y5: 1.0001552 | Z5: 1.0001552 | AA5: 389.60036 | AB5: 0.0001552 | AC5: 2.41e-08 | AD5: 0.10123591 | AE5: 0.10317985 | AF5: 0.10317985 | AH5: 390.3621 | AI5: 13.63 | AJ5: 396.21753 | AK5: 384.50667 | AL5: 0.00050981 | AM5: 0.000344466 | AN5: 1.4e-11 | AO5: -9.77e-08 | AP5: -9.77e-08 | AR5: 0.11926823 | AS5: 0.96145323 | AT5: 0.977773 | AU5: 1.0554629 | AV5: 424.82616 | AW5: 0.000157208 | AX5: 1.0554629 | AY5: 0.11023706 | BD5: 45139
A6: C5 | B6: 4598.9125 | C6: 0 | D6: 9837.032 | E6: 45139 | F6: 2023-08-01C5 | G6: FALSE | H6: FALSE | I6: FALSE | J6: FALSE | K6: FALSE | L6: 4598.9125 | M6: 4598.9125 | N6: FALSE | O6: 4598.9125 | P6: 1.0003616 | Q6: 393.37257 | R6: 9837.032 | S6: 9837.032 | X6: 0.0533 | Y6: 1.0003835 | Z6: 1.0003835 | AA6: 389.74977 | AB6: 0.000383421 | AC6: 1.47e-07 | AD6: 0.098231087 | AE6: 0.10165864 | AF6: 0.10165864 | AH6: 390.3621 | AI6: 13.63 | AJ6: 396.21753 | AK6: 384.50667 | AL6: 0.000344466 | AM6: 0.000179123 | AN6: 9.28e-20 | AO6: -5.62e-14 | AP6: -5.62e-14 | AR6: 0.11926823 | AS6: 0.96145323 | AT6: 1.0397684 | AU6: 1.0715961 | AV6: 424.99743 | AW6: 0.000403151 | AX6: 1.0715961 | AY6: 0.11023496 | BD6: 45139
A7: C6 | B7: 4603.85 | C7: 0 | D7: 9847.978 | E7: 45139 | F7: 2023-08-01C6 | G7: FALSE | H7: FALSE | I7: FALSE | J7: FALSE | K7: FALSE | L7: 4603.85 | M7: 4603.85 | N7: FALSE | O7: 4603.85 | P7: 1.0010736 | Q7: 393.79491 | R7: 9847.978 | S7: 9847.978 | X7: 0.0533 | Y7: 1.0011127 | Z7: 1.0011127 | AA7: 390.18346 | AB7: 0.001112115 | AC7: 1.24e-06 | AD7: 0.095923348 | AE7: 0.10044847 | AF7: 0.10044847 | AH7: 390.3621 | AI7: 13.63 | AJ7: 396.21753 | AK7: 384.50667 | AL7: 0.000179123 | AM7: 0 | AN7: 0 | AO7: 0 | AP7: 0 | AR7: 0.11926823 | AS7: 0.96145323 | AT7: 1.0397853 | AU7: 1.0876314 | AV7: 425.50351 | AW7: 0.001190798 | AX7: 1.0876314 | AY7: 0.11023177 | BD7: 45139
A8: C7 | B8: 4602.9 | C8: 0 | D8: 9845.137 | E8: 45139 | F8: 2023-08-01C7 | G8: FALSE | H8: FALSE | I8: FALSE | J8: FALSE | K8: FALSE | L8: 4602.9 | M8: 4602.9 | N8: FALSE | O8: 4602.9 | P8: 0.99979365 | Q8: 393.71365 | R8: 9845.137 | S8: 9845.137 | T8: 45139 | U8: 9845.137 | V8: 393.71365 | W8: 0.0533 | X8: 0.0533 | Y8: 0.99971151 | Z8: 0.99971151 | AA8: 390.0709 | AB8: -0.000288527 | AC8: 8.32e-08 | AD8: 0.093048494 | AE8: 0.098952534 | AF8: 0.098952534 | AG8: 390.0709 | AH8: 390.3621 | AI8: 13.63 | AJ8: 396.21753 | AK8: 384.50667 | AL8: 0 | AN8: 0 | AO8: 0 | AP8: 0 | AQ8: 0.11862292 | AR8: 0.11926823 | AS8: 0.96145323 | AT8: 1.0398108 | AU8: 1.1007347 | AV8: 425.36945 | AW8: -0.000315076 | AX8: 1.1007347 | AY8: 0.10998393 | AZ8: 45139 | BA8: 425.36945 | BB8: 425.36944 | BC8: 7.09e-06 | BD8: 45139
A9: C1 | B9: 4564.425 | C9: 0 | D9: 9765.052 | E9: 45140 | F9: 2023-08-02C1 | G9: FALSE | H9: FALSE | I9: FALSE | J9: FALSE | K9: FALSE | L9: 4564.425 | M9: 4564.425 | N9: FALSE | O9: 4564.425 | P9: 0.99164114 | Q9: 390.42265 | R9: 9765.052 | S9: 9765.052 | X9: 0.0533 | Y9: 0.99171747 | Z9: 0.99171747 | AA9: 386.84013 | AB9: -0.008317019 | AC9: 6.92e-05 | AD9: 0.12433741 | AE9: 0.11471042 | AF9: 0.12433741 | AH9: 390.0709 | AI9: 13.93 | AJ9: 395.92196 | AK9: 384.21984 | AL9: 0.001005842 | AM9: 0.000840498 | AN9: 4.62e-09 | AO9: -0.045996441 | AP9: -0.045996437 | AR9: 0.11862292 | AS9: 0.96747103 | AT9: 1.0417934 | AU9: 1.1243691 | AV9: 421.4845 | AW9: -0.009133119 | AX9: 1.1243691 | AY9: 0.11457859 | BD9: 45140
A10: C2 | B10: 4545.825 | C10: 0 | D10: 9725.409 | E10: 45140 | F10: 2023-08-02C2 | G10: FALSE | H10: FALSE | I10: FALSE | J10: FALSE | K10: FALSE | L10: 4545.825 | M10: 4545.825 | N10: FALSE | O10: 4545.825 | P10: 0.99592501 | Q10: 388.83168 | R10: 9725.409 | S10: 9725.409 | X10: 0.0533 | Y10: 0.99594032 | Z10: 0.99594032 | AA10: 385.26968 | AB10: -0.004067944 | AC10: 1.65e-05 | AD10: 0.12760745 | AE10: 0.11678808 | AF10: 0.12760745 | AH10: 390.0709 | AI10: 13.93 | AJ10: 395.92196 | AK10: 384.21984 | AL10: 0.000840498 | AM10: 0.000675154 | AN10: 2.47e-14 | AO10: -0.22491925 | AP10: -0.22491925 | AR10: 0.11862292 | AS10: 0.96747103 | AT10: 1.0036511 | AU10: 0.85007571 | AV10: 419.55006 | AW10: -0.00458958 | AX10: 0.87436906 | AY10: 0.11572065 | BD10: 45140
A11: C3 | B11: 4543.35 | C11: 0 | D11: 9720.508 | E11: 45140 | F11: 2023-08-02C3 | G11: FALSE | H11: FALSE | I11: FALSE | J11: FALSE | K11: FALSE | L11: 4543.35 | M11: 4543.35 | N11: FALSE | O11: 4543.35 | P11: 0.99945554 | Q11: 388.61998 | R11: 9720.508 | S11: 9720.508 | X11: 0.0533 | Y11: 0.99949606 | Z11: 0.99949606 | AA11: 385.07553 | AB11: -0.000504065 | AC11: 2.54e-07 | AD11: 0.12382865 | AE11: 0.11508135 | AF11: 0.12382865 | AH11: 390.0709 | AI11: 13.93 | AJ11: 395.92196 | AK11: 384.21984 | AL11: 0.000675154 | AM11: 0.00050981 | AN11: 5.23e-19 | AO11: -0.23920444 | AP11: -0.23920444 | AR11: 0.11862292 | AS11: 0.96747103 | AT11: 0.99369398 | AU11: 0.68007118 | AV11: 419.35704 | AW11: -0.000460057 | AX11: 0.68007118 | AY11: 0.11573302 | BD11: 45140
A12: C4 | B12: 4543.15 | C12: 0 | D12: 9720.296 | E12: 45140 | F12: 2023-08-02C4 | G12: FALSE | H12: FALSE | I12: FALSE | J12: FALSE | K12: FALSE | L12: 4543.15 | M12: 4543.15 | N12: FALSE | O12: 4543.15 | P12: 0.99995598 | Q12: 388.60287 | R12: 9720.296 | S12: 9720.296 | X12: 0.0533 | Y12: 0.99997819 | Z12: 0.99997819 | AA12: 385.06713 | AB12: -2.18e-05 | AC12: 4.76e-10 | AD12: 0.12005654 | AE12: 0.1133421 | AF12: 0.12005654 | AH12: 390.0709 | AI12: 13.93 | AJ12: 395.92196 | AK12: 384.21984 | AL12: 0.00050981 | AM12: 0.000344466 | AN12: 2.92e-27 | AO12: -0.19674261 | AP12: -0.19674261 | AR12: 0.11862292 | AS12: 0.96747103 | AT12: 0.99358504 | AU12: 0.68285465 | AV12: 419.3507 | AW12: -1.51e-05 | AX12: 0.68285465 | AY12: 0.11558212 | BD12: 45140
A13: C5 | B13: 4542.925 | C13: 0 | D13: 9719.164 | E13: 45140 | F13: 2023-08-02C5 | G13: FALSE | H13: FALSE | I13: FALSE | J13: FALSE | K13: FALSE | L13: 4542.925 | M13: 4542.925 | N13: FALSE | O13: 4542.925 | P13: 0.99995048 | Q13: 388.58363 | R13: 9719.164 | S13: 9719.164 | X13: 0.0533 | Y13: 0.99988354 | Z13: 0.99988354 | AA13: 385.02228 | AB13: -0.000116464 | AC13: 1.36e-08 | AD13: 0.1164053 | AE13: 0.11163224 | AF13: 0.1164053 | AH13: 390.0709 | AI13: 13.93 | AJ13: 395.92196 | AK13: 384.21984 | AL13: 0.000344466 | AM13: 0.000179123 | AN13: 5.54e-51 | AO13: -0.13135605 | AP13: -0.13135605 | AR13: 0.11862292 | AS13: 0.96747103 | AT13: 0.99491234 | AU13: 0.74137849 | AV13: 419.3149 | AW13: -8.54e-05 | AX13: 0.74137849 | AY13: 0.11558179 | BD13: 45140
A14: C6 | B14: 4540.675 | C14: 0 | D14: 9714.58 | E14: 45140 | F14: 2023-08-02C6 | G14: FALSE | H14: FALSE | I14: FALSE | J14: FALSE | K14: FALSE | L14: 4540.675 | M14: 4540.675 | N14: FALSE | O14: 4540.675 | P14: 0.99950472 | Q14: 388.39117 | R14: 9714.58 | S14: 9714.58 | X14: 0.0533 | Y14: 0.99952835 | Z14: 0.99952835 | AA14: 384.84069 | AB14: -0.000471757 | AC14: 2.23e-07 | AD14: 0.11296343 | AE14: 0.10999855 | AF14: 0.11296343 | AH14: 390.0709 | AI14: 13.93 | AJ14: 395.92196 | AK14: 384.21984 | AL14: 0.000179123 | AM14: 0 | AN14: 0 | AO14: 0 | AP14: 0 | AR14: 0.11862292 | AS14: 0.96747103 | AT14: 0.99491521 | AU14: 0.8315384 | AV14: 419.1645 | AW14: -0.000358684 | AX14: 0.8315384 | AY14: 0.11556505 | BD14: 45140
A15: C7 | B15: 4538.375 | C15: 0 | D15: 9709.585 | E15: 45140 | F15: 2023-08-02C7 | G15: FALSE | H15: FALSE | I15: FALSE | J15: FALSE | K15: FALSE | L15: 4538.375 | M15: 4538.375 | N15: FALSE | O15: 4538.375 | P15: 0.99949347 | Q15: 388.19444 | R15: 9709.585 | S15: 9709.585 | T15: 45140 | U15: 9709.585 | V15: 388.19444 | W15: 0.0533 | X15: 0.0533 | Y15: 0.99948582 | Z15: 0.99948582 | AA15: 384.64281 | AB15: -0.000514308 | AC15: 2.65e-07 | AD15: 0.10964985 | AE15: 0.1084006 | AF15: 0.10964985 | AG15: 384.64281 | AH15: 390.0709 | AI15: 13.93 | AJ15: 395.92196 | AK15: 384.21984 | AL15: 0 | AN15: 0 | AO15: 0 | AP15: 0 | AQ15: 0.12042 | AR15: 0.11862292 | AS15: 0.96747103 | AT15: 0.99506226 | AU15: 0.98491313 | AV15: 418.979 | AW15: -0.000442557 | AX15: 0.9815384 | AY15: 0.1155642 | AZ15: 45140 | BA15: 418.979 | BB15: 418.97899 | BC15: 7.1e-06 | BD15: 45140
A16: C1 | B16: 4516.925 | C16: 0 | D16: 9667.663 | E16: 45141 | F16: 2023-08-03C1 | G16: FALSE | H16: FALSE | I16: FALSE | J16: FALSE | K16: FALSE | L16: 4516.925 | M16: 4516.925 | N16: FALSE | O16: 4516.925 | P16: 0.99527364 | Q16: 386.35969 | R16: 9667.663 | S16: 9667.663 | X16: 0.0533 | Y16: 0.99553435 | Z16: 0.99553435 | AA16: 382.92514 | AB16: -0.004475646 | AC16: 2e-05 | AD16: 0.11585261 | AE16: 0.11161644 | AF16: 0.11585261 | AH16: 384.64281 | AI16: 16.09 | AJ16: 390.41246 | AK16: 378.87317 | AL16: 0.001005842 | AM16: 0.000840498 | AN16: 1.67e-05 | AO16: -0.011219327 | AP16: -0.011202623 | AR16: 0.12042 | AS16: 0.95053559 | AT16: 0.99506975 | AU16: 0.99691514 | AV16: 417.13606 | AW16: -0.004398628 | AX16: 0.99691514 | AY16: 0.11635593 | BD16: 45141
A17: C2 | B17: 4514.35 | C17: 0 | D17: 9662.681 | E17: 45141 | F17: 2023-08-03C2 | G17: FALSE | H17: FALSE | I17: FALSE | J17: FALSE | K17: FALSE | L17: 4514.35 | M17: 4514.35 | N17: FALSE | O17: 4514.35 | P17: 0.99942992 | Q17: 386.13944 | R17: 9662.681 | S17: 9662.681 | X17: 0.0533 | Y17: 0.99948467 | Z17: 0.99948467 | AA17: 382.72781 | AB17: -0.000515459 | AC17: 2.66e-07 | AD17: 0.11244838 | AE17: 0.10999338 | AF17: 0.11244838 | AH17: 384.64281 | AI17: 16.09 | AJ17: 390.41246 | AK17: 378.87317 | AL17: 0.000840498 | AM17: 0.000675154 | AN17: 1e-06 | AO17: -0.007690198 | AP17: -0.007689196 | AR17: 0.12042 | AS17: 0.95053559 | AT17: 0.98806865 | AU17: 0.93410478 | AV17: 416.91915 | AW17: -0.000520018 | AX17: 0.93410478 | AY17: 0.11635262 | BD17: 45141
A18: C3 | B18: 4527.125 | C18: 0 | D18: 9690.477 | E18: 45141 | F18: 2023-08-03C3 | G18: FALSE | H18: FALSE | I18: FALSE | J18: FALSE | K18: FALSE | L18: 4527.125 | M18: 4527.125 | N18: FALSE | O18: 4527.125 | P18: 1.0028299 | Q18: 387.23216 | R18: 9690.477 | S18: 9690.477 | X18: 0.0533 | Y18: 1.0028766 | Z18: 1.0028766 | AA18: 383.82877 | AB18: 0.002872505 | AC18: 8.25e-06 | AD18: 0.11295697 | AE18: 0.1103279 | AF18: 0.11295697 | AH18: 384.64281 | AI18: 16.09 | AJ18: 390.41246 | AK18: 378.87317 | AL18: 0.000675154 | AM18: 0.00050981 | AN18: 1.44e-06 | AO18: -0.000172587 | AP18: -0.000171149 | AR18: 0.12042 | AS18: 0.95053559 | AT18: 0.98809806 | AU18: 0.96238356 | AV18: 418.03826 | AW18: 0.00268425 | AX18: 0.96238356 | AY18: 0.11670178 | BD18: 45141
A19: C4 | B19: 4538.225 | C19: 0 | D19: 9714.581 | E19: 45141 | F19: 2023-08-03C4 | G19: FALSE | H19: FALSE | I19: FALSE | J19: FALSE | K19: FALSE | L19: 4538.225 | M19: 4538.225 | N19: FALSE | O19: 4538.225 | P19: 1.0024519 | Q19: 388.18161 | R19: 9714.581 | S19: 9714.581 | X19: 0.0533 | Y19: 1.0024874 | Z19: 1.0024874 | AA19: 384.7835 | AB19: 0.002484302 | AC19: 6.17e-06 | AD19: 0.11245861 | AE19: 0.11015302 | AF19: 0.11245861 | AH19: 384.64281 | AI19: 16.09 | AJ19: 390.41246 | AK19: 378.87317 | AL19: 0.00050981 | AM19: 0.000344466 | AN19: 5.82e-07 | AO19: -1.08e-07 | AP19: 4.74e-07 | AR19: 0.12042 | AS19: 0.95053559 | AT19: 0.9849796 | AU19: 0.96772775 | AV19: 419.03875 | AW19: 0.002393289 | AX19: 0.96772775 | AY19: 0.11682761 | BD19: 45141
A20: C5 | B20: 4531.45 | C20: 0 | D20: 9699.407 | E20: 45141 | F20: 2023-08-03C5 | G20: FALSE | H20: FALSE | I20: FALSE | J20: FALSE | K20: FALSE | L20: 4531.45 | M20: 4531.45 | N20: FALSE | O20: 4531.45 | P20: 0.99850713 | Q20: 387.6021 | R20: 9699.407 | S20: 9699.407 | X20: 0.0533 | Y20: 0.99843802 | Z20: 0.99843802 | AA20: 384.18248 | AB20: -0.001563203 | AC20: 2.44e-06 | AD20: 0.11021231 | AE20: 0.1090825 | AF20: 0.11021231 | AH20: 384.64281 | AI20: 16.09 | AJ20: 390.41246 | AK20: 378.87317 | AL20: 0.000344466 | AM20: 0.000179123 | AN20: 4.04e-14 | AO20: -5.12e-11 | AP20: -5.12e-11 | AR20: 0.12042 | AS20: 0.95053559 | AT20: 0.98385105 | AU20: 0.97201622 | AV20: 418.40516 | AW20: -0.001512002 | AX20: 0.97201622 | AY20: 0.11692827 | BD20: 45141
A21: C6 | B21: 4530.725 | C21: 0 | D21: 9698.152 | E21: 45141 | F21: 2023-08-03C6 | G21: FALSE | H21: FALSE | I21: FALSE | J21: FALSE | K21: FALSE | L21: 4530.725 | M21: 4530.725 | N21: FALSE | O21: 4530.725 | P21: 0.99984001 | Q21: 387.54009 | R21: 9698.152 | S21: 9698.152 | X21: 0.0533 | Y21: 0.99987061 | Z21: 0.99987061 | AA21: 384.13277 | AB21: -0.000129398 | AC21: 1.67e-08 | AD21: 0.10686309 | AE21: 0.10743793 | AF21: 0.10743793 | AH21: 384.64281 | AI21: 16.09 | AJ21: 390.41246 | AK21: 378.87317 | AL21: 0.000179123 | AM21: 0 | AN21: 0 | AO21: 0 | AP21: 0 | AR21: 0.12042 | AS21: 0.95053559 | AT21: 0.98294645 | AU21: 0.99182742 | AV21: 418.35171 | AW21: -0.00012775 | AX21: 0.99182742 | AY21: 0.11692795 | BD21: 45141
A22: C7 | B22: 4524.875 | C22: 0 | D22: 9686.459 | E22: 45141 | F22: 2023-08-03C7 | G22: FALSE | H22: FALSE | I22: FALSE | J22: FALSE | K22: FALSE | L22: 4524.875 | M22: 4524.875 | N22: FALSE | O22: 4524.875 | P22: 0.99870882 | Q22: 387.0397 | R22: 9686.459 | S22: 9686.459 | T22: 45141 | U22: 9686.459 | V22: 387.0397 | W22: 0.054212124 | X22: 0.0533 | Y22: 0.99879431 | Z22: 0.99879431 | AA22: 383.66962 | AB22: -0.001206421 | AC22: 1.46e-06 | AD22: 0.10434837 | AE22: 0.10617742 | AF22: 0.10617742 | AG22: 383.66962 | AH22: 384.64281 | AI22: 16.09 | AJ22: 390.41246 | AK22: 378.87317 | AL22: 0 | AN22: 0 | AO22: 0 | AP22: 0 | AQ22: 0.12027019 | AR22: 0.12042 | AS22: 0.95053559 | AT22: 0.98294937 | AU22: 1.0174395 | AV22: 417.85036 | AW22: -0.001198401 | AX22: 1.0174395 | AY22: 0.11700796 | AZ22: 45141 | BA22: 417.85036 | BB22: 417.85035 | BC22: 7.06e-06 | BD22: 45141
A23: C1 | B23: 4545.025 | C23: 0 | D23: 9730.621 | E23: 45142 | F23: 2023-08-04C1 | G23: FALSE | H23: FALSE | I23: FALSE | J23: FALSE | K23: FALSE | L23: 4545.025 | M23: 4545.025 | N23: FALSE | O23: 4545.025 | P23: 1.0044532 | Q23: 388.76325 | R23: 9730.621 | S23: 9730.621 | X23: 0.054212124 | Y23: 1.0044086 | Z23: 1.0044086 | AA23: 385.36105 | AB23: 0.00439887 | AC23: 1.94e-05 | AD23: 0.11082995 | AE23: 0.10935922 | AF23: 0.11082995 | AH23: 383.66962 | AI23: 15.92 | AJ23: 389.42467 | AK23: 377.91458 | AL23: 0.001005842 | AM23: 0.000840498 | AN23: 0.011590109 | AO23: -1.17e-05 | AP23: 0.011578423 | AR23: 0.12027019 | AS23: 0.95196864 | AT23: 0.98222913 | AU23: 1.0310704 | AV23: 419.71823 | AW23: 0.00447019 | AX23: 1.0310704 | AY23: 0.10995552 | BD23: 45142
A24: C2 | B24: 4542.225 | C24: 0 | D24: 9724.96 | E24: 45142 | F24: 2023-08-04C2 | G24: FALSE | H24: FALSE | I24: FALSE | J24: FALSE | K24: FALSE | L24: 4542.225 | M24: 4542.225 | N24: FALSE | O24: 4542.225 | P24: 0.99938394 | Q24: 388.52375 | R24: 9724.96 | S24: 9724.96 | X24: 0.054212124 | Y24: 0.99941823 | Z24: 0.99941823 | AA24: 385.13686 | AB24: -0.000581941 | AC24: 3.39e-07 | AD24: 0.10762028 | AE24: 0.10778951 | AF24: 0.10778951 | AH24: 383.66962 | AI24: 15.92 | AJ24: 389.42467 | AK24: 377.91458 | AL24: 0.000840498 | AM24: 0.000675154 | AN24: 0.003742674 | AO24: -2.34e-06 | AP24: 0.003740332 | AR24: 0.12027019 | AS24: 0.95196864 | AT24: 1.0420202 | AU24: 0.997665 | AV24: 419.46506 | AW24: -0.000603188 | AX24: 0.997665 | AY24: 0.10934561 | BD24: 45142
A25: C3 | B25: 4549.775 | C25: 0 | D25: 9741.2 | E25: 45142 | F25: 2023-08-04C3 | G25: FALSE | H25: FALSE | I25: FALSE | J25: FALSE | K25: FALSE | L25: 4549.775 | M25: 4549.775 | N25: FALSE | O25: 4549.775 | P25: 1.0016622 | Q25: 389.16955 | R25: 9741.2 | S25: 9741.2 | X25: 0.054212124 | Y25: 1.0016699 | Z25: 1.0016699 | AA25: 385.78001 | AB25: 0.001668537 | AC25: 2.78e-06 | AD25: 0.1057443 | AE25: 0.106852 | AF25: 0.106852 | AH25: 383.66962 | AI25: 15.92 | AJ25: 389.42467 | AK25: 377.91458 | AL25: 0.000675154 | AM25: 0.00050981 | AN25: 0.004472738 | AO25: -4.95e-09 | AP25: 0.004472733 | AR25: 0.12027019 | AS25: 0.95196864 | AT25: 1.0468618 | AU25: 1.0156498 | AV25: 420.16314 | AW25: 0.001664232 | AX25: 1.0156498 | AY25: 0.10942462 | BD25: 45142
A26: C4 | B26: 4559.525 | C26: 0 | D26: 9761.688 | E26: 45142 | F26: 2023-08-04C4 | G26: FALSE | H26: FALSE | I26: FALSE | J26: FALSE | K26: FALSE | L26: 4559.525 | M26: 4559.525 | N26: FALSE | O26: 4559.525 | P26: 1.002143 | Q26: 390.00353 | R26: 9761.688 | S26: 9761.688 | X26: 0.054212124 | Y26: 1.0021032 | Z26: 1.0021032 | AA26: 386.5914 | AB26: 0.002101023 | AC26: 4.41e-06 | AD26: 0.10477669 | AE26: 0.10634112 | AF26: 0.10634112 | AH26: 383.66962 | AI26: 15.92 | AJ26: 389.42467 | AK26: 377.91458 | AL26: 0.00050981 | AM26: 0.000344466 | AN26: 0.00675823 | AO26: -7.66e-15 | AP26: 0.00675823 | AR26: 0.12027019 | AS26: 0.95196864 | AT26: 1.0462374 | AU26: 1.024561 | AV26: 421.0603 | AW26: 0.002135256 | AX26: 1.024561 | AY26: 0.1095498 | BD26: 45142
A27: C5 | B27: 4546.65 | C27: 0 | D27: 9734.577 | E27: 45142 | F27: 2023-08-04C5 | G27: FALSE | H27: FALSE | I27: FALSE | J27: FALSE | K27: FALSE | L27: 4546.65 | M27: 4546.65 | N27: FALSE | O27: 4546.65 | P27: 0.99717624 | Q27: 388.90225 | R27: 9734.577 | S27: 9734.577 | X27: 0.054212124 | Y27: 0.99722271 | Z27: 0.99722271 | AA27: 385.51772 | AB27: -0.00278115 | AC27: 7.73e-06 | AD27: 0.10553727 | AE27: 0.10667008 | AF27: 0.10667008 | AH27: 383.66962 | AI27: 15.92 | AJ27: 389.42467 | AK27: 377.91458 | AL27: 0.000344466 | AM27: 0.000179123 | AN27: 1.12e-06 | AO27: 0 | AP27: 1.12e-06 | AR27: 0.12027019 | AS27: 0.95196864 | AT27: 1.0452463 | AU27: 1.039778 | AV27: 419.86153 | AW27: -0.002847021 | AX27: 1.039778 | AY27: 0.11003636 | BD27: 45142
A28: C6 | B28: 4505.775 | C28: 0 | D28: 9647.667 | E28: 45142 | F28: 2023-08-04C6 | G28: FALSE | H28: FALSE | I28: FALSE | J28: FALSE | K28: FALSE | L28: 4505.775 | M28: 4505.775 | N28: FALSE | O28: 4505.775 | P28: 0.99100986 | Q28: 385.40597 | R28: 9647.667 | S28: 9647.667 | X28: 0.054212124 | Y28: 0.99107203 | Z28: 0.99107203 | AA28: 382.07583 | AB28: -0.008968062 | AC28: 8.04e-05 | AD28: 0.13777565 | AE28: 0.1236661 | AF28: 0.13777565 | AH28: 383.66962 | AI28: 15.92 | AJ28: 389.42467 | AK28: 377.91458 | AL28: 0.000179123 | AM28: 0 | AN28: 0 | AO28: 0 | AP28: 0 | AR28: 0.12027019 | AS28: 0.95196864 | AT28: 1.0413747 | AU28: 1.0263083 | AV28: 415.96335 | AW28: -0.009284452 | AX28: 1.0263083 | AY28: 0.11478924 | BD28: 45142
A29: C7 | B29: 4496.825 | C29: 0 | D29: 9627.304 | E29: 45142 | F29: 2023-08-04C7 | G29: FALSE | H29: FALSE | I29: FALSE | J29: FALSE | K29: FALSE | L29: 4496.825 | M29: 4496.825 | N29: FALSE | O29: 4496.825 | P29: 0.99801366 | Q29: 384.64042 | R29: 9627.304 | S29: 9627.304 | T29: 45142 | U29: 9627.304 | V29: 384.64042 | W29: 0.053760245 | X29: 0.054212124 | Y29: 0.99788933 | Z29: 0.99788933 | AA29: 381.2694 | AB29: -0.002112896 | AC29: 4.46e-06 | AD29: 0.13533554 | AE29: 0.12276301 | AF29: 0.13533554 | AG29: 381.2694 | AH29: 383.66962 | AI29: 15.92 | AJ29: 389.42467 | AK29: 377.91458 | AL29: 0 | AN29: 0 | AO29: 0 | AP29: 0 | AQ29: 0.12072708 | AR29: 0.12027019 | AS29: 0.95196864 | AT29: 1.0018294 | AU29: 0.79459898 | AV29: 415.05265 | AW29: -0.002189365 | AX29: 0.79459898 | AY29: 0.11505488 | AZ29: 45142 | BA29: 415.05265 | BB29: 415.05265 | BC29: 7.01e-06 | BD29: 45142
A30: C1 | B30: 4517.75 | C30: 0 | D30: 9672.475 | E30: 45145 | F30: 2023-08-07C1 | G30: FALSE | H30: FALSE | I30: FALSE | J30: FALSE | K30: FALSE | L30: 4517.75 | M30: 4517.75 | N30: FALSE | O30: 4517.75 | P30: 1.0046533 | Q30: 386.43026 | R30: 9672.475 | S30: 9672.475 | X30: 0.053760245 | Y30: 1.004244 | Z30: 1.004244 | AA30: 382.88749 | AB30: 0.004234985 | AC30: 1.79e-05 | AD30: 0.13825707 | AE30: 0.12477083 | AF30: 0.13825707 | AH30: 381.2694 | AI30: 17.1 | AJ30: 386.98844 | AK30: 375.55036 | AL30: 0.001005842 | AM30: 0.000840498 | AN30: 0.015916387 | AO30: -4.7e-05 | AP30: 0.015869344 | AR30: 0.12072708 | AS30: 0.94758562 | AT30: 0.99952255 | AU30: 0.80520126 | AV30: 416.43458 | AW30: 0.003329524 | AX30: 0.80520126 | AY30: 0.11559742 | BD30: 45145
A31: C2 | B31: 4523.7 | C31: 0 | D31: 9685.827 | E31: 45145 | F31: 2023-08-07C2 | G31: FALSE | H31: FALSE | I31: FALSE | J31: FALSE | K31: FALSE | L31: 4523.7 | M31: 4523.7 | N31: FALSE | O31: 4523.7 | P31: 1.001317 | Q31: 386.9392 | R31: 9685.827 | S31: 9685.827 | X31: 0.053760245 | Y31: 1.0013804 | Z31: 1.0013804 | AA31: 383.41604 | AB31: 0.00137946 | AC31: 1.9e-06 | AD31: 0.13479436 | AE31: 0.12329407 | AF31: 0.13479436 | AH31: 381.2694 | AI31: 17.1 | AJ31: 386.98844 | AK31: 375.55036 | AL31: 0.000840498 | AM31: 0.000675154 | AN31: 0.01853275 | AO31: -1.53e-06 | AP31: 0.018531225 | AR31: 0.12072708 | AS31: 0.94758562 | AT31: 0.99477794 | AU31: 0.80395017 | AV31: 416.8974 | AW31: 0.001111384 | AX31: 0.80395017 | AY31: 0.11564063 | BD31: 45145
A32: C3 | B32: 4521.4 | C32: 0 | D32: 9681.132 | E32: 45145 | F32: 2023-08-07C3 | G32: FALSE | H32: FALSE | I32: FALSE | J32: FALSE | K32: FALSE | L32: 4521.4 | M32: 4521.4 | N32: FALSE | O32: 4521.4 | P32: 0.99949157 | Q32: 386.74247 | R32: 9681.132 | S32: 9681.132 | X32: 0.053760245 | Y32: 0.99951527 | Z32: 0.99951527 | AA32: 383.23018 | AB32: -0.000484846 | AC32: 2.35e-07 | AD32: 0.13078314 | AE32: 0.12148179 | AF32: 0.13078314 | AH32: 381.2694 | AI32: 17.1 | AJ32: 386.98844 | AK32: 375.55036 | AL32: 0.000675154 | AM32: 0.00050981 | AN32: 0.00577418 | AO32: -7.82e-08 | AP32: 0.005774102 | AR32: 0.12072708 | AS32: 0.94758562 | AT32: 0.9943981 | AU32: 0.8246027 | AV32: 416.73407 | AW32: -0.000391763 | AX32: 0.8246027 | AY32: 0.11561565 | BD32: 45145
A33: C4 | B33: 4524.55 | C33: 0 | D33: 9688.233 | E33: 45145 | F33: 2023-08-07C4 | G33: FALSE | H33: FALSE | I33: FALSE | J33: FALSE | K33: FALSE | L33: 4524.55 | M33: 4524.55 | N33: FALSE | O33: 4524.55 | P33: 1.0006967 | Q33: 387.0119 | R33: 9688.233 | S33: 9688.233 | X33: 0.053760245 | Y33: 1.0007335 | Z33: 1.0007335 | AA33: 383.51128 | AB33: 0.00073322 | AC33: 5.38e-07 | AD33: 0.12702313 | AE33: 0.11976452 | AF33: 0.12702313 | AH33: 381.2694 | AI33: 17.1 | AJ33: 386.98844 | AK33: 375.55036 | AL33: 0.00050981 | AM33: 0.000344466 | AN33: 0.002239306 | AO33: -1.91e-11 | AP33: 0.002239306 | AR33: 0.12072708 | AS33: 0.94758562 | AT33: 0.99461766 | AU33: 0.84156163 | AV33: 416.98542 | AW33: 0.000603141 | AX33: 0.84156163 | AY33: 0.11485469 | BD33: 45145
A34: C5 | B34: 4529.175 | C34: 0 | D34: 9698.46 | E34: 45145 | F34: 2023-08-07C5 | G34: FALSE | H34: FALSE | I34: FALSE | J34: FALSE | K34: FALSE | L34: 4529.175 | M34: 4529.175 | N34: FALSE | O34: 4529.175 | P34: 1.0010222 | Q34: 387.40751 | R34: 9698.46 | S34: 9698.46 | X34: 0.053760245 | Y34: 1.0010556 | Z34: 1.0010556 | AA34: 383.91612 | AB34: 0.001055054 | AC34: 1.11e-06 | AD34: 0.12363089 | AE34: 0.11820382 | AF34: 0.12363089 | AH34: 381.2694 | AI34: 17.1 | AJ34: 386.98844 | AK34: 375.55036 | AL34: 0.000344466 | AM34: 0.000179123 | AN34: 0.000249171 | AO34: 0 | AP34: 0.000249171 | AR34: 0.12072708 | AS34: 0.94758562 | AT34: 1.0012619 | AU34: 0.85789372 | AV34: 417.35518 | AW34: 0.000886728 | AX34: 0.85789372 | AY34: 0.11488493 | BD34: 45145
A35: C6 | B35: 4531.2 | C35: 0 | D35: 9702.114 | E35: 45145 | F35: 2023-08-07C6 | G35: FALSE | H35: FALSE | I35: FALSE | J35: FALSE | K35: FALSE | L35: 4531.2 | M35: 4531.2 | N35: FALSE | O35: 4531.2 | P35: 1.0004471 | Q35: 387.58072 | R35: 9702.114 | S35: 9702.114 | X35: 0.053760245 | Y35: 1.0003768 | Z35: 1.0003768 | AA35: 384.06076 | AB35: 0.00037669 | AC35: 1.42e-07 | AD35: 0.11992723 | AE35: 0.1164495 | AF35: 0.11992723 | AH35: 381.2694 | AI35: 17.1 | AJ35: 386.98844 | AK35: 375.55036 | AL35: 0.000179123 | AM35: 0 | AN35: 0 | AO35: 0 | AP35: 0 | AR35: 0.12072708 | AS35: 0.94758562 | AT35: 1.0009996 | AU35: 0.88143297 | AV35: 417.48909 | AW35: 0.000320867 | AX35: 0.88143297 | AY35: 0.11466431 | BD35: 45145
A36: C7 | B36: 4536.325 | C36: 0 | D36: 9713.002 | E36: 45145 | F36: 2023-08-07C7 | G36: FALSE | H36: FALSE | I36: FALSE | J36: FALSE | K36: FALSE | L36: 4536.325 | M36: 4536.325 | N36: FALSE | O36: 4536.325 | P36: 1.001131 | Q36: 388.01909 | R36: 9713.002 | S36: 9713.002 | T36: 45145 | U36: 9713.002 | V36: 388.01909 | W36: 0.055335247 | X36: 0.053760245 | Y36: 1.0011222 | Z36: 1.0011222 | AA36: 384.49177 | AB36: 0.0011216 | AC36: 1.26e-06 | AD36: 0.11684491 | AE36: 0.11497933 | AF36: 0.11684491 | AG36: 384.49177 | AH36: 381.2694 | AI36: 17.1 | AJ36: 386.98844 | AK36: 375.55036 | AL36: 0 | AN36: 0 | AO36: 0 | AP36: 0 | AQ36: 0.12076784 | AR36: 0.12072708 | AS36: 0.94758562 | AT36: 1.0029105 | AU36: 0.90865392 | AV36: 417.90092 | AW36: 0.000986448 | AX36: 0.90865392 | AY36: 0.11311634 | AZ36: 45145 | BA36: 417.90092 | BB36: 417.90092 | BC36: 6.98e-06 | BD36: 45145
A37: C1 | B37: 4495.475 | C37: 0 | D37: 9628.349 | E37: 45146 | F37: 2023-08-08C1 | G37: FALSE | H37: FALSE | I37: FALSE | J37: FALSE | K37: FALSE | L37: 4495.475 | M37: 4495.475 | N37: FALSE | O37: 4495.475 | P37: 0.99099491 | Q37: 384.52494 | R37: 9628.349 | S37: 9628.349 | X37: 0.055335247 | Y37: 0.99113086 | Z37: 0.99113086 | AA37: 381.08165 | AB37: -0.008908705 | AC37: 7.94e-05 | AD37: 0.14571741 | AE37: 0.13047465 | AF37: 0.14571741 | AH37: 384.49177 | AI37: 15.77 | AJ37: 390.25914 | AK37: 378.72439 | AL37: 0.001005842 | AM37: 0.000840498 | AN37: 9.82e-08 | AO37: -0.086999723 | AP37: -0.086999624 | AR37: 0.12076784 | AS37: 0.94719283 | AT37: 1.0161156 | AU37: 0.93223723 | AV37: 414.52628 | AW37: -0.008075226 | AX37: 0.93223723 | AY37: 0.11665417 | BD37: 45146
A38: C2 | B38: 4488.925 | C38: 0 | D38: 9614.577 | E38: 45146 | F38: 2023-08-08C2 | G38: FALSE | H38: FALSE | I38: FALSE | J38: FALSE | K38: FALSE | L38: 4488.925 | M38: 4488.925 | N38: FALSE | O38: 4488.925 | P38: 0.99854298 | Q38: 383.96468 | R38: 9614.577 | S38: 9614.577 | X38: 0.055335247 | Y38: 0.99856964 | Z38: 0.99856964 | AA38: 380.53657 | AB38: -0.001431383 | AC38: 2.05e-06 | AD38: 0.14204366 | AE38: 0.12892382 | AF38: 0.14204366 | AH38: 384.49177 | AI38: 15.77 | AJ38: 390.25914 | AK38: 378.72439 | AL38: 0.000840498 | AM38: 0.000675154 | AN38: 3.76e-10 | AO38: -0.12160493 | AP38: -0.12160493 | AR38: 0.12076784 | AS38: 0.94719283 | AT38: 0.98540598 | AU38: 0.68024631 | AV38: 413.96317 | AW38: -0.001358434 | AX38: 0.68223723 | AY38: 0.1167599 | BD38: 45146
A39: C3 | B39: 4486.775 | C39: 0 | D39: 9610.229 | E39: 45146 | F39: 2023-08-08C3 | G39: FALSE | H39: FALSE | I39: FALSE | J39: FALSE | K39: FALSE | L39: 4486.775 | M39: 4486.775 | N39: FALSE | O39: 4486.775 | P39: 0.99952104 | Q39: 383.78078 | R39: 9610.229 | S39: 9610.229 | X39: 0.055335247 | Y39: 0.99954777 | Z39: 0.99954777 | AA39: 380.36448 | AB39: -0.000452332 | AC39: 2.05e-07 | AD39: 0.13779504 | AE39: 0.12701787 | AF39: 0.13779504 | AH39: 384.49177 | AI39: 15.77 | AJ39: 390.25914 | AK39: 378.72439 | AL39: 0.000675154 | AM39: 0.00050981 | AN39: 2.79e-13 | AO39: -0.11211347 | AP39: -0.11211347 | AR39: 0.12076784 | AS39: 0.94719283 | AT39: 0.98445868 | AU39: 0.67483417 | AV39: 413.83515 | AW39: -0.000309268 | AX39: 0.67483417 | AY39: 0.1167218 | BD39: 45146
A40: C4 | B40: 4493.3 | C40: 0 | D40: 9623.96 | E40: 45146 | F40: 2023-08-08C4 | G40: FALSE | H40: FALSE | I40: FALSE | J40: FALSE | K40: FALSE | L40: 4493.3 | M40: 4493.3 | N40: FALSE | O40: 4493.3 | P40: 1.0014543 | Q40: 384.3389 | R40: 9623.96 | S40: 9623.96 | X40: 0.055335247 | Y40: 1.0014288 | Z40: 1.0014288 | AA40: 380.90794 | AB40: 0.00142777 | AC40: 2.04e-06 | AD40: 0.13440231 | AE40: 0.12552853 | AF40: 0.13440231 | AH40: 384.49177 | AI40: 15.77 | AJ40: 390.25914 | AK40: 378.72439 | AL40: 0.00050981 | AM40: 0.000344466 | AN40: 5.91e-17 | AO40: -0.024668628 | AP40: -0.024668628 | AR40: 0.12076784 | AS40: 0.94719283 | AT40: 0.98480019 | AU40: 0.70354629 | AV40: 414.23298 | AW40: 0.000961325 | AX40: 0.70354629 | AY40: 0.11674077 | BD40: 45146
A41: C5 | B41: 4500.6 | C41: 0 | D41: 9639.248 | E41: 45146 | F41: 2023-08-08C5 | G41: FALSE | H41: FALSE | I41: FALSE | J41: FALSE | K41: FALSE | L41: 4500.6 | M41: 4500.6 | N41: FALSE | O41: 4500.6 | P41: 1.0016246 | Q41: 384.96332 | R41: 9639.248 | S41: 9639.248 | X41: 0.055335247 | Y41: 1.0015885 | Z41: 1.0015885 | AA41: 381.51303 | AB41: 0.001587275 | AC41: 2.52e-06 | AD41: 0.13132707 | AE41: 0.12416931 | AF41: 0.13132707 | AH41: 384.49177 | AI41: 15.77 | AJ41: 390.25914 | AK41: 378.72439 | AL41: 0.000344466 | AM41: 0.000179123 | AN41: 3.37e-27 | AO41: -0.000253566 | AP41: -0.000253566 | AR41: 0.12076784 | AS41: 0.94719283 | AT41: 0.98463015 | AU41: 0.79424699 | AV41: 414.69217 | AW41: 0.001108538 | AX41: 0.79424699 | AY41: 0.11678692 | BD41: 45146
A42: C6 | B42: 4506.475 | C42: 0 | D42: 9651.196 | E42: 45146 | F42: 2023-08-08C6 | G42: FALSE | H42: FALSE | I42: FALSE | J42: FALSE | K42: FALSE | L42: 4506.475 | M42: 4506.475 | N42: FALSE | O42: 4506.475 | P42: 1.0013054 | Q42: 385.46584 | R42: 9651.196 | S42: 9651.196 | X42: 0.055335247 | Y42: 1.0012395 | Z42: 1.0012395 | AA42: 381.98592 | AB42: 0.001238748 | AC42: 1.53e-06 | AD42: 0.12796251 | AE42: 0.12262415 | AF42: 0.12796251 | AH42: 384.49177 | AI42: 15.77 | AJ42: 390.25914 | AK42: 378.72439 | AL42: 0.000179123 | AM42: 0 | AN42: 0 | AO42: 0 | AP42: 0 | AR42: 0.12076784 | AS42: 0.94719283 | AT42: 0.98421628 | AU42: 0.82943427 | AV42: 415.09897 | AW42: 0.000980963 | AX42: 0.82943427 | AY42: 0.11682598 | BD42: 45146
A43: C7 | B43: 4519.25 | C43: 0 | D43: 9678.548 | E43: 45146 | F43: 2023-08-08C7 | G43: FALSE | H43: FALSE | I43: FALSE | J43: FALSE | K43: FALSE | L43: 4519.25 | M43: 4519.25 | N43: FALSE | O43: 4519.25 | P43: 1.0028348 | Q43: 386.55856 | R43: 9678.548 | S43: 9678.548 | T43: 45146 | U43: 9678.548 | V43: 386.55856 | W43: 0.05553037 | X43: 0.055335247 | Y43: 1.0028341 | Z43: 1.0028341 | AA43: 383.06849 | AB43: 0.002830045 | AC43: 8.01e-06 | AD43: 0.1274348 | AE43: 0.12251297 | AF43: 0.1274348 | AG43: 383.06849 | AH43: 384.49177 | AI43: 15.77 | AJ43: 390.25914 | AK43: 378.72439 | AL43: 0 | AN43: 0 | AO43: 0 | AP43: 0 | AQ43: 0.12096821 | AR43: 0.12076784 | AS43: 0.94719283 | AT43: 0.98386571 | AU43: 0.85124289 | AV43: 416.07382 | AW43: 0.00234848 | AX43: 0.85124289 | AY43: 0.11708194 | AZ43: 45146 | BA43: 416.07382 | BB43: 416.07381 | BC43: 7.07e-06 | BD43: 45146
A44: C1 | B44: 4512.5 | C44: 0 | D44: 9665.619 | E44: 45147 | F44: 2023-08-09C1 | G44: FALSE | H44: FALSE | I44: FALSE | J44: FALSE | K44: FALSE | L44: 4512.5 | M44: 4512.5 | N44: FALSE | O44: 4512.5 | P44: 0.99850639 | Q44: 385.9812 | R44: 9665.619 | S44: 9665.619 | X44: 0.05553037 | Y44: 0.99850991 | Z44: 0.99850991 | AA44: 382.49768 | AB44: -0.001491203 | AC44: 2.22e-06 | AD44: 0.12450143 | AE44: 0.12114793 | AF44: 0.12450143 | AH44: 383.06849 | AI44: 15.99 | AJ44: 388.81451 | AK44: 377.32246 | AL44: 0.001005842 | AM44: 0.000840498 | AN44: 0.000206936 | AO44: -0.0016363 | AP44: -0.001429364 | AR44: 0.12096821 | AS44: 0.94525747 | AT44: 0.98156232 | AU44: 0.85302138 | AV44: 415.54021 | AW44: -0.001282497 | AX44: 0.85302138 | AY44: 0.1169223 | BD44: 45147
A45: C2 | B45: 4510.075 | C45: 0 | D45: 9660.249 | E45: 45147 | F45: 2023-08-09C2 | G45: FALSE | H45: FALSE | I45: FALSE | J45: FALSE | K45: FALSE | L45: 4510.075 | M45: 4510.075 | N45: FALSE | O45: 4510.075 | P45: 0.9994626 | Q45: 385.77377 | R45: 9660.249 | S45: 9660.249 | X45: 0.05553037 | Y45: 0.99944442 | Z45: 0.99944442 | AA45: 382.28517 | AB45: -0.000555732 | AC45: 3.09e-07 | AD45: 0.12084393 | AE45: 0.11938535 | AF45: 0.12084393 | AH45: 383.06849 | AI45: 15.99 | AJ45: 388.81451 | AK45: 377.32246 | AL45: 0.000840498 | AM45: 0.000675154 | AN45: 2.31e-05 | AO45: -0.000824651 | AP45: -0.000801551 | AR45: 0.12096821 | AS45: 0.94525747 | AT45: 0.98300011 | AU45: 0.87311938 | AV45: 415.34244 | AW45: -0.000475929 | AX45: 0.87311938 | AY45: 0.1168975 | BD45: 45147
A46: C3 | B46: 4484.3 | C46: 0 | D46: 9607.062 | E46: 45147 | F46: 2023-08-09C3 | G46: FALSE | H46: FALSE | I46: FALSE | J46: FALSE | K46: FALSE | L46: 4484.3 | M46: 4484.3 | N46: FALSE | O46: 4484.3 | P46: 0.99428502 | Q46: 383.56908 | R46: 9607.062 | S46: 9607.062 | X46: 0.05553037 | Y46: 0.99449424 | Z46: 0.99449424 | AA46: 380.1804 | AB46: -0.005520971 | AC46: 3.05e-05 | AD46: 0.13020439 | AE46: 0.1242511 | AF46: 0.13020439 | AH46: 383.06849 | AI46: 15.99 | AJ46: 388.81451 | AK46: 377.32246 | AL46: 0.000675154 | AM46: 0.00050981 | AN46: 2.51e-10 | AO46: -0.018227488 | AP46: -0.018227488 | AR46: 0.12096821 | AS46: 0.94525747 | AT46: 0.98322317 | AU46: 0.89954543 | AV46: 413.34471 | AW46: -0.004809827 | AX46: 0.89954543 | AY46: 0.11810876 | BD46: 45147
A47: C4 | B47: 4493.35 | C47: 0 | D47: 9624.85 | E47: 45147 | F47: 2023-08-09C4 | G47: FALSE | H47: FALSE | I47: FALSE | J47: FALSE | K47: FALSE | L47: 4493.35 | M47: 4493.35 | N47: FALSE | O47: 4493.35 | P47: 1.0020182 | Q47: 384.34318 | R47: 9624.85 | S47: 9624.85 | X47: 0.05553037 | Y47: 1.0018516 | Z47: 1.0018516 | AA47: 380.88433 | AB47: 0.001849843 | AC47: 3.42e-06 | AD47: 0.12766428 | AE47: 0.12311082 | AF47: 0.12766428 | AH47: 383.06849 | AI47: 15.99 | AJ47: 388.81451 | AK47: 377.32246 | AL47: 0.00050981 | AM47: 0.000344466 | AN47: 1.93e-12 | AO47: -0.000769005 | AP47: -0.000769005 | AR47: 0.12096821 | AS47: 0.94525747 | AT47: 0.97221591 | AU47: 0.81817914 | AV47: 414.0298 | AW47: 0.001657421 | AX47: 0.81817914 | AY47: 0.11823217 | BD47: 45147
A48: C5 | B48: 4504.6 | C48: 0 | D48: 9649.016 | E48: 45147 | F48: 2023-08-09C5 | G48: FALSE | H48: FALSE | I48: FALSE | J48: FALSE | K48: FALSE | L48: 4504.6 | M48: 4504.6 | N48: FALSE | O48: 4504.6 | P48: 1.0025037 | Q48: 385.30546 | R48: 9649.016 | S48: 9649.016 | X48: 0.05553037 | Y48: 1.0025108 | Z48: 1.0025108 | AA48: 381.84065 | AB48: 0.002507646 | AC48: 6.29e-06 | AD48: 0.12643508 | AE48: 0.12261469 | AF48: 0.12643508 | AH48: 383.06849 | AI48: 15.99 | AJ48: 388.81451 | AK48: 377.32246 | AL48: 0.000344466 | AM48: 0.000179123 | AN48: 1.38e-17 | AO48: -1.32e-08 | AP48: -1.32e-08 | AR48: 0.12096821 | AS48: 0.94525747 | AT48: 0.97108108 | AU48: 0.85148806 | AV48: 414.87895 | AW48: 0.002050947 | AX48: 0.85148806 | AY48: 0.11840197 | BD48: 45147
A49: C6 | B49: 4513.275 | C49: 0 | D49: 9667.442 | E49: 45147 | F49: 2023-08-09C6 | G49: FALSE | H49: FALSE | I49: FALSE | J49: FALSE | K49: FALSE | L49: 4513.275 | M49: 4513.275 | N49: FALSE | O49: 4513.275 | P49: 1.0019258 | Q49: 386.04749 | R49: 9667.442 | S49: 9667.442 | X49: 0.05553037 | Y49: 1.0019096 | Z49: 1.0019096 | AA49: 382.56982 | AB49: 0.001907804 | AC49: 3.64e-06 | AD49: 0.1241447 | AE49: 0.12155634 | AF49: 0.1241447 | AH49: 383.06849 | AI49: 15.99 | AJ49: 388.81451 | AK49: 377.32246 | AL49: 0.000179123 | AM49: 0 | AN49: 0 | AO49: 0 | AP49: 0 | AR49: 0.12096821 | AS49: 0.94525747 | AT49: 0.96951542 | AU49: 0.85976618 | AV49: 415.55321 | AW49: 0.001625195 | AX49: 0.85976618 | AY49: 0.11851375 | BD49: 45147
A50: C7 | B50: 4487.775 | C50: 0 | D50: 9613.652 | E50: 45147 | F50: 2023-08-09C7 | G50: FALSE | H50: FALSE | I50: FALSE | J50: FALSE | K50: FALSE | L50: 4487.775 | M50: 4487.775 | N50: FALSE | O50: 4487.775 | P50: 0.99435 | Q50: 383.86632 | R50: 9613.652 | S50: 9613.652 | T50: 45147 | U50: 9613.652 | V50: 383.86632 | W50: 0.059820669 | X50: 0.05553037 | Y50: 0.99443596 | Z50: 0.99443596 | AA50: 380.44119 | AB50: -0.005579573 | AC50: 3.11e-05 | AD50: 0.13334979 | AE50: 0.12641263 | AF50: 0.13334979 | AG50: 380.44119 | AH50: 383.06849 | AI50: 15.99 | AJ50: 388.81451 | AK50: 377.32246 | AL50: 0 | AN50: 0 | AO50: 0 | AP50: 0 | AQ50: 0.12133195 | AR50: 0.12096821 | AS50: 0.94525747 | AT50: 0.96848219 | AU50: 0.87562823 | AV50: 413.56464 | AW50: -0.004785357 | AX50: 0.87562823 | AY50: 0.11899422 | AZ50: 45147 | BA50: 413.56464 | BB50: 413.56463 | BC50: 7.09e-06 | BD50: 45147
A51: C1 | B51: 4531.575 | C51: 0 | D51: 9711.555 | E51: 45148 | F51: 2023-08-10C1 | G51: FALSE | H51: FALSE | I51: FALSE | J51: FALSE | K51: FALSE | L51: 4531.575 | M51: 4531.575 | N51: FALSE | O51: 4531.575 | P51: 1.0097598 | Q51: 387.61279 | R51: 9711.555 | S51: 9711.555 | X51: 0.059820669 | Y51: 1.0100176 | Z51: 1.0100176 | AA51: 384.25229 | AB51: 0.009967735 | AC51: 9.94e-05 | AD51: 0.16501833 | AE51: 0.14407864 | AF51: 0.16501833 | AH51: 380.44119 | AI51: 15.96 | AJ51: 386.14781 | AK51: 374.73457 | AL51: 0.001005842 | AM51: 0.000840498 | AN51: 0.14430049 | AO51: -2.93e-08 | AP51: 0.14430046 | AR51: 0.12133195 | AS51: 0.94172579 | AT51: 0.9640171 | AU51: 0.81213827 | AV51: 417.18392 | AW51: 0.008751437 | AX51: 0.81213827 | AY51: 0.11754544 | BD51: 45148
A52: C2 | B52: 4519.275 | C52: 0 | D52: 9685.825 | E52: 45148 | F52: 2023-08-10C2 | G52: FALSE | H52: FALSE | I52: FALSE | J52: FALSE | K52: FALSE | L52: 4519.275 | M52: 4519.275 | N52: FALSE | O52: 4519.275 | P52: 0.99728571 | Q52: 386.5607 | R52: 9685.825 | S52: 9685.825 | X52: 0.059820669 | Y52: 0.99735058 | Z52: 0.99735058 | AA52: 383.23424 | AB52: -0.002652937 | AC52: 7.04e-06 | AD52: 0.16230248 | AE52: 0.14320737 | AF52: 0.16230248 | AH52: 380.44119 | AI52: 15.96 | AJ52: 386.14781 | AK52: 374.73457 | AL52: 0.000840498 | AM52: 0.000675154 | AN52: 0.034056335 | AO52: -3.14e-08 | AP52: 0.034056303 | AR52: 0.12133195 | AS52: 0.94172579 | AT52: 0.97736461 | AU52: 0.74816085 | AV52: 416.2836 | AW52: -0.002158094 | AX52: 0.74816085 | AY52: 0.11773614 | BD52: 45148
A53: C3 | B53: 4501.3 | C53: 0 | D53: 9648.075 | E53: 45148 | F53: 2023-08-10C3 | G53: FALSE | H53: FALSE | I53: FALSE | J53: FALSE | K53: FALSE | L53: 4501.3 | M53: 4501.3 | N53: FALSE | O53: 4501.3 | P53: 0.99602259 | Q53: 385.02319 | R53: 9648.075 | S53: 9648.075 | X53: 0.059820669 | Y53: 0.99610255 | Z53: 0.99610255 | AA53: 381.74061 | AB53: -0.003905063 | AC53: 1.52e-05 | AD53: 0.1624056 | AE53: 0.1438753 | AF53: 0.1624056 | AH53: 380.44119 | AI53: 15.96 | AJ53: 386.14781 | AK53: 374.73457 | AL53: 0.000675154 | AM53: 0.00050981 | AN53: 0.000727317 | AO53: -1.36e-07 | AP53: 0.000727181 | AR53: 0.12133195 | AS53: 0.94172579 | AT53: 0.97562744 | AU53: 0.68728106 | AV53: 415.06722 | AW53: -0.002922006 | AX53: 0.68728106 | AY53: 0.11767232 | BD53: 45148
A54: C4 | B54: 4502.575 | C54: 0 | D54: 9649.749 | E54: 45148 | F54: 2023-08-10C4 | G54: FALSE | H54: FALSE | I54: FALSE | J54: FALSE | K54: FALSE | L54: 4502.575 | M54: 4502.575 | N54: FALSE | O54: 4502.575 | P54: 1.0002833 | Q54: 385.13225 | R54: 9649.749 | S54: 9649.749 | X54: 0.059820669 | Y54: 1.0001735 | Z54: 1.0001735 | AA54: 381.80684 | AB54: 0.000173491 | AC54: 3.01e-08 | AD54: 0.15746819 | AE54: 0.14170636 | AF54: 0.15746819 | AH54: 380.44119 | AI54: 15.96 | AJ54: 386.14781 | AK54: 374.73457 | AL54: 0.00050981 | AM54: 0.000344466 | AN54: 6.81e-05 | AO54: -1.36e-10 | AP54: 6.81e-05 | AR54: 0.12133195 | AS54: 0.94172579 | AT54: 0.97620946 | AU54: 0.66683949 | AV54: 415.11587 | AW54: 0.000117203 | AX54: 0.66683949 | AY54: 0.11764392 | BD54: 45148
A55: C5 | B55: 4486.15 | C55: 0 | D55: 9614.733 | E55: 45148 | F55: 2023-08-10C5 | G55: FALSE | H55: FALSE | I55: FALSE | J55: FALSE | K55: FALSE | L55: 4486.15 | M55: 4486.15 | N55: FALSE | O55: 4486.15 | P55: 0.99635209 | Q55: 383.72732 | R55: 9614.733 | S55: 9614.733 | X55: 0.059820669 | Y55: 0.99637131 | Z55: 0.99637131 | AA55: 380.42138 | AB55: -0.003635295 | AC55: 1.32e-05 | AD55: 0.15718515 | AE55: 0.14204798 | AF55: 0.15718515 | AH55: 380.44119 | AI55: 15.96 | AJ55: 386.14781 | AK55: 374.73457 | AL55: 0.000344466 | AM55: 0.000179123 | AN55: 1.34e-12 | AO55: -8.8e-13 | AP55: 4.6e-13 | AR55: 0.12133195 | AS55: 0.94172579 | AT55: 0.97646821 | AU55: 0.68774823 | AV55: 414.11052 | AW55: -0.002421848 | AX55: 0.68774823 | AY55: 0.11792015 | BD55: 45148
A56: C6 | B56: 4495.225 | C56: 0 | D56: 9633.449 | E56: 45148 | F56: 2023-08-10C6 | G56: FALSE | H56: FALSE | I56: FALSE | J56: FALSE | K56: FALSE | L56: 4495.225 | M56: 4495.225 | N56: FALSE | O56: 4495.225 | P56: 1.0020229 | Q56: 384.50356 | R56: 9633.449 | S56: 9633.449 | X56: 0.059820669 | Y56: 1.0019466 | Z56: 1.0019466 | AA56: 381.16191 | AB56: 0.001944704 | AC56: 3.78e-06 | AD56: 0.15370431 | AE56: 0.1406145 | AF56: 0.15370431 | AH56: 380.44119 | AI56: 15.96 | AJ56: 386.14781 | AK56: 374.73457 | AL56: 0.000179123 | AM56: 0 | AN56: 0 | AO56: 0 | AP56: 0 | AR56: 0.12133195 | AS56: 0.94172579 | AT56: 0.9739456 | AU56: 0.68898664 | AV56: 414.66487 | AW56: 0.001338644 | AX56: 0.68898664 | AY56: 0.11801376 | BD56: 45148
A57: C7 | B57: 4485.575 | C57: 0 | D57: 9613.197 | E57: 45148 | F57: 2023-08-10C7 | G57: FALSE | H57: FALSE | I57: FALSE | J57: FALSE | K57: FALSE | L57: 4485.575 | M57: 4485.575 | N57: FALSE | O57: 4485.575 | P57: 0.99785328 | Q57: 383.67814 | R57: 9613.197 | S57: 9613.197 | T57: 45148 | U57: 9613.197 | V57: 383.67814 | W57: 0.058491653 | X57: 0.059820669 | Y57: 0.99789774 | Z57: 0.99789774 | AA57: 380.36061 | AB57: -0.002104471 | AC57: 4.43e-06 | AD57: 0.15058638 | AE57: 0.13933283 | AF57: 0.15058638 | AG57: 380.36061 | AH57: 380.44119 | AI57: 15.96 | AJ57: 386.14781 | AK57: 374.73457 | AL57: 0 | AN57: 0 | AO57: 0 | AP57: 0 | AQ57: 0.12062311 | AR57: 0.12133195 | AS57: 0.94172579 | AT57: 0.97308787 | AU57: 0.70458967 | AV57: 414.06361 | AW57: -0.001449988 | AX57: 0.70458967 | AY57: 0.11807837 | AZ57: 45148 | BA57: 414.06361 | BB57: 414.0636 | BC57: 7.1e-06 | BD57: 45148
A58: C1 | B58: 4464.875 | C58: 0 | D58: 9570.332 | E58: 45149 | F58: 2023-08-11C1 | G58: FALSE | H58: FALSE | I58: FALSE | J58: FALSE | K58: FALSE | L58: 4464.875 | M58: 4464.875 | N58: FALSE | O58: 4464.875 | P58: 0.99538521 | Q58: 381.90754 | R58: 9570.332 | S58: 9570.332 | X58: 0.058491653 | Y58: 0.99537855 | Z58: 0.99537855 | AA58: 378.60279 | AB58: -0.004632163 | AC58: 2.15e-05 | AD58: 0.15357957 | AE58: 0.14130367 | AF58: 0.15357957 | AH58: 380.36061 | AI58: 15.85 | AJ58: 386.06602 | AK58: 374.6552 | AL58: 0.001005842 | AM58: 0.000840498 | AN58: 1.09e-05 | AO58: -0.011206511 | AP58: -0.011195623 | AR58: 0.12062311 | AS58: 0.94858624 | AT58: 0.97249498 | AU58: 0.72441758 | AV58: 412.70875 | AW58: -0.003272099 | AX58: 0.72441758 | AY58: 0.11730676 | BD58: 45149
A59: C2 | B59: 4483.675 | C59: 0 | D59: 9610.513 | E59: 45149 | F59: 2023-08-11C2 | G59: FALSE | H59: FALSE | I59: FALSE | J59: FALSE | K59: FALSE | L59: 4483.675 | M59: 4483.675 | N59: FALSE | O59: 4483.675 | P59: 1.0042106 | Q59: 383.51562 | R59: 9610.513 | S59: 9610.513 | X59: 0.058491653 | Y59: 1.0041985 | Z59: 1.0041985 | AA59: 380.19235 | AB59: 0.004189707 | AC59: 1.76e-05 | AD59: 0.15501406 | AE59: 0.14246637 | AF59: 0.15501406 | AH59: 380.36061 | AI59: 15.85 | AJ59: 386.06602 | AK59: 374.6552 | AL59: 0.000840498 | AM59: 0.000675154 | AN59: 9.94e-05 | AO59: -0.000182351 | AP59: -8.29e-05 | AR59: 0.12062311 | AS59: 0.94858624 | AT59: 0.9795305 | AU59: 0.70319604 | AV59: 413.96311 | AW59: 0.003039342 | AX59: 0.70319604 | AY59: 0.11779828 | BD59: 45149
A60: C3 | B60: 4471.7 | C60: 0 | D60: 9584.994 | E60: 45149 | F60: 2023-08-11C3 | G60: FALSE | H60: FALSE | I60: FALSE | J60: FALSE | K60: FALSE | L60: 4471.7 | M60: 4471.7 | N60: FALSE | O60: 4471.7 | P60: 0.9973292 | Q60: 382.49133 | R60: 9584.994 | S60: 9584.994 | X60: 0.058491653 | Y60: 0.99734468 | Z60: 0.99734468 | AA60: 379.18282 | AB60: -0.002658853 | AC60: 7.07e-06 | AD60: 0.15276071 | AE60: 0.14163998 | AF60: 0.15276071 | AH60: 380.36061 | AI60: 15.85 | AJ60: 386.06602 | AK60: 374.6552 | AL60: 0.000675154 | AM60: 0.00050981 | AN60: 2.52e-07 | AO60: -0.000392056 | AP60: -0.000391805 | AR60: 0.12062311 | AS60: 0.94858624 | AT60: 0.97506006 | AU60: 0.70372594 | AV60: 413.19013 | AW60: -0.001867264 | AX60: 0.70372594 | AY60: 0.11796206 | BD60: 45149
A61: C4 | B61: 4472.3375 | C61: 0 | D61: 9586.512 | E61: 45149 | F61: 2023-08-11C4 | G61: FALSE | H61: FALSE | I61: FALSE | J61: FALSE | K61: FALSE | L61: 4472.3375 | M61: 4472.3375 | N61: FALSE | O61: 4472.3375 | P61: 1.0001426 | Q61: 382.54586 | R61: 9586.512 | S61: 9586.512 | X61: 0.058491653 | Y61: 1.0001584 | Z61: 1.0001584 | AA61: 379.24287 | AB61: 0.00015836 | AC61: 2.51e-08 | AD61: 0.14811596 | AE61: 0.13950396 | AF61: 0.14811596 | AH61: 380.36061 | AI61: 15.85 | AJ61: 386.06602 | AK61: 374.6552 | AL61: 0.00050981 | AM61: 0.000344466 | AN61: 6.8e-10 | AO61: -1.75e-05 | AP61: -1.75e-05 | AR61: 0.12062311 | AS61: 0.94858624 | AT61: 0.97356177 | AU61: 0.71410652 | AV61: 413.23576 | AW61: 0.000110413 | AX61: 0.71410652 | AY61: 0.11792902 | BD61: 45149
A62: C5 | B62: 4472.4 | C62: 0 | D62: 9586.686 | E62: 45149 | F62: 2023-08-11C5 | G62: FALSE | H62: FALSE | I62: FALSE | J62: FALSE | K62: FALSE | L62: 4472.4 | M62: 4472.4 | N62: FALSE | O62: 4472.4 | P62: 1.000014 | Q62: 382.5512 | R62: 9586.686 | S62: 9586.686 | X62: 0.058491653 | Y62: 1.0000182 | Z62: 1.0000182 | AA62: 379.24975 | AB62: 1.82e-05 | AC62: 3.29e-10 | AD62: 0.14360387 | AE62: 0.13739553 | AF62: 0.14360387 | AH62: 380.36061 | AI62: 15.85 | AJ62: 386.06602 | AK62: 374.6552 | AL62: 0.000344466 | AM62: 0.000179123 | AN62: 2.3e-17 | AO62: -4.54e-09 | AP62: -4.54e-09 | AR62: 0.12062311 | AS62: 0.94858624 | AT62: 0.97386434 | AU62: 0.73650008 | AV62: 413.24019 | AW62: 1.07e-05 | AX62: 0.73650008 | AY62: 0.11792701 | BD62: 45149
A63: C6 | B63: 4485.7 | C63: 0 | D63: 9614.542 | E63: 45149 | F63: 2023-08-11C6 | G63: FALSE | H63: FALSE | I63: FALSE | J63: FALSE | K63: FALSE | L63: 4485.7 | M63: 4485.7 | N63: FALSE | O63: 4485.7 | P63: 1.0029738 | Q63: 383.68883 | R63: 9614.542 | S63: 9614.542 | X63: 0.058491653 | Y63: 1.0029057 | Z63: 1.0029057 | AA63: 380.35174 | AB63: 0.002901483 | AC63: 8.42e-06 | AD63: 0.14239303 | AE63: 0.13695516 | AF63: 0.14239303 | AH63: 380.36061 | AI63: 15.85 | AJ63: 386.06602 | AK63: 374.6552 | AL63: 0.000179123 | AM63: 0 | AN63: 0 | AO63: 0 | AP63: 0 | AR63: 0.12062311 | AS63: 0.94858624 | AT63: 0.97388273 | AU63: 0.75964119 | AV63: 414.12358 | AW63: 0.002137732 | AX63: 0.75964119 | AY63: 0.11812525 | BD63: 45149
A64: C7 | B64: 4479.775 | C64: 0 | D64: 9601.144 | E64: 45149 | F64: 2023-08-11C7 | G64: FALSE | H64: FALSE | I64: FALSE | J64: FALSE | K64: FALSE | L64: 4479.775 | M64: 4479.775 | N64: FALSE | O64: 4479.775 | P64: 0.99867914 | Q64: 383.18203 | R64: 9601.144 | S64: 9601.144 | T64: 45149 | U64: 9601.144 | V64: 383.18203 | W64: 0.056196546 | X64: 0.058491653 | Y64: 0.99860649 | Z64: 0.99860649 | AA64: 379.82171 | AB64: -0.001394486 | AC64: 1.94e-06 | AD64: 0.13879857 | AE64: 0.13526612 | AF64: 0.13879857 | AG64: 379.82171 | AH64: 380.36061 | AI64: 15.85 | AJ64: 386.06602 | AK64: 374.6552 | AL64: 0 | AN64: 0 | AO64: 0 | AP64: 0 | AQ64: 0.12049296 | AR64: 0.12062311 | AS64: 0.94858624 | AT64: 0.97206441 | AU64: 0.76610085 | AV64: 413.68494 | AW64: -0.001059217 | AX64: 0.76610085 | AY64: 0.11808761 | AZ64: 45149 | BA64: 413.68494 | BB64: 413.68493 | BC64: 7.12e-06 | BD64: 45149
A65: C1 | B65: 4474.65 | C65: 0 | D65: 9592.545 | E65: 45152 | F65: 2023-08-14C1 | G65: FALSE | H65: FALSE | I65: FALSE | J65: FALSE | K65: FALSE | L65: 4474.65 | M65: 4474.65 | N65: FALSE | O65: 4474.65 | P65: 0.99885597 | Q65: 382.74366 | R65: 9592.545 | S65: 9592.545 | X65: 0.056196546 | Y65: 0.99863607 | Z65: 0.99863607 | AA65: 379.30366 | AB65: -0.001364858 | AC65: 1.86e-06 | AD65: 0.13530079 | AE65: 0.13359116 | AF65: 0.13530079 | AH65: 379.82171 | AI65: 14.84 | AJ65: 385.51904 | AK65: 374.12439 | AL65: 0.001005842 | AM65: 0.000840498 | AN65: 7.98e-05 | AO65: -0.000692352 | AP65: -0.00061257 | AR65: 0.12049296 | AS65: 0.94983615 | AT65: 0.9724102 | AU65: 0.7869761 | AV65: 413.23457 | AW65: -0.00108866 | AX65: 0.7869761 | AY65: 0.11783423 | BD65: 45152
A66: C2 | B66: 4496.775 | C66: 0 | D66: 9640.057 | E66: 45152 | F66: 2023-08-14C2 | G66: FALSE | H66: FALSE | I66: FALSE | J66: FALSE | K66: FALSE | L66: 4496.775 | M66: 4496.775 | N66: FALSE | O66: 4496.775 | P66: 1.0049445 | Q66: 384.63614 | R66: 9640.057 | S66: 9640.057 | X66: 0.056196546 | Y66: 1.004953 | Z66: 1.004953 | AA66: 381.18236 | AB66: 0.004940787 | AC66: 2.44e-05 | AD66: 0.14068271 | AE66: 0.136393 | AF66: 0.14068271 | AH66: 379.82171 | AI66: 14.84 | AJ66: 385.51904 | AK66: 374.12439 | AL66: 0.000840498 | AM66: 0.000675154 | AN66: 0.001684639 | AO66: -6.21e-07 | AP66: 0.001684018 | AR66: 0.12049296 | AS66: 0.94983615 | AT66: 0.97473155 | AU66: 0.80732093 | AV66: 414.84448 | AW66: 0.003895868 | AX66: 0.80732093 | AY66: 0.1183721 | BD66: 45152
A67: C3 | B67: 4500.725 | C67: 0 | D67: 9649.012 | E67: 45152 | F67: 2023-08-14C3 | G67: FALSE | H67: FALSE | I67: FALSE | J67: FALSE | K67: FALSE | L67: 4500.725 | M67: 4500.725 | N67: FALSE | O67: 4500.725 | P67: 1.0008784 | Q67: 384.97401 | R67: 9649.012 | S67: 9649.012 | X67: 0.056196546 | Y67: 1.0009289 | Z67: 1.0009289 | AA67: 381.53645 | AB67: 0.000928505 | AC67: 8.62e-07 | AD67: 0.13673103 | AE67: 0.13450123 | AF67: 0.13673103 | AH67: 379.82171 | AI67: 14.84 | AJ67: 385.51904 | AK67: 374.12439 | AL67: 0.000675154 | AM67: 0.00050981 | AN67: 0.00097609 | AO67: -2.36e-09 | AP67: 0.000976088 | AR67: 0.12049296 | AS67: 0.94983615 | AT67: 0.9697912 | AU67: 0.77643626 | AV67: 415.15431 | AW67: 0.000746861 | AX67: 0.77643626 | AY67: 0.11834333 | BD67: 45152
A68: C4 | B68: 4496.65 | C68: 0 | D68: 9639.622 | E68: 45152 | F68: 2023-08-14C4 | G68: FALSE | H68: FALSE | I68: FALSE | J68: FALSE | K68: FALSE | L68: 4496.65 | M68: 4496.65 | N68: FALSE | O68: 4496.65 | P68: 0.99909459 | Q68: 384.62545 | R68: 9639.622 | S68: 9639.622 | X68: 0.056196546 | Y68: 0.99902684 | Z68: 0.99902684 | AA68: 381.16516 | AB68: -0.00097363 | AC68: 9.48e-07 | AD68: 0.13294354 | AE68: 0.13265757 | AF68: 0.13294354 | AH68: 379.82171 | AI68: 14.84 | AJ68: 385.51904 | AK68: 374.12439 | AL68: 0.00050981 | AM68: 0.000344466 | AN68: 1.88e-05 | AO68: -6.41e-12 | AP68: 1.88e-05 | AR68: 0.12049296 | AS68: 0.94983615 | AT68: 0.97005663 | AU68: 0.79887614 | AV68: 414.83969 | AW68: -0.000757838 | AX68: 0.79887614 | AY68: 0.11832154 | BD68: 45152
A69: C5 | B69: 4495.225 | C69: 0 | D69: 9637.201 | E69: 45152 | F69: 2023-08-14C5 | G69: FALSE | H69: FALSE | I69: FALSE | J69: FALSE | K69: FALSE | L69: 4495.225 | M69: 4495.225 | N69: FALSE | O69: 4495.225 | P69: 0.9996831 | Q69: 384.50356 | R69: 9637.201 | S69: 9637.201 | X69: 0.056196546 | Y69: 0.99974885 | Z69: 0.99974885 | AA69: 381.06943 | AB69: -0.000251182 | AC69: 6.31e-08 | AD69: 0.12891944 | AE69: 0.13066533 | AF69: 0.13066533 | AH69: 379.82171 | AI69: 14.84 | AJ69: 385.51904 | AK69: 374.12439 | AL69: 0.000344466 | AM69: 0.000179123 | AN69: 2.55e-09 | AO69: 0 | AP69: 2.55e-09 | AR69: 0.12049296 | AS69: 0.94983615 | AT69: 0.97025764 | AU69: 0.82163572 | AV69: 414.75552 | AW69: -0.000202914 | AX69: 0.82163572 | AY69: 0.11831175 | BD69: 45152
A70: C6 | B70: 4492.6 | C70: 0 | D70: 9631.083 | E70: 45152 | F70: 2023-08-14C6 | G70: FALSE | H70: FALSE | I70: FALSE | J70: FALSE | K70: FALSE | L70: 4492.6 | M70: 4492.6 | N70: FALSE | O70: 4492.6 | P70: 0.99941605 | Q70: 384.27903 | R70: 9631.083 | S70: 9631.083 | X70: 0.056196546 | Y70: 0.99936517 | Z70: 0.99936517 | AA70: 380.82751 | AB70: -0.000635033 | AC70: 4.03e-07 | AD70: 0.12516266 | AE70: 0.12877331 | AF70: 0.12877331 | AH70: 379.82171 | AI70: 14.84 | AJ70: 385.51904 | AK70: 374.12439 | AL70: 0.000179123 | AM70: 0 | AN70: 0 | AO70: 0 | AP70: 0 | AR70: 0.12049296 | AS70: 0.94983615 | AT70: 0.97034785 | AU70: 0.8359613 | AV70: 414.53859 | AW70: -0.000523033 | AX70: 0.8359613 | AY70: 0.1182645 | BD70: 45152
A71: C7 | B71: 4500.275 | C71: 0 | D71: 9647.219 | E71: 45152 | F71: 2023-08-14C7 | G71: FALSE | H71: FALSE | I71: FALSE | J71: FALSE | K71: FALSE | L71: 4500.275 | M71: 4500.275 | N71: FALSE | O71: 4500.275 | P71: 1.0017084 | Q71: 384.93552 | R71: 9647.219 | S71: 9647.219 | T71: 45152 | U71: 9647.219 | V71: 384.93552 | W71: 0.057132627 | X71: 0.056196546 | Y71: 1.0016754 | Z71: 1.0016754 | AA71: 381.46556 | AB71: 0.001674007 | AC71: 2.8e-06 | AD71: 0.12256567 | AE71: 0.12741031 | AF71: 0.12741031 | AG71: 381.46556 | AH71: 379.82171 | AI71: 14.84 | AJ71: 385.51904 | AK71: 374.12439 | AL71: 0 | AN71: 0 | AO71: 0 | AP71: 0 | AQ71: 0.11940506 | AR71: 0.12049296 | AS71: 0.94983615 | AT71: 0.97078334 | AU71: 0.84824375 | AV71: 415.11867 | AW71: 0.001399349 | AX71: 0.84824375 | AY71: 0.11830509 | AZ71: 45152 | BA71: 415.11867 | BB71: 415.11866 | BC71: 7.12e-06 | BD71: 45152
A72: C1 | B72: 4478.3 | C72: 0 | D72: 9603.475 | E72: 45153 | F72: 2023-08-15C1 | G72: FALSE | H72: FALSE | I72: FALSE | J72: FALSE | K72: FALSE | L72: 4478.3 | M72: 4478.3 | N72: FALSE | O72: 4478.3 | P72: 0.99511697 | Q72: 383.05586 | R72: 9603.475 | S72: 9603.475 | X72: 0.057132627 | Y72: 0.99530694 | Z72: 0.99530694 | AA72: 379.67531 | AB72: -0.004704112 | AC72: 2.21e-05 | AD72: 0.12830862 | AE72: 0.13006704 | AF72: 0.13006704 | AH72: 381.46556 | AI72: 14.82 | AJ72: 387.18754 | AK72: 375.74357 | AL72: 0.001005842 | AM72: 0.000840498 | AN72: 2.58e-06 | AO72: -0.007655666 | AP72: -0.007653084 | AR72: 0.11940506 | AS72: 0.96016819 | AT72: 0.97040933 | AU72: 0.86664371 | AV72: 413.45961 | AW72: -0.003996592 | AX72: 0.86664371 | AY72: 0.11908991 | BD72: 45153
A73: C2 | B73: 4466.9 | C73: 0 | D73: 9578.778 | E73: 45153 | F73: 2023-08-15C2 | G73: FALSE | H73: FALSE | I73: FALSE | J73: FALSE | K73: FALSE | L73: 4466.9 | M73: 4466.9 | N73: FALSE | O73: 4466.9 | P73: 0.99745439 | Q73: 382.08075 | R73: 9578.778 | S73: 9578.778 | X73: 0.057132627 | Y73: 0.99742833 | Z73: 0.99742833 | AA73: 378.69891 | AB73: -0.002574986 | AC73: 6.63e-06 | AD73: 0.12718921 | AE73: 0.12946351 | AF73: 0.12946351 | AH73: 381.46556 | AI73: 14.82 | AJ73: 387.18754 | AK73: 375.74357 | AL73: 0.000840498 | AM73: 0.000675154 | AN73: 4.34e-09 | AO73: -0.020852405 | AP73: -0.020852401 | AR73: 0.11940506 | AS73: 0.96016819 | AT73: 0.96312322 | AU73: 0.84045235 | AV73: 412.53704 | AW73: -0.002231344 | AX73: 0.84045235 | AY73: 0.11919679 | BD73: 45153
A74: C3 | B74: 4472.975 | C74: 0 | D74: 9591.321 | E74: 45153 | F74: 2023-08-15C3 | G74: FALSE | H74: FALSE | I74: FALSE | J74: FALSE | K74: FALSE | L74: 4472.975 | M74: 4472.975 | N74: FALSE | O74: 4472.975 | P74: 1.00136 | Q74: 382.60038 | R74: 9591.321 | S74: 9591.321 | X74: 0.057132627 | Y74: 1.0013095 | Z74: 1.0013095 | AA74: 379.1948 | AB74: 0.001308601 | AC74: 1.71e-06 | AD74: 0.12404722 | AE74: 0.12786164 | AF74: 0.12786164 | AH74: 381.46556 | AI74: 14.82 | AJ74: 387.18754 | AK74: 375.74357 | AL74: 0.000675154 | AM74: 0.00050981 | AN74: 2.3e-10 | AO74: -0.003127894 | AP74: -0.003127894 | AR74: 0.11940506 | AS74: 0.96016819 | AT74: 0.96212298 | AU74: 0.83584136 | AV74: 412.99086 | AW74: 0.001100075 | AX74: 0.83584136 | AY74: 0.11914611 | BD74: 45153
A75: C4 | B75: 4464.2125 | C75: 0 | D75: 9573.196 | E75: 45153 | F75: 2023-08-15C4 | G75: FALSE | H75: FALSE | I75: FALSE | J75: FALSE | K75: FALSE | L75: 4464.2125 | M75: 4464.2125 | N75: FALSE | O75: 4464.2125 | P75: 0.99804101 | Q75: 381.85088 | R75: 9573.196 | S75: 9573.196 | X75: 0.057132627 | Y75: 0.99811027 | Z75: 0.99811027 | AA75: 378.47823 | AB75: -0.001891517 | AC75: 3.58e-06 | AD75: 0.12183238 | AE75: 0.12667865 | AF75: 0.12667865 | AH75: 381.46556 | AI75: 14.82 | AJ75: 387.18754 | AK75: 375.74357 | AL75: 0.00050981 | AM75: 0.000344466 | AN75: 6.7e-17 | AO75: -0.004172426 | AP75: -0.004172426 | AR75: 0.11940506 | AS75: 0.96016819 | AT75: 0.96259749 | AU75: 0.86358461 | AV75: 412.33739 | AW75: -0.001582288 | AX75: 0.86358461 | AY75: 0.11925227 | BD75: 45153
A76: C5 | B76: 4463.8 | C76: 0 | D76: 9571.673 | E76: 45153 | F76: 2023-08-15C5 | G76: FALSE | H76: FALSE | I76: FALSE | J76: FALSE | K76: FALSE | L76: 4463.8 | M76: 4463.8 | N76: FALSE | O76: 4463.8 | P76: 0.9999076 | Q76: 381.81559 | R76: 9571.673 | S76: 9571.673 | X76: 0.057132627 | Y76: 0.99984091 | Z76: 0.99984091 | AA76: 378.41801 | AB76: -0.000159103 | AC76: 2.53e-08 | AD76: 0.11813221 | AE76: 0.12476936 | AF76: 0.12476936 | AH76: 381.46556 | AI76: 14.82 | AJ76: 387.18754 | AK76: 375.74357 | AL76: 0.000344466 | AM76: 0.000179123 | AN76: 3.72e-31 | AO76: -0.000173897 | AP76: -0.000173897 | AR76: 0.11940506 | AS76: 0.96016819 | AT76: 0.96160294 | AU76: 0.87164921 | AV76: 412.28041 | AW76: -0.000138194 | AX76: 0.87164921 | AY76: 0.1192088 | BD76: 45153
A77: C6 | B77: 4468.25 | C77: 0 | D77: 9581.387 | E77: 45153 | F77: 2023-08-15C6 | G77: FALSE | H77: FALSE | I77: FALSE | J77: FALSE | K77: FALSE | L77: 4468.25 | M77: 4468.25 | N77: FALSE | O77: 4468.25 | P77: 1.0009969 | Q77: 382.19623 | R77: 9581.387 | S77: 9581.387 | X77: 0.057132627 | Y77: 1.0010149 | Z77: 1.0010149 | AA77: 378.80206 | AB77: 0.001014355 | AC77: 1.03e-06 | AD77: 0.11500786 | AE77: 0.12310493 | AF77: 0.12310493 | AH77: 381.46556 | AI77: 14.82 | AJ77: 387.18754 | AK77: 375.74357 | AL77: 0.000179123 | AM77: 0 | AN77: 0 | AO77: 0 | AP77: 0 | AR77: 0.11940506 | AS77: 0.96016819 | AT77: 0.96201043 | AU77: 0.8849876 | AV77: 412.64457 | AW77: 0.000883276 | AX77: 0.8849876 | AY77: 0.11925239 | BD77: 45153
A78: C7 | B78: 4454.45 | C78: 0 | D78: 9551.149 | E78: 45153 | F78: 2023-08-15C7 | G78: FALSE | H78: FALSE | I78: FALSE | J78: FALSE | K78: FALSE | L78: 4454.45 | M78: 4454.45 | N78: FALSE | O78: 4454.45 | P78: 0.99691154 | Q78: 381.01583 | R78: 9551.149 | S78: 9551.149 | T78: 45153 | U78: 9551.149 | V78: 381.01583 | W78: 0.05896819 | X78: 0.057132627 | Y78: 0.99684409 | Z78: 0.99684409 | AA78: 377.60659 | AB78: -0.003160901 | AC78: 9.99e-06 | AD78: 0.11614937 | AE78: 0.1234055 | AF78: 0.1234055 | AG78: 377.60659 | AH78: 381.46556 | AI78: 14.82 | AJ78: 387.18754 | AK78: 375.74357 | AL78: 0 | AN78: 0 | AO78: 0 | AP78: 0 | AQ78: 0.12008805 | AR78: 0.11940506 | AS78: 0.96016819 | AT78: 0.96160182 | AU78: 0.89695307 | AV78: 411.49158 | AW78: -0.002794138 | AX78: 0.89695307 | AY78: 0.11959479 | AZ78: 45153 | BA78: 411.49158 | BB78: 411.49157 | BC78: 7.1e-06 | BD78: 45153
A79: C1 | B79: 4461.5125 | C79: 0 | D79: 9568.503 | E79: 45154 | F79: 2023-08-16C1 | G79: FALSE | H79: FALSE | I79: FALSE | J79: FALSE | K79: FALSE | L79: 4461.5125 | M79: 4461.5125 | N79: FALSE | O79: 4461.5125 | P79: 1.0015855 | Q79: 381.61993 | R79: 9568.503 | S79: 9568.503 | X79: 0.05896819 | Y79: 1.0016532 | Z79: 1.0016532 | AA79: 378.23084 | AB79: 0.001651789 | AC79: 2.73e-06 | AD79: 0.11388596 | AE79: 0.12213287 | AF79: 0.12213287 | AH79: 377.60659 | AI79: 16.46 | AJ79: 383.27069 | AK79: 371.94249 | AL79: 0.001005842 | AM79: 0.000840498 | AN79: 0.002790101 | AO79: -0.000219302 | AP79: 0.002570799 | AR79: 0.12008805 | AS79: 0.95370576 | AT79: 0.95838101 | AU79: 0.88874614 | AV79: 412.09569 | AW79: 0.001468092 | AX79: 0.88874614 | AY79: 0.11972182 | BD79: 45154
A80: C2 | B80: 4458.25 | C80: 0 | D80: 9560.508 | E80: 45154 | F80: 2023-08-16C2 | G80: FALSE | H80: FALSE | I80: FALSE | J80: FALSE | K80: FALSE | L80: 4458.25 | M80: 4458.25 | N80: FALSE | O80: 4458.25 | P80: 0.99926875 | Q80: 381.34087 | R80: 9560.508 | S80: 9560.508 | X80: 0.05896819 | Y80: 0.99916445 | Z80: 0.99916445 | AA80: 377.9148 | AB80: -0.000835903 | AC80: 6.99e-07 | AD80: 0.11075091 | AE80: 0.12044053 | AF80: 0.12044053 | AH80: 377.60659 | AI80: 16.46 | AJ80: 383.27069 | AK80: 371.94249 | AL80: 0.000840498 | AM80: 0.000675154 | AN80: 0.000504065 | AO80: -9.7e-05 | AP80: 0.000407051 | AR80: 0.12008805 | AS80: 0.95370576 | AT80: 0.957181 | AU80: 0.89800694 | AV80: 411.78928 | AW80: -0.000743521 | AX80: 0.89800694 | AY80: 0.11932119 | BD80: 45154
A81: C3 | B81: 4452.075 | C81: 0 | D81: 9547.363 | E81: 45154 | F81: 2023-08-16C3 | G81: FALSE | H81: FALSE | I81: FALSE | J81: FALSE | K81: FALSE | L81: 4452.075 | M81: 4452.075 | N81: FALSE | O81: 4452.075 | P81: 0.99861493 | Q81: 380.81268 | R81: 9547.363 | S81: 9547.363 | X81: 0.05896819 | Y81: 0.99862507 | Z81: 0.99862507 | AA81: 377.3952 | AB81: -0.001375873 | AC81: 1.89e-06 | AD81: 0.10830594 | AE81: 0.11904168 | AF81: 0.11904168 | AH81: 377.60659 | AI81: 16.46 | AJ81: 383.27069 | AK81: 371.94249 | AL81: 0.000675154 | AM81: 0.00050981 | AN81: 1.63e-05 | AO81: -4.47e-05 | AP81: -2.84e-05 | AR81: 0.12008805 | AS81: 0.95370576 | AT81: 0.96095628 | AU81: 0.91062504 | AV81: 411.28033 | AW81: -0.001235956 | AX81: 0.91062504 | AY81: 0.1190614 | BD81: 45154
A82: C4 | B82: 4443.9 | C82: 0 | D82: 9530.768 | E82: 45154 | F82: 2023-08-16C4 | G82: FALSE | H82: FALSE | I82: FALSE | J82: FALSE | K82: FALSE | L82: 4443.9 | M82: 4443.9 | N82: FALSE | O82: 4443.9 | P82: 0.99816378 | Q82: 380.11343 | R82: 9530.768 | S82: 9530.768 | X82: 0.05896819 | Y82: 0.99826182 | Z82: 0.99826182 | AA82: 376.73922 | AB82: -0.001739689 | AC82: 3.03e-06 | AD82: 0.10652085 | AE82: 0.11792353 | AF82: 0.11792353 | AH82: 377.60659 | AI82: 16.46 | AJ82: 383.27069 | AK82: 371.94249 | AL82: 0.00050981 | AM82: 0.000344466 | AN82: 9.28e-09 | AO82: -1.36e-05 | AP82: -1.36e-05 | AR82: 0.12008805 | AS82: 0.95370576 | AT82: 0.9633897 | AU82: 0.9213257 | AV82: 410.62891 | AW82: -0.001583897 | AX82: 0.9213257 | AY82: 0.11916179 | BD82: 45154
A83: C5 | B83: 4446.5 | C83: 0 | D83: 9535.651 | E83: 45154 | F83: 2023-08-16C5 | G83: FALSE | H83: FALSE | I83: FALSE | J83: FALSE | K83: FALSE | L83: 4446.5 | M83: 4446.5 | N83: FALSE | O83: 4446.5 | P83: 1.0005851 | Q83: 380.33582 | R83: 9535.651 | S83: 9535.651 | X83: 0.05896819 | Y83: 1.0005123 | Z83: 1.0005123 | AA83: 376.93224 | AB83: 0.000512209 | AC83: 2.62e-07 | AD83: 0.10341015 | AE83: 0.11620096 | AF83: 0.11620096 | AH83: 377.60659 | AI83: 16.46 | AJ83: 383.27069 | AK83: 371.94249 | AL83: 0.000344466 | AM83: 0.000179123 | AN83: 1.88e-14 | AO83: -7.23e-10 | AP83: -7.23e-10 | AR83: 0.12008805 | AS83: 0.95370576 | AT83: 0.96245073 | AU83: 0.93006176 | AV83: 410.82238 | AW83: 0.000471159 | AX83: 0.93006176 | AY83: 0.11910352 | BD83: 45154
A84: C6 | B84: 4442.5 | C84: 0 | D84: 9527.822 | E84: 45154 | F84: 2023-08-16C6 | G84: FALSE | H84: FALSE | I84: FALSE | J84: FALSE | K84: FALSE | L84: 4442.5 | M84: 4442.5 | N84: FALSE | O84: 4442.5 | P84: 0.99910042 | Q84: 379.99368 | R84: 9527.822 | S84: 9527.822 | X84: 0.05896819 | Y84: 0.99917898 | Z84: 0.99917898 | AA84: 376.62277 | AB84: -0.000821361 | AC84: 6.75e-07 | AD84: 0.10061532 | AE84: 0.11460055 | AF84: 0.11460055 | AH84: 377.60659 | AI84: 16.46 | AJ84: 383.27069 | AK84: 371.94249 | AL84: 0.000179123 | AM84: 0 | AN84: 0 | AO84: 0 | AP84: 0 | AR84: 0.12008805 | AS84: 0.95370576 | AT84: 0.96299597 | AU84: 0.94384901 | AV84: 410.50811 | AW84: -0.000764982 | AX84: 0.94384901 | AY84: 0.11877984 | BD84: 45154
A85: C7 | B85: 4422.95 | C85: 0 | D85: 9485.674 | E85: 45154 | F85: 2023-08-16C7 | G85: FALSE | H85: FALSE | I85: FALSE | J85: FALSE | K85: FALSE | L85: 4422.95 | M85: 4422.95 | N85: FALSE | O85: 4422.95 | P85: 0.99559933 | Q85: 378.32145 | R85: 9485.674 | S85: 9485.674 | T85: 45154 | U85: 9485.674 | V85: 378.32145 | W85: 0.058404098 | X85: 0.05896819 | Y85: 0.99557632 | Z85: 0.99557632 | AA85: 374.95671 | AB85: -0.00443349 | AC85: 1.97e-05 | AD85: 0.10768662 | AE85: 0.117386 | AF85: 0.117386 | AG85: 374.95671 | AH85: 377.60659 | AI85: 16.46 | AJ85: 383.27069 | AK85: 371.94249 | AL85: 0 | AN85: 0 | AO85: 0 | AP85: 0 | AQ85: 0.12045846 | AR85: 0.12008805 | AS85: 0.95370576 | AT85: 0.96601412 | AU85: 0.95703002 | AV85: 408.79358 | AW85: -0.004176601 | AX85: 0.95703002 | AY85: 0.1195618 | AZ85: 45154 | BA85: 408.79358 | BB85: 408.79357 | BC85: 7.18e-06 | BD85: 45154
A86: C1 | B86: 4425.4 | C86: 0 | D86: 9494.642 | E86: 45155 | F86: 2023-08-17C1 | G86: FALSE | H86: FALSE | I86: FALSE | J86: FALSE | K86: FALSE | L86: 4425.4 | M86: 4425.4 | N86: FALSE | O86: 4425.4 | P86: 1.0005539 | Q86: 378.53101 | R86: 9494.642 | S86: 9494.642 | X86: 0.058404098 | Y86: 1.0007832 | Z86: 1.0007832 | AA86: 375.25037 | AB86: 0.000782886 | AC86: 6.13e-07 | AD86: 0.10471626 | AE86: 0.11575199 | AF86: 0.11575199 | AH86: 374.95671 | AI86: 16.78 | AJ86: 380.58106 | AK86: 369.33236 | AL86: 0.001005842 | AM86: 0.000840498 | AN86: 0.001882862 | AO86: -0.000537491 | AP86: 0.001345371 | AR86: 0.12045846 | AS86: 0.95016704 | AT86: 0.95869221 | AU86: 0.93085385 | AV86: 409.09324 | AW86: 0.000733032 | AX86: 0.93085385 | AY86: 0.11874759 | BD86: 45155
A87: C2 | B87: 4422.675 | C87: 0 | D87: 9488.197 | E87: 45155 | F87: 2023-08-17C2 | G87: FALSE | H87: FALSE | I87: FALSE | J87: FALSE | K87: FALSE | L87: 4422.675 | M87: 4422.675 | N87: FALSE | O87: 4422.675 | P87: 0.99938424 | Q87: 378.29792 | R87: 9488.197 | S87: 9488.197 | X87: 0.058404098 | Y87: 0.9993212 | Z87: 0.9993212 | AA87: 374.99565 | AB87: -0.000679034 | AC87: 4.61e-07 | AD87: 0.10176624 | AE87: 0.11410946 | AF87: 0.11410946 | AH87: 374.95671 | AI87: 16.78 | AJ87: 380.58106 | AK87: 369.33236 | AL87: 0.000840498 | AM87: 0.000675154 | AN87: 0.00035104 | AO87: -0.000239374 | AP87: 0.000111666 | AR87: 0.12045846 | AS87: 0.95016704 | AT87: 0.96631386 | AU87: 0.94399419 | AV87: 408.83421 | AW87: -0.000633181 | AX87: 0.94399419 | AY87: 0.11874469 | BD87: 45155
A88: C3 | B88: 4414.025 | C88: 0 | D88: 9470.286 | E88: 45155 | F88: 2023-08-17C3 | G88: FALSE | H88: FALSE | I88: FALSE | J88: FALSE | K88: FALSE | L88: 4414.025 | M88: 4414.025 | N88: FALSE | O88: 4414.025 | P88: 0.99804417 | Q88: 377.55804 | R88: 9470.286 | S88: 9470.286 | X88: 0.058404098 | Y88: 0.99811229 | Z88: 0.99811229 | AA88: 374.28777 | AB88: -0.001889498 | AC88: 3.57e-06 | AD88: 0.10056269 | AE88: 0.11322224 | AF88: 0.11322224 | AH88: 374.95671 | AI88: 16.78 | AJ88: 380.58106 | AK88: 369.33236 | AL88: 0.000675154 | AM88: 0.00050981 | AN88: 5.44e-06 | AO88: -0.00021604 | AP88: -0.000210605 | AR88: 0.12045846 | AS88: 0.95016704 | AT88: 0.96634082 | AU88: 0.95758238 | AV88: 408.10511 | AW88: -0.00178335 | AX88: 0.95758238 | AY88: 0.11885382 | BD88: 45155
A89: C4 | B89: 4421.925 | C89: 0 | D89: 9487.592 | E89: 45155 | F89: 2023-08-17C4 | G89: FALSE | H89: FALSE | I89: FALSE | J89: FALSE | K89: FALSE | L89: 4421.925 | M89: 4421.925 | N89: FALSE | O89: 4421.925 | P89: 1.0017897 | Q89: 378.23377 | R89: 9487.592 | S89: 9487.592 | X89: 0.058404098 | Y89: 1.0018274 | Z89: 1.0018274 | AA89: 374.97174 | AB89: 0.001825732 | AC89: 3.33e-06 | AD89: 0.099291893 | AE89: 0.11229913 | AF89: 0.11229913 | AH89: 374.95671 | AI89: 16.78 | AJ89: 380.58106 | AK89: 369.33236 | AL89: 0.00050981 | AM89: 0.000344466 | AN89: 9.38e-07 | AO89: -5.66e-07 | AP89: 3.73e-07 | AR89: 0.12045846 | AS89: 0.95016704 | AT89: 0.96532588 | AU89: 0.96508612 | AV89: 408.81894 | AW89: 0.001749136 | AX89: 0.96508612 | AY89: 0.11888124 | BD89: 45155
A90: C5 | B90: 4408.375 | C90: 0 | D90: 9458.348 | E90: 45155 | F90: 2023-08-17C5 | G90: FALSE | H90: FALSE | I90: FALSE | J90: FALSE | K90: FALSE | L90: 4408.375 | M90: 4408.375 | N90: FALSE | O90: 4408.375 | P90: 0.99693572 | Q90: 377.07476 | R90: 9458.348 | S90: 9458.348 | X90: 0.058404098 | Y90: 0.99691766 | Z90: 0.99691766 | AA90: 373.81595 | AB90: -0.003087102 | AC90: 9.53e-06 | AD90: 0.10137072 | AE90: 0.11285876 | AF90: 0.11285876 | AH90: 374.95671 | AI90: 16.78 | AJ90: 380.58106 | AK90: 369.33236 | AL90: 0.000344466 | AM90: 0.000179123 | AN90: 7.01e-16 | AO90: -3.85e-08 | AP90: -3.85e-08 | AR90: 0.12045846 | AS90: 0.95016704 | AT90: 0.96507057 | AU90: 0.97301919 | AV90: 407.60249 | AW90: -0.002975518 | AX90: 0.97301919 | AY90: 0.1192511 | BD90: 45155
A91: C6 | B91: 4397.85 | C91: 0 | D91: 9436.153 | E91: 45155 | F91: 2023-08-17C6 | G91: FALSE | H91: FALSE | I91: FALSE | J91: FALSE | K91: FALSE | L91: 4397.85 | M91: 4397.85 | N91: FALSE | O91: 4397.85 | P91: 0.9976125 | Q91: 376.17449 | R91: 9436.153 | S91: 9436.153 | X91: 0.058404098 | Y91: 0.9976534 | Z91: 0.9976534 | AA91: 372.93875 | AB91: -0.002349362 | AC91: 5.52e-06 | AD91: 0.1012109 | AE91: 0.11245923 | AF91: 0.11245923 | AH91: 374.95671 | AI91: 16.78 | AJ91: 380.58106 | AK91: 369.33236 | AL91: 0.000179123 | AM91: 0 | AN91: 0 | AO91: 0 | AP91: 0 | AR91: 0.12045846 | AS91: 0.95016704 | AT91: 0.96161395 | AU91: 0.96819429 | AV91: 406.67162 | AW91: -0.002283773 | AX91: 0.96819429 | AY91: 0.11945041 | BD91: 45155
A92: C7 | B92: 4388.575 | C92: 0 | D92: 9416.244 | E92: 45155 | F92: 2023-08-17C7 | G92: FALSE | H92: FALSE | I92: FALSE | J92: FALSE | K92: FALSE | L92: 4388.575 | M92: 4388.575 | N92: FALSE | O92: 4388.575 | P92: 0.99789101 | Q92: 375.38115 | R92: 9416.244 | S92: 9416.244 | T92: 45155 | U92: 9416.244 | V92: 375.38115 | W92: 0.059652464 | X92: 0.058404098 | Y92: 0.99789014 | Z92: 0.99789014 | AA92: 372.1519 | AB92: -0.002112093 | AC92: 4.46e-06 | AD92: 0.10050459 | AE92: 0.11182012 | AF92: 0.11182012 | AG92: 372.1519 | AH92: 374.95671 | AI92: 16.78 | AJ92: 380.58106 | AK92: 369.33236 | AL92: 0 | AN92: 0 | AO92: 0 | AP92: 0 | AQ92: 0.12032477 | AR92: 0.12045846 | AS92: 0.95016704 | AT92: 0.95974157 | AU92: 0.97163395 | AV92: 405.84075 | AW92: -0.002043102 | AX92: 0.97163395 | AY92: 0.1195701 | AZ92: 45155 | BA92: 405.84075 | BB92: 405.84074 | BC92: 7.23e-06 | BD92: 45155
A93: C1 | B93: 4367.25 | C93: 0 | D93: 9371.595 | E93: 45156 | F93: 2023-08-18C1 | G93: FALSE | H93: FALSE | I93: FALSE | J93: FALSE | K93: FALSE | L93: 4367.25 | M93: 4367.25 | N93: FALSE | O93: 4367.25 | P93: 0.99514079 | Q93: 373.55709 | R93: 9371.595 | S93: 9371.595 | X93: 0.059652464 | Y93: 0.9950926 | Z93: 0.9950926 | AA93: 370.3256 | AB93: -0.004919482 | AC93: 2.42e-05 | AD93: 0.1098024 | AE93: 0.11579879 | AF93: 0.11579879 | AH93: 372.1519 | AI93: 17.89 | AJ93: 377.73418 | AK93: 366.56962 | AL93: 0.001005842 | AM93: 0.000840498 | AN93: 6.77e-05 | AO93: -0.024528786 | AP93: -0.024461116 | AR93: 0.12032477 | AS93: 0.95144699 | AT93: 0.95861392 | AU93: 0.97850371 | AV93: 403.89971 | AW93: -0.004782773 | AX93: 0.97850371 | AY93: 0.12050582 | BD93: 45156
A94: C2 | B94: 4367.425 | C94: 0 | D94: 9371.99 | E94: 45156 | F94: 2023-08-18C2 | G94: FALSE | H94: FALSE | I94: FALSE | J94: FALSE | K94: FALSE | L94: 4367.425 | M94: 4367.425 | N94: FALSE | O94: 4367.425 | P94: 1.0000401 | Q94: 373.57206 | R94: 9371.99 | S94: 9371.99 | X94: 0.059652464 | Y94: 1.0000421 | Z94: 1.0000421 | AA94: 370.34121 | AB94: 4.21e-05 | AC94: 1.78e-09 | AD94: 0.10645826 | AE94: 0.114049 | AF94: 0.114049 | AH94: 372.1519 | AI94: 17.89 | AJ94: 377.73418 | AK94: 366.56962 | AL94: 0.000840498 | AM94: 0.000675154 | AN94: 1.07e-05 | AO94: -0.013748282 | AP94: -0.013737584 | AR94: 0.12032477 | AS94: 0.95144699 | AT94: 0.94971279 | AU94: 0.92429834 | AV94: 403.91417 | AW94: 3.58e-05 | AX94: 0.92429834 | AY94: 0.11977871 | BD94: 45156
A95: C3 | B95: 4377.7 | C95: 0 | D95: 9393.956 | E95: 45156 | F95: 2023-08-18C3 | G95: FALSE | H95: FALSE | I95: FALSE | J95: FALSE | K95: FALSE | L95: 4377.7 | M95: 4377.7 | N95: FALSE | O95: 4377.7 | P95: 1.0023526 | Q95: 374.45094 | R95: 9393.956 | S95: 9393.956 | X95: 0.059652464 | Y95: 1.0023438 | Z95: 1.0023438 | AA95: 371.20921 | AB95: 0.00234105 | AC95: 5.48e-06 | AD95: 0.10598782 | AE95: 0.11360892 | AF95: 0.11360892 | AH95: 372.1519 | AI95: 17.89 | AJ95: 377.73418 | AK95: 366.56962 | AL95: 0.000675154 | AM95: 0.00050981 | AN95: 8.1e-06 | AO95: -0.000917531 | AP95: -0.000909433 | AR95: 0.12032477 | AS95: 0.95144699 | AT95: 0.95664271 | AU95: 0.94978688 | AV95: 404.78817 | AW95: 0.002163815 | AX95: 0.94978688 | AY95: 0.11993964 | BD95: 45156
A96: C4 | B96: 4383.75 | C96: 0 | D96: 9407.127 | E96: 45156 | F96: 2023-08-18C4 | G96: FALSE | H96: FALSE | I96: FALSE | J96: FALSE | K96: FALSE | L96: 4383.75 | M96: 4383.75 | N96: FALSE | O96: 4383.75 | P96: 1.001382 | Q96: 374.96844 | R96: 9407.127 | S96: 9407.127 | X96: 0.059652464 | Y96: 1.0014021 | Z96: 1.0014021 | AA96: 371.72968 | AB96: 0.00140109 | AC96: 1.96e-06 | AD96: 0.10376503 | AE96: 0.11235507 | AF96: 0.11235507 | AH96: 372.1519 | AI96: 17.89 | AJ96: 377.73418 | AK96: 366.56962 | AL96: 0.00050981 | AM96: 0.000344466 | AN96: 7.03e-07 | AO96: -1.27e-05 | AP96: -1.2e-05 | AR96: 0.12032477 | AS96: 0.95144699 | AT96: 0.95511689 | AU96: 0.96309693 | AV96: 405.32668 | AW96: 0.001330338 | AX96: 0.96309693 | AY96: 0.12004367 | BD96: 45156
A97: C5 | B97: 4378.575 | C97: 0 | D97: 9396.258 | E97: 45156 | F97: 2023-08-18C5 | G97: FALSE | H97: FALSE | I97: FALSE | J97: FALSE | K97: FALSE | L97: 4378.575 | M97: 4378.575 | N97: FALSE | O97: 4378.575 | P97: 0.9988195 | Q97: 374.52579 | R97: 9396.258 | S97: 9396.258 | X97: 0.059652464 | Y97: 0.9988446 | Z97: 0.9988446 | AA97: 371.30018 | AB97: -0.001156069 | AC97: 1.34e-06 | AD97: 0.10130452 | AE97: 0.11097603 | AF97: 0.11097603 | AH97: 372.1519 | AI97: 17.89 | AJ97: 377.73418 | AK97: 366.56962 | AL97: 0.000344466 | AM97: 0.000179123 | AN97: 3.64e-13 | AO97: -4.24e-08 | AP97: -4.24e-08 | AR97: 0.12032477 | AS97: 0.95144699 | AT97: 0.95412814 | AU97: 0.97384481 | AV97: 404.87521 | AW97: -0.001113838 | AX97: 0.97384481 | AY97: 0.12007871 | BD97: 45156
A98: C6 | B98: 4383.025 | C98: 0 | D98: 9406.43 | E98: 45156 | F98: 2023-08-18C6 | G98: FALSE | H98: FALSE | I98: FALSE | J98: FALSE | K98: FALSE | L98: 4383.025 | M98: 4383.025 | N98: FALSE | O98: 4383.025 | P98: 1.0010163 | Q98: 374.90642 | R98: 9406.43 | S98: 9406.43 | X98: 0.059652464 | Y98: 1.0010826 | Z98: 1.0010826 | AA98: 371.70213 | AB98: 0.001081973 | AC98: 1.17e-06 | AD98: 0.098847119 | AE98: 0.10958176 | AF98: 0.10958176 | AH98: 372.1519 | AI98: 17.89 | AJ98: 377.73418 | AK98: 366.56962 | AL98: 0.000179123 | AM98: 0 | AN98: 0 | AO98: 0 | AP98: 0 | AR98: 0.12032477 | AS98: 0.95144699 | AT98: 0.95379468 | AU98: 0.98594626 | AV98: 405.30155 | AW98: 0.001053034 | AX98: 0.98594626 | AY98: 0.11982818 | BD98: 45156
A99: C7 | B99: 4385.225 | C99: 0 | D99: 9409.995 | E99: 45156 | F99: 2023-08-18C7 | G99: FALSE | H99: FALSE | I99: FALSE | J99: FALSE | K99: FALSE | L99: 4385.225 | M99: 4385.225 | N99: FALSE | O99: 4385.225 | P99: 1.0005019 | Q99: 375.0946 | R99: 9409.995 | S99: 9409.995 | T99: 45156 | U99: 9409.995 | V99: 375.0946 | W99: 0.058122122 | X99: 0.059652464 | Y99: 1.000379 | Z99: 1.000379 | AA99: 371.84301 | AB99: 0.000378924 | AC99: 1.44e-07 | AD99: 0.095915091 | AE99: 0.10796071 | AF99: 0.10796071 | AG99: 371.84301 | AH99: 372.1519 | AI99: 17.89 | AJ99: 377.73418 | AK99: 366.56962 | AL99: 0 | AN99: 0 | AO99: 0 | AP99: 0 | AQ99: 0.12032836 | AR99: 0.12032477 | AS99: 0.95144699 | AT99: 0.9561741 | AU99: 0.99849108 | AV99: 405.4525 | AW99: 0.000372415 | AX99: 0.99849108 | AY99: 0.11979647 | AZ99: 45156 | BA99: 405.4525 | BB99: 405.45249 | BC99: 7.29e-06 | BD99: 45156
A100: C1 | B100: 4397.425 | C100: 0 | D100: 9439.94 | E100: 45159 | F100: 2023-08-21C1 | G100: FALSE | H100: FALSE | I100: FALSE | J100: FALSE | K100: FALSE | L100: 4397.425 | M100: 4397.425 | N100: FALSE | O100: 4397.425 | P100: 1.0027821 | Q100: 376.13814 | R100: 9439.94 | S100: 9439.94 | X100: 0.058122122 | Y100: 1.0026979 | Z100: 1.0026979 | AA100: 372.8462 | AB100: 0.002694271 | AC100: 7.26e-06 | AD100: 0.097036204 | AE100: 0.1081203 | AF100: 0.1081203 | AH100: 371.84301 | AI100: 17.3 | AJ100: 377.42065 | AK100: 366.26536 | AL100: 0.001005842 | AM100: 0.000840498 | AN100: 0.007573985 | AO100: -0.000190374 | AP100: 0.007383611 | AR100: 0.12032836 | AS100: 0.9514127 | AT100: 0.95647458 | AU100: 1.013447 | AV100: 406.52722 | AW100: 0.00265067 | AX100: 1.013447 | AY100: 0.11988172 | BD100: 45159
...

Sheet April25 Exposure
A1: CHANGE | B1: DATE OF INDEX | C1: INDEX NAME | D1: INDEX CODE | E1: INDEX KEY | F1: GICS CODE | G1: ISO CODE | H1: INDEX VALUE | I1: CLOSE MARKET CAP | J1: CLOSE DIVISOR | K1: CLOSE COUNT | L1: DAILY RETURN | M1: INDEX DIVIDEND | N1: ADJ MARKET CAP | O1: ADJ DIVISOR | P1: ADJ COUNT
B2: 20250331 | C2: S&P 500 FC TCA 0.50% Decrement Index (USD) ER - C1 - EXPOSURE LEVEL | D2: SPXFCDUC1EL | G2: USD | H2: 0.30592154 | L2: -0.51564923
B3: 20250331 | C3: S&P 500 FC TCA 0.50% Decrement Index (USD) ER - C2 - EXPOSURE LEVEL | D3: SPXFCDUC2EL | G3: USD | H3: 0.23859211 | L3: -0.60707076
B4: 20250331 | C4: S&P 500 FC TCA 0.50% Decrement Index (USD) ER - C3 - EXPOSURE LEVEL | D4: SPXFCDUC3EL | G4: USD | H4: 0.38859211 | L4: 0.087841446
B5: 20250331 | C5: S&P 500 FC TCA 0.50% Decrement Index (USD) ER - C4 - EXPOSURE LEVEL | D5: SPXFCDUC4EL | G5: USD | H5: 0.46198349 | L5: 0.76270427
B6: 20250331 | C6: S&P 500 FC TCA 0.50% Decrement Index (USD) ER - C5 - EXPOSURE LEVEL | D6: SPXFCDUC5EL | G6: USD | H6: 0.48111861 | L6: 4.122777
B7: 20250331 | C7: S&P 500 FC TCA 0.50% Decrement Index (USD) ER - C6 - EXPOSURE LEVEL | D7: SPXFCDUC6EL | G7: USD | H7: 0.4951521 | L7: 82.618743
B8: 20250331 | C8: S&P 500 FC TCA 0.50% Decrement Index (USD) ER - C7 - EXPOSURE LEVEL | D8: SPXFCDUC7EL | G8: USD | H8: 0.4830342 | L8: 2.0979311
B9: 20250401 | C9: S&P 500 FC TCA 0.50% Decrement Index (USD) ER - C1 - EXPOSURE LEVEL | D9: SPXFCDUC1EL | G9: USD | H9: 0.49274464 | L9: 0.61068956
B10: 20250401 | C10: S&P 500 FC TCA 0.50% Decrement Index (USD) ER - C2 - EXPOSURE LEVEL | D10: SPXFCDUC2EL | G10: USD | H10: 0.49528223 | L10: 1.0758534
B11: 20250401 | C11: S&P 500 FC TCA 0.50% Decrement Index (USD) ER - C3 - EXPOSURE LEVEL | D11: SPXFCDUC3EL | G11: USD | H11: 0.51575713 | L11: 0.32724552
B12: 20250401 | C12: S&P 500 FC TCA 0.50% Decrement Index (USD) ER - C4 - EXPOSURE LEVEL | D12: SPXFCDUC4EL | G12: USD | H12: 0.522776 | L12: 0.13159024
B13: 20250401 | C13: S&P 500 FC TCA 0.50% Decrement Index (USD) ER - C5 - EXPOSURE LEVEL | D13: SPXFCDUC5EL | G13: USD | H13: 0.53160171 | L13: 0.1049286
... B155: 20250430 | C155: S&P 500 FC TCA 0.50% Decrement Index (USD) ER - C7 - EXPOSURE LEVEL | D155: SPXFCDUC7EL | G155: USD | H155: 0.35210984 | L155: -0.036183155

Sheet Daily Returns
B1: ='Index Levels'!B2 -> S&P 500 FC TCA 0.50% Decrement Index (USD) ER | C1: ='Index Levels'!C2 -> S&P 500
A2: ='Index Levels'!A3 -> 44286
A3: ='Index Levels'!A4 -> 44287 | B3: ='Index Levels'!B4/'Index Levels'!B3-1 -> 0.0088653585 | C3: ='Index Levels'!C4/'Index Levels'!C3-1 -> 0.011823436
A4: ='Index Levels'!A5 -> 44291 | B4: ='Index Levels'!B5/'Index Levels'!B4-1 -> 0.015857785 | C4: ='Index Levels'!C5/'Index Levels'!C4-1 -> 0.014440348
A5: ='Index Levels'!A6 -> 44292 | B5: ='Index Levels'!B6/'Index Levels'!B5-1 -> -0.0023458125 | C5: ='Index Levels'!C6/'Index Levels'!C5-1 -> -0.00097428113
A6: ='Index Levels'!A7 -> 44293 | B6: ='Index Levels'!B7/'Index Levels'!B6-1 -> 0.0018170128 | C6: ='Index Levels'!C7/'Index Levels'!C6-1 -> 0.0014757844
A7: ='Index Levels'!A8 -> 44294 | B7: ='Index Levels'!B8/'Index Levels'!B7-1 -> 0.0053020317 | C7: ='Index Levels'!C8/'Index Levels'!C7-1 -> 0.0042194411
A8: ='Index Levels'!A9 -> 44295 | B8: ='Index Levels'!B9/'Index Levels'!B8-1 -> 0.0097997352 | C8: ='Index Levels'!C9/'Index Levels'!C8-1 -> 0.0077209509
A9: ='Index Levels'!A10 -> 44298 | B9: ='Index Levels'!B10/'Index Levels'!B9-1 -> 0.00084522215 | C9: ='Index Levels'!C10/'Index Levels'!C9-1 -> -0.00019590323
A10: ='Index Levels'!A11 -> 44299 | B10: ='Index Levels'!B11/'Index Levels'!B10-1 -> 0.0043654417 | C10: ='Index Levels'!C11/'Index Levels'!C10-1 -> 0.0032947063
A11: ='Index Levels'!A12 -> 44300 | B11: ='Index Levels'!B12/'Index Levels'!B11-1 -> -0.007140187 | C11: ='Index Levels'!C12/'Index Levels'!C11-1 -> -0.004088554
A12: ='Index Levels'!A13 -> 44301 | B12: ='Index Levels'!B13/'Index Levels'!B12-1 -> 0.017942188 | C12: ='Index Levels'!C13/'Index Levels'!C12-1 -> 0.01109477
A13: ='Index Levels'!A14 -> 44302 | B13: ='Index Levels'!B14/'Index Levels'!B13-1 -> 0.0055011571 | C13: ='Index Levels'!C14/'Index Levels'!C13-1 -> 0.0036077687
A14: ='Index Levels'!A15 -> 44305 | B14: ='Index Levels'!B15/'Index Levels'!B14-1 -> -0.0098046141 | C14: ='Index Levels'!C15/'Index Levels'!C14-1 -> -0.0053066017
... A567: ='Index Levels'!A568 -> 45106 | B567: ='Index Levels'!B568/'Index Levels'!B567-1 -> 0.005704908 | C567: ='Index Levels'!C568/'Index Levels'!C567-1 -> 0.004473456
A568: ='Index Levels'!A569 -> 45107 | B568: ='Index Levels'!B569/'Index Levels'!B568-1 -> 0.015243513 | C568: ='Index Levels'!C569/'Index Levels'!C568-1 -> 0.012268529 | D568: =_xlfn.STDEV.S(B318:B568)*SQRT(252) -> 0.12160628 | E568: =_xlfn.STDEV.S(C318:C568)*SQRT(252) -> 0.19394666 | F568: =E568-D568 -> 0.072340382
A569: ='Index Levels'!A570 -> 45110 | B569: ='Index Levels'!B570/'Index Levels'!B569-1 -> -0.00033272744 | C569: ='Index Levels'!C570/'Index Levels'!C569-1 -> 0.0011712623
A570: ='Index Levels'!A571 -> 45112 | B570: ='Index Levels'!B571/'Index Levels'!B570-1 -> -0.0016134468 | C570: ='Index Levels'!C571/'Index Levels'!C570-1 -> -0.0019681105
A571: ='Index Levels'!A572 -> 45113 | B571: ='Index Levels'!B572/'Index Levels'!B571-1 -> -0.011721565 | C571: ='Index Levels'!C572/'Index Levels'!C571-1 -> -0.0079234157
A572: ='Index Levels'!A573 -> 45114 | B572: ='Index Levels'!B573/'Index Levels'!B572-1 -> -0.0023794695 | C572: ='Index Levels'!C573/'Index Levels'!C572-1 -> -0.002864743
A573: ='Index Levels'!A574 -> 45117 | B573: ='Index Levels'!B574/'Index Levels'!B573-1 -> 0.00027536288 | C573: ='Index Levels'!C574/'Index Levels'!C573-1 -> 0.0024035594
A574: ='Index Levels'!A575 -> 45118 | B574: ='Index Levels'!B575/'Index Levels'!B574-1 -> 0.008038161 | C574: ='Index Levels'!C575/'Index Levels'!C574-1 -> 0.0067423413
A575: ='Index Levels'!A576 -> 45119 | B575: ='Index Levels'!B576/'Index Levels'!B575-1 -> 0.0084291238 | C575: ='Index Levels'!C576/'Index Levels'!C575-1 -> 0.0074120508
A576: ='Index Levels'!A577 -> 45120 | B576: ='Index Levels'!B577/'Index Levels'!B576-1 -> 0.0079905489 | C576: ='Index Levels'!C577/'Index Levels'!C576-1 -> 0.0084705083
A577: ='Index Levels'!A578 -> 45121 | B577: ='Index Levels'!B578/'Index Levels'!B577-1 -> -0.0019361769 | C577: ='Index Levels'!C578/'Index Levels'!C577-1 -> -0.0010247039
A578: ='Index Levels'!A579 -> 45124 | B578: ='Index Levels'!B579/'Index Levels'!B578-1 -> 0.0043929858 | C578: ='Index Levels'!C579/'Index Levels'!C578-1 -> 0.0038559688
A579: ='Index Levels'!A580 -> 45125 | B579: ='Index Levels'!B580/'Index Levels'!B579-1 -> 0.0086268998 | C579: ='Index Levels'!C580/'Index Levels'!C579-1 -> 0.0071159227
A580: ='Index Levels'!A581 -> 45126 | B580: ='Index Levels'!B581/'Index Levels'!B580-1 -> 0.0026704419 | C580: ='Index Levels'!C581/'Index Levels'!C580-1 -> 0.0023578085
... A587: ='Index Levels'!A588 -> 45135 | B587: ='Index Levels'!B588/'Index Levels'!B587-1 -> 0.0079577086 | C587: ='Index Levels'!C588/'Index Levels'!C587-1 -> 0.0098777589
A588: ='Index Levels'!A589 -> 45138 | B588: ='Index Levels'!B589/'Index Levels'!B588-1 -> -0.00052669353 | C588: ='Index Levels'!C589/'Index Levels'!C588-1 -> 0.001468676 | D588: =_xlfn.STDEV.S(B338:B588)*SQRT(252) -> 0.11913598 | E588: =_xlfn.STDEV.S(C338:C588)*SQRT(252) -> 0.18712047 | F588: =E588-D588 -> 0.067984485
A589: ='Index Levels'!A590 -> 45139 | B589: ='Index Levels'!B590/'Index Levels'!B589-1 -> -0.00063129368 | C589: ='Index Levels'!C590/'Index Levels'!C589-1 -> -0.0026655245
A590: ='Index Levels'!A591 -> 45140 | B590: ='Index Levels'!B591/'Index Levels'!B590-1 -> -0.01502329 | C590: ='Index Levels'!C591/'Index Levels'!C590-1 -> -0.013838549
A591: ='Index Levels'!A592 -> 45141 | B591: ='Index Levels'!B592/'Index Levels'!B591-1 -> -0.0026937891 | C591: ='Index Levels'!C592/'Index Levels'!C591-1 -> -0.0025497847
A592: ='Index Levels'!A593 -> 45142 | B592: ='Index Levels'!B593/'Index Levels'!B592-1 -> -0.0066954661 | C592: ='Index Levels'!C593/'Index Levels'!C592-1 -> -0.0052981869
A593: ='Index Levels'!A594 -> 45145 | B593: ='Index Levels'!B594/'Index Levels'!B593-1 -> 0.0068624315 | C593: ='Index Levels'!C594/'Index Levels'!C593-1 -> 0.0090239428
A594: ='Index Levels'!A595 -> 45146 | B594: ='Index Levels'!B595/'Index Levels'!B594-1 -> -0.0043721003 | C594: ='Index Levels'!C595/'Index Levels'!C594-1 -> -0.0042196179
A595: ='Index Levels'!A596 -> 45147 | B595: ='Index Levels'!B596/'Index Levels'!B595-1 -> -0.0060306086 | C595: ='Index Levels'!C596/'Index Levels'!C595-1 -> -0.0070372332
A596: ='Index Levels'!A597 -> 45148 | B596: ='Index Levels'!B597/'Index Levels'!B596-1 -> 0.0012065015 | C596: ='Index Levels'!C597/'Index Levels'!C596-1 -> 0.00025083984
A597: ='Index Levels'!A598 -> 45149 | B597: ='Index Levels'!B598/'Index Levels'!B597-1 -> -0.00091452195 | C597: ='Index Levels'!C598/'Index Levels'!C597-1 -> -0.0010696772
A598: ='Index Levels'!A599 -> 45152 | B598: ='Index Levels'!B599/'Index Levels'!B598-1 -> 0.0034657611 | C598: ='Index Levels'!C599/'Index Levels'!C598-1 -> 0.0057489819
A599: ='Index Levels'!A600 -> 45153 | B599: ='Index Levels'!B600/'Index Levels'!B599-1 -> -0.0087374782 | C599: ='Index Levels'!C600/'Index Levels'!C599-1 -> -0.011550676
A600: ='Index Levels'!A601 -> 45154 | B600: ='Index Levels'!B601/'Index Levels'!B600-1 -> -0.0065566403 | C600: ='Index Levels'!C601/'Index Levels'!C600-1 -> -0.0075544491
... A610: ='Index Levels'!A611 -> 45168 | B610: ='Index Levels'!B611/'Index Levels'!B610-1 -> 0.0034585707 | C610: ='Index Levels'!C611/'Index Levels'!C610-1 -> 0.003831704
A611: ='Index Levels'!A612 -> 45169 | B611: ='Index Levels'!B612/'Index Levels'!B611-1 -> -6.3560335e-05 | C611: ='Index Levels'!C612/'Index Levels'!C611-1 -> -0.0015954998 | D611: =_xlfn.STDEV.S(B361:B611)*SQRT(252) -> 0.11864409 | E611: =_xlfn.STDEV.S(C360:C611)*SQRT(252) -> 0.18137853 | F611: =E611-D611 -> 0.062734443
A612: ='Index Levels'!A613 -> 45170 | B612: ='Index Levels'!B613/'Index Levels'!B612-1 -> 0.00023082896 | C612: ='Index Levels'!C613/'Index Levels'!C612-1 -> 0.0017981838
A613: ='Index Levels'!A614 -> 45174 | B613: ='Index Levels'!B614/'Index Levels'!B613-1 -> -0.0048588777 | C613: ='Index Levels'!C614/'Index Levels'!C613-1 -> -0.0041942181
A614: ='Index Levels'!A615 -> 45175 | B614: ='Index Levels'!B615/'Index Levels'!B614-1 -> -0.0098046497 | C614: ='Index Levels'!C615/'Index Levels'!C614-1 -> -0.0069699184
A615: ='Index Levels'!A616 -> 45176 | B615: ='Index Levels'!B616/'Index Levels'!B615-1 -> -0.0030139195 | C615: ='Index Levels'!C616/'Index Levels'!C615-1 -> -0.0032128171
A616: ='Index Levels'!A617 -> 45177 | B616: ='Index Levels'!B617/'Index Levels'!B616-1 -> 0.00018041758 | C616: ='Index Levels'!C617/'Index Levels'!C616-1 -> 0.0014269004
A617: ='Index Levels'!A618 -> 45180 | B617: ='Index Levels'!B618/'Index Levels'!B617-1 -> 0.0080746568 | C617: ='Index Levels'!C618/'Index Levels'!C617-1 -> 0.0067245374
A618: ='Index Levels'!A619 -> 45181 | B618: ='Index Levels'!B619/'Index Levels'!B618-1 -> -0.0067078879 | C618: ='Index Levels'!C619/'Index Levels'!C618-1 -> -0.0056956325
A619: ='Index Levels'!A620 -> 45182 | B619: ='Index Levels'!B620/'Index Levels'!B619-1 -> 0.0008643553 | C619: ='Index Levels'!C620/'Index Levels'!C619-1 -> 0.0012409524
A620: ='Index Levels'!A621 -> 45183 | B620: ='Index Levels'!B621/'Index Levels'!B620-1 -> 0.01251967 | C620: ='Index Levels'!C621/'Index Levels'!C620-1 -> 0.0084286158
A621: ='Index Levels'!A622 -> 45184 | B621: ='Index Levels'!B622/'Index Levels'!B621-1 -> -0.017334558 | C621: ='Index Levels'!C622/'Index Levels'!C621-1 -> -0.012159562
A622: ='Index Levels'!A623 -> 45187 | B622: ='Index Levels'!B623/'Index Levels'!B622-1 -> -0.00026379423 | C622: ='Index Levels'!C623/'Index Levels'!C622-1 -> 0.00072298552
A623: ='Index Levels'!A624 -> 45188 | B623: ='Index Levels'!B624/'Index Levels'!B623-1 -> -0.0026720955 | C623: ='Index Levels'!C624/'Index Levels'!C623-1 -> -0.0021525148
... A630: ='Index Levels'!A631 -> 45197 | B630: ='Index Levels'!B631/'Index Levels'!B630-1 -> 0.004993562 | C630: ='Index Levels'!C631/'Index Levels'!C630-1 -> 0.005893677
A631: ='Index Levels'!A632 -> 45198 | B631: ='Index Levels'!B632/'Index Levels'!B631-1 -> -0.0012319894 | C631: ='Index Levels'!C632/'Index Levels'!C631-1 -> -0.0027089946 | D631: =_xlfn.STDEV.S(B382:B631)*SQRT(252) -> 0.11888346 | E631: =_xlfn.STDEV.S(C382:C631)*SQRT(252) -> 0.17049842 | F631: =E631-D631 -> 0.051614959
A632: ='Index Levels'!A633 -> 45201 | B632: ='Index Levels'!B633/'Index Levels'!B632-1 -> -0.0023685477 | C632: ='Index Levels'!C633/'Index Levels'!C632-1 -> 7.8492215e-05
A633: ='Index Levels'!A634 -> 45202 | B633: ='Index Levels'!B634/'Index Levels'!B633-1 -> -0.011271675 | C633: ='Index Levels'!C634/'Index Levels'!C633-1 -> -0.013743541
A634: ='Index Levels'!A635 -> 45203 | B634: ='Index Levels'!B635/'Index Levels'!B634-1 -> 0.0066588572 | C634: ='Index Levels'!C635/'Index Levels'!C634-1 -> 0.0081093499
A635: ='Index Levels'!A636 -> 45204 | B635: ='Index Levels'!B636/'Index Levels'!B635-1 -> -0.0011911327 | C635: ='Index Levels'!C636/'Index Levels'!C635-1 -> -0.0013052681
A636: ='Index Levels'!A637 -> 45205 | B636: ='Index Levels'!B637/'Index Levels'!B636-1 -> 0.0084017112 | C636: ='Index Levels'!C637/'Index Levels'!C636-1 -> 0.011816406
A637: ='Index Levels'!A638 -> 45208 | B637: ='Index Levels'!B638/'Index Levels'!B637-1 -> 0.0032119832 | C637: ='Index Levels'!C638/'Index Levels'!C637-1 -> 0.0063027141
A638: ='Index Levels'!A639 -> 45209 | B638: ='Index Levels'!B639/'Index Levels'!B638-1 -> 0.0035698205 | C638: ='Index Levels'!C639/'Index Levels'!C638-1 -> 0.0052080547
A639: ='Index Levels'!A640 -> 45210 | B639: ='Index Levels'!B640/'Index Levels'!B639-1 -> 0.0030196842 | C639: ='Index Levels'!C640/'Index Levels'!C639-1 -> 0.0042924056
A640: ='Index Levels'!A641 -> 45211 | B640: ='Index Levels'!B641/'Index Levels'!B640-1 -> -0.0050292609 | C640: ='Index Levels'!C641/'Index Levels'!C640-1 -> -0.0062462302
A641: ='Index Levels'!A642 -> 45212 | B641: ='Index Levels'!B642/'Index Levels'!B641-1 -> -0.0043655499 | C641: ='Index Levels'!C642/'Index Levels'!C641-1 -> -0.0050171786
A642: ='Index Levels'!A643 -> 45215 | B642: ='Index Levels'!B643/'Index Levels'!B642-1 -> 0.0083531831 | C642: ='Index Levels'!C643/'Index Levels'!C642-1 -> 0.01059475
A643: ='Index Levels'!A644 -> 45216 | B643: ='Index Levels'!B644/'Index Levels'!B643-1 -> -0.0015078069 | C643: ='Index Levels'!C644/'Index Levels'!C643-1 -> -0.00010033282
... A652: ='Index Levels'!A653 -> 45229 | B652: ='Index Levels'!B653/'Index Levels'!B652-1 -> 0.0098330894 | C652: ='Index Levels'!C653/'Index Levels'!C652-1 -> 0.012007973
A653: ='Index Levels'!A654 -> 45230 | B653: ='Index Levels'!B654/'Index Levels'!B653-1 -> 0.0041509615 | C653: ='Index Levels'!C654/'Index Levels'!C653-1 -> 0.0064763646 | D653: =_xlfn.STDEV.S(B403:B653)*SQRT(252) -> 0.11804579 | E653: =_xlfn.STDEV.S(C403:C653)*SQRT(252) -> 0.1555814 | F653: =E653-D653 -> 0.037535603
A654: ='Index Levels'!A655 -> 45231 | B654: ='Index Levels'!B655/'Index Levels'!B654-1 -> 0.0082792499 | C654: ='Index Levels'!C655/'Index Levels'!C654-1 -> 0.010504717 | D654: =_xlfn.STDEV.S(B632:B653)*SQRT(252) -> 0.10895789 | E654: =_xlfn.STDEV.S(C632:C653)*SQRT(252) -> 0.14101838 | F654: =E654-D654 -> 0.032060482
A655: ='Index Levels'!A656 -> 45232 | B655: ='Index Levels'!B656/'Index Levels'!B655-1 -> 0.015607867 | C655: ='Index Levels'!C656/'Index Levels'!C655-1 -> 0.018858553
A656: ='Index Levels'!A657 -> 45233 | B656: ='Index Levels'!B657/'Index Levels'!B656-1 -> 0.0088554403 | C656: ='Index Levels'!C657/'Index Levels'!C656-1 -> 0.0093936582
A657: ='Index Levels'!A658 -> 45236 | B657: ='Index Levels'!B658/'Index Levels'!B657-1 -> 6.7287062e-05 | C657: ='Index Levels'!C658/'Index Levels'!C657-1 -> 0.0017536136
A658: ='Index Levels'!A659 -> 45237 | B658: ='Index Levels'!B659/'Index Levels'!B658-1 -> 0.002605125 | C658: ='Index Levels'!C659/'Index Levels'!C658-1 -> 0.0028404004
A659: ='Index Levels'!A660 -> 45238 | B659: ='Index Levels'!B660/'Index Levels'!B659-1 -> 0.0012848557 | C659: ='Index Levels'!C660/'Index Levels'!C659-1 -> 0.0010059979
A660: ='Index Levels'!A661 -> 45239 | B660: ='Index Levels'!B661/'Index Levels'!B660-1 -> -0.0082942502 | C660: ='Index Levels'!C661/'Index Levels'!C660-1 -> -0.0080849218
A661: ='Index Levels'!A662 -> 45240 | B661: ='Index Levels'!B662/'Index Levels'!B661-1 -> 0.015032256 | C661: ='Index Levels'!C662/'Index Levels'!C661-1 -> 0.015617648
A662: ='Index Levels'!A663 -> 45243 | B662: ='Index Levels'!B663/'Index Levels'!B662-1 -> -0.0013255307 | C662: ='Index Levels'!C663/'Index Levels'!C662-1 -> -0.00083569566
A663: ='Index Levels'!A664 -> 45244 | B663: ='Index Levels'!B664/'Index Levels'!B663-1 -> 0.016945007 | C663: ='Index Levels'!C664/'Index Levels'!C663-1 -> 0.019074159
A664: ='Index Levels'!A665 -> 45245 | B664: ='Index Levels'!B665/'Index Levels'!B664-1 -> 0.0021328293 | C664: ='Index Levels'!C665/'Index Levels'!C664-1 -> 0.0015964674
A665: ='Index Levels'!A666 -> 45246 | B665: ='Index Levels'!B666/'Index Levels'!B665-1 -> 0.00083028094 | C665: ='Index Levels'!C666/'Index Levels'!C665-1 -> 0.0011913857
A666: ='Index Levels'!A667 -> 45247 | B666: ='Index Levels'!B667/'Index Levels'!B666-1 -> 0.0011119379 | C666: ='Index Levels'!C667/'Index Levels'!C666-1 -> 0.0012808465
... A673: ='Index Levels'!A674 -> 45259 | B673: ='Index Levels'!B674/'Index Levels'!B673-1 -> -0.00076821209 | C673: ='Index Levels'!C674/'Index Levels'!C673-1 -> -0.00094584908
A674: ='Index Levels'!A675 -> 45260 | B674: ='Index Levels'!B675/'Index Levels'!B674-1 -> 0.0045216059 | C674: ='Index Levels'!C675/'Index Levels'!C674-1 -> 0.0037833236 | D674: =_xlfn.STDEV.S(B424:B674)*SQRT(252) -> 0.11667899 | E674: =_xlfn.STDEV.S(C424:C674)*SQRT(252) -> 0.13834011 | F674: =E674-D674 -> 0.021661116
A675: ='Index Levels'!A676 -> 45261 | B675: ='Index Levels'!B676/'Index Levels'!B675-1 -> 0.0078991293 | C675: ='Index Levels'!C676/'Index Levels'!C675-1 -> 0.0058743698 | D675: =_xlfn.STDEV.S(B653:B674)*SQRT(252) -> 0.099298614 | E675: =_xlfn.STDEV.S(C653:C674)*SQRT(252) -> 0.10920457 | F675: =E675-D675 -> 0.0099059587
A676: ='Index Levels'!A677 -> 45264 | B676: ='Index Levels'!B677/'Index Levels'!B676-1 -> -0.007664614 | C676: ='Index Levels'!C677/'Index Levels'!C676-1 -> -0.0054084897
A677: ='Index Levels'!A678 -> 45265 | B677: ='Index Levels'!B678/'Index Levels'!B677-1 -> -0.0013709675 | C677: ='Index Levels'!C678/'Index Levels'!C677-1 -> -0.00056864618
A678: ='Index Levels'!A679 -> 45266 | B678: ='Index Levels'!B679/'Index Levels'!B678-1 -> -0.0049782607 | C678: ='Index Levels'!C679/'Index Levels'!C678-1 -> -0.0039073522
A679: ='Index Levels'!A680 -> 45267 | B679: ='Index Levels'!B680/'Index Levels'!B679-1 -> 0.010000363 | C679: ='Index Levels'!C680/'Index Levels'!C679-1 -> 0.007967932
A680: ='Index Levels'!A681 -> 45268 | B680: ='Index Levels'!B681/'Index Levels'!B680-1 -> 0.0056310256 | C680: ='Index Levels'!C681/'Index Levels'!C680-1 -> 0.0040967635
A681: ='Index Levels'!A682 -> 45271 | B681: ='Index Levels'!B682/'Index Levels'!B681-1 -> 0.0040134969 | C681: ='Index Levels'!C682/'Index Levels'!C681-1 -> 0.0039242092
A682: ='Index Levels'!A683 -> 45272 | B682: ='Index Levels'!B683/'Index Levels'!B682-1 -> 0.0062927434 | C682: ='Index Levels'!C683/'Index Levels'!C682-1 -> 0.0045995178
A683: ='Index Levels'!A684 -> 45273 | B683: ='Index Levels'!B684/'Index Levels'!B683-1 -> 0.019746141 | C683: ='Index Levels'!C684/'Index Levels'!C683-1 -> 0.013650659
A684: ='Index Levels'!A685 -> 45274 | B684: ='Index Levels'!B685/'Index Levels'!B684-1 -> 0.0062879786 | C684: ='Index Levels'!C685/'Index Levels'!C684-1 -> 0.0026471882
A685: ='Index Levels'!A686 -> 45275 | B685: ='Index Levels'!B686/'Index Levels'!B685-1 -> 0.00092959648 | C685: ='Index Levels'!C686/'Index Levels'!C685-1 -> -7.6547522e-05
A686: ='Index Levels'!A687 -> 45278 | B686: ='Index Levels'!B687/'Index Levels'!B686-1 -> 0.0040384652 | C686: ='Index Levels'!C687/'Index Levels'!C686-1 -> 0.0045273366
A687: ='Index Levels'!A688 -> 45279 | B687: ='Index Levels'!B688/'Index Levels'!B687-1 -> 0.0052841449 | C687: ='Index Levels'!C688/'Index Levels'!C687-1 -> 0.0058662647
...

Sheet Index Levels - Full
B1: ='Index Levels'!B2 -> S&P 500 FC TCA 0.50% Decrement Index (USD) ER | C1: ='Index Levels'!C2 -> S&P 500
A2: 44286 | B2: =IFERROR(INDEX('Index Levels'!B:B,MATCH('Index Levels - Full'!$A2,'Index Levels'!$A:$A,0)),B1) -> 385.28802 | C2: =IFERROR(INDEX('Index Levels'!C:C,MATCH('Index Levels - Full'!$A2,'Index Levels'!$A:$A,0)),C1) -> 3972.8922
A3: =A2+1 -> 44287 | B3: =IFERROR(INDEX('Index Levels'!B:B,MATCH('Index Levels - Full'!$A3,'Index Levels'!$A:$A,0)),B2) -> 388.70373 | C3: =IFERROR(INDEX('Index Levels'!C:C,MATCH('Index Levels - Full'!$A3,'Index Levels'!$A:$A,0)),C2) -> 4019.8654
A4: =A3+1 -> 44288 | B4: =IFERROR(INDEX('Index Levels'!B:B,MATCH('Index Levels - Full'!$A4,'Index Levels'!$A:$A,0)),B3) -> 388.70373 | C4: =IFERROR(INDEX('Index Levels'!C:C,MATCH('Index Levels - Full'!$A4,'Index Levels'!$A:$A,0)),C3) -> 4019.8654
A5: =A4+1 -> 44289 | B5: =IFERROR(INDEX('Index Levels'!B:B,MATCH('Index Levels - Full'!$A5,'Index Levels'!$A:$A,0)),B4) -> 388.70373 | C5: =IFERROR(INDEX('Index Levels'!C:C,MATCH('Index Levels - Full'!$A5,'Index Levels'!$A:$A,0)),C4) -> 4019.8654
A6: =A5+1 -> 44290 | B6: =IFERROR(INDEX('Index Levels'!B:B,MATCH('Index Levels - Full'!$A6,'Index Levels'!$A:$A,0)),B5) -> 388.70373 | C6: =IFERROR(INDEX('Index Levels'!C:C,MATCH('Index Levels - Full'!$A6,'Index Levels'!$A:$A,0)),C5) -> 4019.8654
A7: =A6+1 -> 44291 | B7: =IFERROR(INDEX('Index Levels'!B:B,MATCH('Index Levels - Full'!$A7,'Index Levels'!$A:$A,0)),B6) -> 394.86771 | C7: =IFERROR(INDEX('Index Levels'!C:C,MATCH('Index Levels - Full'!$A7,'Index Levels'!$A:$A,0)),C6) -> 4077.9137
A8: =A7+1 -> 44292 | B8: =IFERROR(INDEX('Index Levels'!B:B,MATCH('Index Levels - Full'!$A8,'Index Levels'!$A:$A,0)),B7) -> 393.94143 | C8: =IFERROR(INDEX('Index Levels'!C:C,MATCH('Index Levels - Full'!$A8,'Index Levels'!$A:$A,0)),C7) -> 4073.9407
A9: =A8+1 -> 44293 | B9: =IFERROR(INDEX('Index Levels'!B:B,MATCH('Index Levels - Full'!$A9,'Index Levels'!$A:$A,0)),B8) -> 394.65722 | C9: =IFERROR(INDEX('Index Levels'!C:C,MATCH('Index Levels - Full'!$A9,'Index Levels'!$A:$A,0)),C8) -> 4079.9529
A10: =A9+1 -> 44294 | B10: =IFERROR(INDEX('Index Levels'!B:B,MATCH('Index Levels - Full'!$A10,'Index Levels'!$A:$A,0)),B9) -> 396.74971 | C10: =IFERROR(INDEX('Index Levels'!C:C,MATCH('Index Levels - Full'!$A10,'Index Levels'!$A:$A,0)),C9) -> 4097.168
A11: =A10+1 -> 44295 | B11: =IFERROR(INDEX('Index Levels'!B:B,MATCH('Index Levels - Full'!$A11,'Index Levels'!$A:$A,0)),B10) -> 400.63775 | C11: =IFERROR(INDEX('Index Levels'!C:C,MATCH('Index Levels - Full'!$A11,'Index Levels'!$A:$A,0)),C10) -> 4128.8021
A12: =A11+1 -> 44296 | B12: =IFERROR(INDEX('Index Levels'!B:B,MATCH('Index Levels - Full'!$A12,'Index Levels'!$A:$A,0)),B11) -> 400.63775 | C12: =IFERROR(INDEX('Index Levels'!C:C,MATCH('Index Levels - Full'!$A12,'Index Levels'!$A:$A,0)),C11) -> 4128.8021
A13: =A12+1 -> 44297 | B13: =IFERROR(INDEX('Index Levels'!B:B,MATCH('Index Levels - Full'!$A13,'Index Levels'!$A:$A,0)),B12) -> 400.63775 | C13: =IFERROR(INDEX('Index Levels'!C:C,MATCH('Index Levels - Full'!$A13,'Index Levels'!$A:$A,0)),C12) -> 4128.8021
A14: =A13+1 -> 44298 | B14: =IFERROR(INDEX('Index Levels'!B:B,MATCH('Index Levels - Full'!$A14,'Index Levels'!$A:$A,0)),B13) -> 400.97638 | C14: =IFERROR(INDEX('Index Levels'!C:C,MATCH('Index Levels - Full'!$A14,'Index Levels'!$A:$A,0)),C13) -> 4127.9932
... A1950: =A1949+1 -> 46234 | B1950: =IFERROR(INDEX('Index Levels'!B:B,MATCH('Index Levels - Full'!$A1950,'Index Levels'!$A:$A,0)),B1949) -> 491.03355 | C1950: =IFERROR(INDEX('Index Levels'!C:C,MATCH('Index Levels - Full'!$A1950,'Index Levels'!$A:$A,0)),C1949) -> 7489.7248

Sheet Index Levels
B1: SPXFCDUE | C1: 500
B2: S&P 500 FC TCA 0.50% Decrement Index (USD) ER | C2: S&P 500
A3: 44286 | B3: 385.28802 | C3: 3972.8922
A4: 44287 | B4: 388.70373 | C4: 4019.8654
A5: 44291 | B5: 394.86771 | C5: 4077.9137
A6: 44292 | B6: 393.94143 | C6: 4073.9407
A7: 44293 | B7: 394.65722 | C7: 4079.9529
A8: 44294 | B8: 396.74971 | C8: 4097.168
A9: 44295 | B9: 400.63775 | C9: 4128.8021
A10: 44298 | B10: 400.97638 | C10: 4127.9932
A11: 44299 | B11: 402.72682 | C11: 4141.5938
A12: 44300 | B12: 399.85127 | C12: 4124.6606
A13: 44301 | B13: 407.02548 | C13: 4170.4228
A14: 44302 | B14: 409.26459 | C14: 4185.4687
... A337: 44770 | B337: 390.57932 | C337: 4072.4343
A338: 44771 | B338: 394.25496 | C338: 4130.2858 | D338: =B338/B87-1 -> -0.051442398 | E338: =C338/C87-1 -> -0.060287209
A339: 44774 | B339: 393.3443 | C339: 4118.6296
A340: 44775 | B340: 391.87339 | C340: 4091.1851
A341: 44776 | B341: 396.05621 | C341: 4155.1727
A342: 44777 | B342: 395.35391 | C342: 4151.9442
A343: 44778 | B343: 395.03085 | C343: 4145.1891
A344: 44781 | B344: 394.61256 | C344: 4140.0584
A345: 44782 | B345: 393.34989 | C345: 4122.4659
A346: 44783 | B346: 399.71377 | C346: 4210.2405
A347: 44784 | B347: 400.53852 | C347: 4207.2744
A348: 44785 | B348: 404.69976 | C348: 4280.1505
A349: 44788 | B349: 405.96549 | C349: 4297.1435
A350: 44789 | B350: 406.64302 | C350: 4305.1993
... A360: 44803 | B360: 389.65225 | C360: 3986.1619
A361: 44804 | B361: 388.33303 | C361: 3954.999 | D361: =B361/B109-1 -> -0.096872845 | E361: =C361/C109-1 -> -0.12551874
A362: 44805 | B362: 387.00127 | C362: 3966.8503
A363: 44806 | B363: 383.4275 | C363: 3924.2596
A364: 44810 | B364: 382.64102 | C364: 3908.19
A365: 44811 | B365: 387.19672 | C365: 3979.8749
A366: 44812 | B366: 388.30794 | C366: 4006.1791
A367: 44813 | B367: 392.73005 | C367: 4067.3623
A368: 44816 | B368: 395.21697 | C368: 4110.4081
A369: 44817 | B369: 387.62553 | C369: 3932.6933
A370: 44818 | B370: 387.52175 | C370: 3946.0124
A371: 44819 | B371: 385.49859 | C371: 3901.3528
A372: 44820 | B372: 383.63019 | C372: 3873.3343
A373: 44823 | B373: 384.88171 | C373: 3899.8859
... A381: 44833 | B381: 370.61059 | C381: 3640.4681
A382: 44834 | B382: 368.5781 | C382: 3585.6241 | D382: =B382/B130-1 -> -0.083132281 | E382: =C382/C130-1 -> -0.1675933
A383: 44837 | B383: 372.54559 | C383: 3678.4288
A384: 44838 | B384: 378.74172 | C384: 3790.9289
A385: 44839 | B385: 377.54936 | C385: 3783.2814
A386: 44840 | B386: 376.12457 | C386: 3744.5198
A387: 44841 | B387: 372.73896 | C387: 3639.66
A388: 44844 | B388: 372.22232 | C388: 3612.3875
A389: 44845 | B389: 370.36459 | C389: 3588.8419
A390: 44846 | B390: 370.07308 | C390: 3577.0317
A391: 44847 | B391: 372.19204 | C391: 3669.9057
A392: 44848 | B392: 369.82495 | C392: 3583.0691
A393: 44851 | B393: 371.99606 | C393: 3677.9538
A394: 44852 | B394: 373.24604 | C394: 3719.9827
... A402: 44862 | B402: 383.5092 | C402: 3901.0638
A403: 44865 | B403: 381.12534 | C403: 3871.9772 | D403: =B403/B151-1 -> -0.10499456 | E403: =C403/C151-1 -> -0.15924852
A404: 44866 | B404: 380.2823 | C404: 3856.1018
A405: 44867 | B405: 374.8132 | C405: 3759.6905
A406: 44868 | B406: 372.40197 | C406: 3719.8933
A407: 44869 | B407: 373.5024 | C407: 3770.5464
A408: 44872 | B408: 375.24092 | C408: 3806.805
A409: 44873 | B409: 375.95672 | C409: 3828.1081
A410: 44874 | B410: 372.5249 | C410: 3748.5726
